Workbook
Name ProjectName: 'Project Info'!$C$3
Name ProjectState: 'Project Info'!$C$14
Name IsPrevailingWage: 'Project Info'!$C$15
Name SubMarkup: 'Project Info'!$C$18
Name SelfPerfOH: 'Project Info'!$C$19
Name SelfPerfProfit: 'Project Info'!$C$20
Name CorpOH: 'Project Info'!$C$21
Name CorpProfit: 'Project Info'!$C$22
Name BondPct: 'Project Info'!$C$25
Name SalesTax: 'Project Info'!$C$26
Name BuildersRisk: 'Project Info'!$C$27
Name TradeContingency: 'Project Info'!$C$30
Name ProjectContingency: 'Project Info'!$C$31
Name CSI_Divisions: 'CSI Reference'!$A$5:$A$39
Name CSI_Div_00: 'CSI Reference'!$D$5:$D$12
Name CSI_Div_01: 'CSI Reference'!$D$13:$D$21
Name CSI_Div_02: 'CSI Reference'!$D$22:$D$28
Name CSI_Div_03: 'CSI Reference'!$D$29:$D$36
Name CSI_Div_04: 'CSI Reference'!$D$37:$D$43
Name CSI_Div_05: 'CSI Reference'!$D$44:$D$49
Name CSI_Div_06: 'CSI Reference'!$D$50:$D$56
Name CSI_Div_07: 'CSI Reference'!$D$57:$D$65
Name CSI_Div_08: 'CSI Reference'!$D$66:$D$73
Name CSI_Div_09: 'CSI Reference'!$D$74:$D$80
Name CSI_Div_10: 'CSI Reference'!$D$81:$D$88
Name CSI_Div_11: 'CSI Reference'!$D$89:$D$96
Name CSI_Div_12: 'CSI Reference'!$D$97:$D$103
Name CSI_Div_13: 'CSI Reference'!$D$104:$D$108
Name CSI_Div_14: 'CSI Reference'!$D$109:$D$115
Name CSI_Div_21: 'CSI Reference'!$D$116:$D$119
Name CSI_Div_22: 'CSI Reference'!$D$120:$D$125
Name CSI_Div_23: 'CSI Reference'!$D$126:$D$133
Name CSI_Div_25: 'CSI Reference'!$D$134:$D$136
Name CSI_Div_26: 'CSI Reference'!$D$137:$D$141
Name CSI_Div_27: 'CSI Reference'!$D$142:$D$146
Name CSI_Div_28: 'CSI Reference'!$D$147:$D$151
Name CSI_Div_31: 'CSI Reference'!$D$152:$D$158
Name CSI_Div_32: 'CSI Reference'!$D$159:$D$163
Name CSI_Div_33: 'CSI Reference'!$D$164:$D$171
Name CSI_Div_34: 'CSI Reference'!$D$172:$D$176
Name CSI_Div_35: 'CSI Reference'!$D$177:$D$182
Name CSI_Div_40: 'CSI Reference'!$D$183:$D$186
Name CSI_Div_41: 'CSI Reference'!$D$187:$D$191
Name CSI_Div_42: 'CSI Reference'!$D$192:$D$194
Name CSI_Div_43: 'CSI Reference'!$D$195:$D$198
Name CSI_Div_44: 'CSI Reference'!$D$199:$D$202
Name CSI_Div_45: 'CSI Reference'!$D$203:$D$203
Name CSI_Div_46: 'CSI Reference'!$D$204:$D$210
Name CSI_Div_48: 'CSI Reference'!$D$211:$D$212

Sheet Instructions
A1: GC BID ESTIMATOR — Instructions
A3: WHAT THIS WORKBOOK IS
A4: Prime-contract bid roll-up for a General Contractor. Use to assemble subcontractor quotes by CSI division, layer General Conditions (Div 01), then apply overhead, profit, bond, and tax to land the final bid number you submit to the Owner.
A6: Unlike trade-specific bid estimators (Steel Erection, Electrical, etc.) which compute labor + material + equipment from scratch, the GC Estimator rolls up sub quotes you received from your trade partners. The detail estimating happens inside the trade-specific workbooks; this workbook is the consolidation layer.
A8: WORKFLOW
A9: 1. Project Info: project, owner, architect, delivery method, schedule, markup defaults.
A10: 2. Trade Bids: one row per CSI division. Enter the lowest qualifying sub quote per trade. Workbook computes GC markup on subs (typically 5-10%) plus optional contingency per trade.
A11: 3. Self-Perform: any work the GC self-performs (rare on true GC; common on design-build / CMAR). Enter as labor + material + equipment cost. Marked up with self-perform OH + profit.
A12: 4. General Conditions: Division 01 — supervision, project office, dumpsters, port-a-john, signage, site security, temporary utilities, etc. Itemized monthly/lump-sum.
A13: 5. Allowances & Contingencies: explicit allowances called out in the bid + project-level contingency.
A14: 6. Bid Summary: roll-up → corporate overhead + profit + payment-and-performance bond + sales tax → final bid number.
A16: MARKUP STRUCTURE (LOCK IT IN ONE WAY OR THE OTHER)
... A42: - Not a job-cost accounting system. Use Job_Costing_Spreadsheet.xlsx (Business tier) for that.

Sheet Project Info
B1: PROJECT INFORMATION — GC Bid
B3: Project Name
B4: Project Address
B5: Owner
B6: Architect
B7: Engineer (Structural / MEP)
B8: Bid Due Date
B9: Project Type | C9: Commercial — New Construction
B10: Delivery Method | C10: Design-Bid-Build
B11: Construction Schedule (months) | C11: 0
B12: Anticipated NTP Date
B13: Anticipated Substantial Completion
B14: Project State (sales-tax rule)
B15: Davis-Bacon / Prevailing Wage? | C15: No
B17: MARKUP CONVENTION (SEE INSTRUCTIONS — PICK ONE)
B18: Sub Markup % (per-trade line-level) | C18: 0.07
B19: Self-Perform OH % | C19: 0.1
B20: Self-Perform Profit % | C20: 0.08
B21: Corporate / Summary OH % | C21: 0
B22: Corporate / Summary Profit % | C22: 0
B24: BOND, INSURANCE, TAX
B25: P&P Bond % | C25: 0.01
B26: Sales Tax on Materials % | C26: 0.07
B27: Builder's Risk in bid? (Owner usually supplies) | C27: No
B29: CONTINGENCY
B30: Per-Trade Contingency Default % | C30: 0.02
B31: Project-Level Contingency % | C31: 0.03
B33: BIDDER OF RECORD
B34: Lead Estimator
B35: Project Executive
B36: Authorized Signatory

Sheet Trade Bids
A1: TRADE BIDS — Subcontractor Quote Roll-Up
A2: One row per CSI division. Enter the lowest qualifying sub quote per trade. The GC Markup column defaults to the SubMarkup named range (set on Project Info — default 7%); override per trade for thin-margin or high-risk scopes. Line Total = SubQuote × (1 + Markup) × (1 + Contingency).
A4: CSI Div | B4: Trade Name | C4: Sub (low qualifying bidder) | D4: Quote Date | E4: Sub Quote ($) | F4: Quote Includes Bond? | G4: Quote Includes Sales Tax? | H4: GC Markup % | I4: Per-Trade Contingency % | J4: Line Total ($) | K4: Notes / Exclusions | L4: CSI Subdivision
A5: 01 | B5: General Requirements | H5: =SubMarkup | I5: =TradeContingency | J5: =IFERROR(E5*(1+H5)*(1+I5),0)
A6: 02 | B6: Existing Conditions | H6: =SubMarkup | I6: =TradeContingency | J6: =IFERROR(E6*(1+H6)*(1+I6),0)
A7: 03 | B7: Concrete | H7: =SubMarkup | I7: =TradeContingency | J7: =IFERROR(E7*(1+H7)*(1+I7),0)
A8: 04 | B8: Masonry | H8: =SubMarkup | I8: =TradeContingency | J8: =IFERROR(E8*(1+H8)*(1+I8),0)
A9: 05 | B9: Metals | H9: =SubMarkup | I9: =TradeContingency | J9: =IFERROR(E9*(1+H9)*(1+I9),0)
A10: 06 | B10: Wood, Plastics, and Composites | H10: =SubMarkup | I10: =TradeContingency | J10: =IFERROR(E10*(1+H10)*(1+I10),0)
A11: 07 | B11: Thermal and Moisture Protection | H11: =SubMarkup | I11: =TradeContingency | J11: =IFERROR(E11*(1+H11)*(1+I11),0)
A12: 08 | B12: Openings | H12: =SubMarkup | I12: =TradeContingency | J12: =IFERROR(E12*(1+H12)*(1+I12),0)
A13: 09 | B13: Finishes | H13: =SubMarkup | I13: =TradeContingency | J13: =IFERROR(E13*(1+H13)*(1+I13),0)
A14: 10 | B14: Specialties | H14: =SubMarkup | I14: =TradeContingency | J14: =IFERROR(E14*(1+H14)*(1+I14),0)
A15: 11 | B15: Equipment | H15: =SubMarkup | I15: =TradeContingency | J15: =IFERROR(E15*(1+H15)*(1+I15),0)
A16: 12 | B16: Furnishings | H16: =SubMarkup | I16: =TradeContingency | J16: =IFERROR(E16*(1+H16)*(1+I16),0)
... A30: 35 | B30: Waterway and Marine Construction | H30: =SubMarkup | I30: =TradeContingency | J30: =IFERROR(E30*(1+H30)*(1+I30),0)
B31: TRADE BIDS TOTAL | E31: =SUM(E5:E30) | J31: =SUM(J5:J30)

Sheet Self-Perform
A1: SELF-PERFORM WORK — GC Crew
A2: Work the GC self-performs with its own crews (rare on true GC; common on Design-Build / CM-at-Risk). Common self-perform scopes: site work, concrete, carpentry, general labor, demolition. Direct Cost auto-sums Labor+Material+Equipment; Line Total applies SelfPerfOH + SelfPerfProfit defaults.
A4: CSI Div | B4: Activity | C4: Labor Cost ($) | D4: Material Cost ($) | E4: Equipment Cost ($) | F4: Direct Cost ($) | G4: OH % | H4: Profit % | I4: Line Total ($) | J4: Notes
A5: 01 | B5: Project Supervision (allocated) | F5: =IFERROR(SUM(C5:E5),0) | G5: =SelfPerfOH | H5: =SelfPerfProfit | I5: =IFERROR(F5*(1+G5)*(1+H5),0)
A6: 02 | B6: Demolition | F6: =IFERROR(SUM(C6:E6),0) | G6: =SelfPerfOH | H6: =SelfPerfProfit | I6: =IFERROR(F6*(1+G6)*(1+H6),0)
A7: 03 | B7: Concrete — flatwork | F7: =IFERROR(SUM(C7:E7),0) | G7: =SelfPerfOH | H7: =SelfPerfProfit | I7: =IFERROR(F7*(1+G7)*(1+H7),0)
A8: 06 | B8: Rough carpentry | F8: =IFERROR(SUM(C8:E8),0) | G8: =SelfPerfOH | H8: =SelfPerfProfit | I8: =IFERROR(F8*(1+G8)*(1+H8),0)
A9: 31 | B9: Site work / earthwork | F9: =IFERROR(SUM(C9:E9),0) | G9: =SelfPerfOH | H9: =SelfPerfProfit | I9: =IFERROR(F9*(1+G9)*(1+H9),0)
F10: =IFERROR(SUM(C10:E10),0) | G10: =SelfPerfOH | H10: =SelfPerfProfit | I10: =IFERROR(F10*(1+G10)*(1+H10),0)
F11: =IFERROR(SUM(C11:E11),0) | G11: =SelfPerfOH | H11: =SelfPerfProfit | I11: =IFERROR(F11*(1+G11)*(1+H11),0)
F12: =IFERROR(SUM(C12:E12),0) | G12: =SelfPerfOH | H12: =SelfPerfProfit | I12: =IFERROR(F12*(1+G12)*(1+H12),0)
B13: SELF-PERFORM TOTAL | F13: =SUM(F5:F12) | I13: =SUM(I5:I12)

Sheet General Conditions
A1: GENERAL CONDITIONS — Division 01
A2: Division 01 line items not part of any sub trade. Basis column drives the math: MONTHLY = Qty × Unit × Duration, LUMP = Qty × Unit, PER-SF = Qty × Unit (where Qty = project SF). Typically 5-10% of trade-cost subtotal on commercial work.
A4: Category | B4: Item | C4: Basis | D4: Quantity | E4: Unit Cost ($) | F4: Duration (months) | G4: Line Total ($) | H4: Notes | I4: CSI Div | J4: CSI Subdivision
A5: Supervision | B5: Project Manager (on-site allocation) | C5: MONTHLY | D5: 1 | E5: 0 | F5: 0 | G5: =IFERROR(IF(C5="MONTHLY",D5*E5*F5,D5*E5),0)
A6: Supervision | B6: Superintendent | C6: MONTHLY | D6: 1 | E6: 0 | F6: 0 | G6: =IFERROR(IF(C6="MONTHLY",D6*E6*F6,D6*E6),0)
A7: Supervision | B7: Assistant Superintendent | C7: MONTHLY | D7: 0 | E7: 0 | F7: 0 | G7: =IFERROR(IF(C7="MONTHLY",D7*E7*F7,D7*E7),0)
A8: Supervision | B8: Project Engineer | C8: MONTHLY | D8: 0 | E8: 0 | F8: 0 | G8: =IFERROR(IF(C8="MONTHLY",D8*E8*F8,D8*E8),0)
A9: Supervision | B9: Safety Officer | C9: MONTHLY | D9: 0 | E9: 0 | F9: 0 | G9: =IFERROR(IF(C9="MONTHLY",D9*E9*F9,D9*E9),0)
A10: Field Office | B10: Trailer rental | C10: MONTHLY | D10: 1 | E10: 0 | F10: 0 | G10: =IFERROR(IF(C10="MONTHLY",D10*E10*F10,D10*E10),0)
A11: Field Office | B11: Trailer set-up + tear-down | C11: LUMP | D11: 1 | E11: 0 | F11: 0 | G11: =IFERROR(IF(C11="MONTHLY",D11*E11*F11,D11*E11),0)
A12: Field Office | B12: Power / utilities to trailer | C12: MONTHLY | D12: 1 | E12: 0 | F12: 0 | G12: =IFERROR(IF(C12="MONTHLY",D12*E12*F12,D12*E12),0)
A13: Field Office | B13: Phone / internet | C13: MONTHLY | D13: 1 | E13: 0 | F13: 0 | G13: =IFERROR(IF(C13="MONTHLY",D13*E13*F13,D13*E13),0)
A14: Field Office | B14: Office supplies + copies | C14: MONTHLY | D14: 1 | E14: 0 | F14: 0 | G14: =IFERROR(IF(C14="MONTHLY",D14*E14*F14,D14*E14),0)
A15: Site Facilities | B15: Port-a-John (per unit per month) | C15: MONTHLY | D15: 1 | E15: 0 | F15: 0 | G15: =IFERROR(IF(C15="MONTHLY",D15*E15*F15,D15*E15),0)
A16: Site Facilities | B16: Dumpsters (rolling) | C16: MONTHLY | D16: 1 | E16: 0 | F16: 0 | G16: =IFERROR(IF(C16="MONTHLY",D16*E16*F16,D16*E16),0)
... A35: Office OH | B35: Permit + inspection fees (allowance) | C35: LUMP | D35: 1 | E35: 0 | F35: 0 | G35: =IFERROR(IF(C35="MONTHLY",D35*E35*F35,D35*E35),0)
D36: 0 | E36: 0 | F36: 0 | G36: =IFERROR(IF(C36="MONTHLY",D36*E36*F36,D36*E36),0)
D37: 0 | E37: 0 | F37: 0 | G37: =IFERROR(IF(C37="MONTHLY",D37*E37*F37,D37*E37),0)
B38: GENERAL CONDITIONS TOTAL | G38: =SUM(G5:G37)

Sheet Allowances
A1: ALLOWANCES & CONTINGENCIES
A2: Explicit allowances (called out in the bid for Owner-directed scope where price isn't yet defined) plus project-level contingency. Per-trade contingency is on the Trade Bids tab.
A4: Type | B4: Description | C4: Amount ($) | D4: Basis / Notes
A5: Allowance | B5: Finish hardware (Owner specifying TBD) | C5: 0 | D5: Owner selects from approved list
A6: Allowance | B6: Appliances (Owner specifying TBD) | C6: 0 | D6: Owner-directed late selection
A7: Allowance | B7: Specialty doors / glazing (TBD design) | C7: 0 | D7: Pending design refinement
A8: Allowance | B8: Paint color selection (TBD) | C8: 0 | D8: Color premium if non-standard
A9: Allowance | B9: Landscaping allowance | C9: 0 | D9: Owner-selected design
A10: Allowance | B10: Permit + inspection fees actual | C10: 0 | D10: If actuals exceed Div 01 allowance
C11: 0
A12: Contingency | B12: Project-level contingency (unknowns) | C12: 0 | D12: =CostOfWork × ProjectContingency
C13: 0
C14: 0
B15: ALLOWANCES + CONTINGENCY TOTAL | C15: =SUM(C5:C14)

Sheet Bid Summary
B1: BID SUMMARY — Roll-Up to Final Prime Bid
B2: Project: =ProjectName
B4: COST OF WORK
B5: Trade Bids (from Trade Bids tab) | C5: ='Trade Bids'!J31
B6: Self-Perform (from Self-Perform tab) | C6: ='Self-Perform'!I13
B7: General Conditions (Div 01) | C7: ='General Conditions'!G38
B8: Allowances + Contingency | C8: ='Allowances'!C15
B9: COST OF WORK SUBTOTAL | C9: =SUM(C5:C8)
B11: Corporate Overhead | C11: =C9*CorpOH | D11: =CorpOH
B12: Corporate Profit | C12: =C9*CorpProfit | D12: =CorpProfit
B13: Sales Tax (on est. material content) | C13: =C9*0.5*SalesTax | D13: =SalesTax | E13: Material is ~50% of trade cost — adjust per project
B14: PRE-BOND SUBTOTAL | C14: =C9+C11+C12+C13
B15: Performance + Payment Bond | C15: =C14*BondPct/(1-BondPct) | D15: =BondPct
B17: FINAL PRIME BID | C17: =C14+C15
B20: SANITY CHECKS
B21: Trade % of total bid (sanity: 75-90% commercial) | C21: =IFERROR('Trade Bids'!J31/C17,0)
B22: Gen Conditions % of trade total (sanity: 5-12%) | C22: =IFERROR('General Conditions'!G38/'Trade Bids'!J31,0)
B23: Self-Perform % of total (varies — 0% true GC, 20-40% CMAR) | C23: =IFERROR('Self-Perform'!I13/C17,0)
B24: Allowance % of total (sanity: typically <5%) | C24: =IFERROR('Allowances'!C15/C17,0)
B25: Effective markup over Cost of Work | C25: =IFERROR((C17-C9)/C9,0)

Sheet CSI Reference
A1: CSI MasterFormat 2020 — Divisions and Subdivisions
A2: Reference data for the bid + log workbooks. Do not delete columns A, B, D, or E — the dropdowns in the other tabs source from these named ranges.
A4: Div Code | B4: Division Title | D4: Subdiv Code | E4: Subdivision Title (parent division shown in col C)
A5: 00 | B5: Procurement and Contracting Requirements | C5: 00 | D5: 00 10 00 | E5: Solicitation
A6: 01 | B6: General Requirements | C6: 00 | D6: 00 20 00 | E6: Instructions for Procurement
A7: 02 | B7: Existing Conditions | C7: 00 | D7: 00 30 00 | E7: Available Information
A8: 03 | B8: Concrete | C8: 00 | D8: 00 40 00 | E8: Procurement Forms and Supplements
A9: 04 | B9: Masonry | C9: 00 | D9: 00 50 00 | E9: Contracting Forms and Supplements
A10: 05 | B10: Metals | C10: 00 | D10: 00 60 00 | E10: Project Forms
A11: 06 | B11: Wood, Plastics, and Composites | C11: 00 | D11: 00 70 00 | E11: Conditions of the Contract
A12: 07 | B12: Thermal and Moisture Protection | C12: 00 | D12: 00 80 00 | E12: Revisions, Clarifications, and Modifications
A13: 08 | B13: Openings | C13: 01 | D13: 01 10 00 | E13: Summary
A14: 09 | B14: Finishes | C14: 01 | D14: 01 20 00 | E14: Price and Payment Procedures
A15: 10 | B15: Specialties | C15: 01 | D15: 01 30 00 | E15: Administrative Requirements
A16: 11 | B16: Equipment | C16: 01 | D16: 01 40 00 | E16: Quality Requirements
... A39: 48 | B39: Electrical Power Generation | C39: 04 | D39: 04 20 00 | E39: Unit Masonry
C40: 04 | D40: 04 40 00 | E40: Stone Assemblies
C41: 04 | D41: 04 50 00 | E41: Refractory Masonry
C42: 04 | D42: 04 60 00 | E42: Corrosion-Resistant Masonry
C43: 04 | D43: 04 70 00 | E43: Manufactured Masonry
C44: 05 | D44: 05 10 00 | E44: Structural Metal Framing
C45: 05 | D45: 05 20 00 | E45: Metal Joists
C46: 05 | D46: 05 30 00 | E46: Metal Decking
C47: 05 | D47: 05 40 00 | E47: Cold-Formed Metal Framing
C48: 05 | D48: 05 50 00 | E48: Metal Fabrications
C49: 05 | D49: 05 70 00 | E49: Decorative Metal
C50: 06 | D50: 06 10 00 | E50: Rough Carpentry
C51: 06 | D51: 06 20 00 | E51: Finish Carpentry
... C212: 48 | D212: 48 70 00 | E212: Electrical Power Generation Testing
