Workbook
Name ProjectName: 'Project Info'!$C$3
Name PrimeContractNo: 'Project Info'!$C$6
Name SubName: 'Project Info'!$C$8
Name PayrollNo: 'Project Info'!$C$18
Name WeekEnding: 'Project Info'!$C$19
Name SignatoryName: 'Project Info'!$C$20
Name SignatoryTitle: 'Project Info'!$C$21
Name WDTable: 'Wage Determination'!$A$5:$H$29

Sheet Instructions
A1: CERTIFIED PAYROLL TRACKER — Instructions
A3: WHAT THIS WORKBOOK IS
A4: A WH-347-mirror workbook for weekly certified payroll on federal Davis-Bacon and state prevailing-wage projects. The printable Weekly Payroll tab matches the column structure of WH-347 so the sheet can be submitted as the certified payroll OR cross-checked against your accounting system's WH-347 export.
A6: USAGE — ONE-TIME SETUP
A7: 1. Project Info: project name, GC, prime contract number, WD identifying number, sub's PM, Statement-of-Compliance signatory.
A8: 2. Wage Determination: one row per classification used on this project. Enter the WD Rate (base) and WD Fringe per hour; the workbook will compute OT rate and total hourly cost.
A9: 3. Workers Master: one row per worker — name, employee ID, classification (validated against the Wage Determination), and any apprenticeship/training program data.
A11: USAGE — WEEKLY
A12: 1. At the end of each workweek, populate the Weekly Payroll tab.
A13: 2. Each row = one worker. Enter daily hours (ST and OT columns for each day Sun-Sat) and the workbook calculates total hours, gross pay, fringe owed, and net wage.
A14: 3. Verify the totals against your payroll software.
A15: 4. Print the Weekly Payroll tab plus the Statement of Compliance tab for the period.
... A36: Davis-Bacon audits are random; state audits are sometimes triggered by employee complaint or by an interested party (union, competing bidder). USDOL audits typically look back 3 years. Keep this workbook plus the underlying timecards, payroll records, deduction authorizations, fringe-plan contribution records, and apprenticeship registrations together.

Sheet Project Info
B1: CERTIFIED PAYROLL PROJECT INFORMATION
B3: Project Name
B4: Project Address
B5: GC
B6: Prime Contract No.
B7: Subcontract No.
B8: Subcontractor (legal name)
B9: Sub Address
B10: Sub FEIN
B11: Federal Davis-Bacon? (Yes / No) | C11: Yes
B12: State Prevailing Wage? (Yes / No) | C12: No
B13: State (if state PW applies)
B14: Wage Determination ID
B15: WD Effective Date
B16: WD Modification No.
B17: Construction Type (Bldg / Hwy / Heavy / Res) | C17: Building
B18: Payroll No. (sequential) | C18: 1
B19: For Week Ending (Saturday)
B20: Statement Signatory (officer name)
B21: Signatory Title
B22: Sub's PM

Sheet Wage Determination
A1: WAGE DETERMINATION — Classifications
A2: Enter one row per classification used on this project. WD Rate + WD Fringe is the floor; Cash + Plan Fringe must equal at least WD Fringe.
A4: Classification | B4: WD Base Rate ($/hr) | C4: WD Fringe ($/hr) | D4: Cash Fringe ($/hr) | E4: Plan Fringe ($/hr) | F4: OT Multiplier | G4: ST Hourly Cost (Base+Fringe) | H4: OT Hourly Cost | I4: Apprenticeable? | J4: Notes
F5: 1.5 | G5: =IF(B5="","",B5+IFERROR(D5,0)+IFERROR(E5,0)) | H5: =IF(B5="","",(B5*F5)+IFERROR(D5,0)+IFERROR(E5,0))
F6: 1.5 | G6: =IF(B6="","",B6+IFERROR(D6,0)+IFERROR(E6,0)) | H6: =IF(B6="","",(B6*F6)+IFERROR(D6,0)+IFERROR(E6,0))
F7: 1.5 | G7: =IF(B7="","",B7+IFERROR(D7,0)+IFERROR(E7,0)) | H7: =IF(B7="","",(B7*F7)+IFERROR(D7,0)+IFERROR(E7,0))
F8: 1.5 | G8: =IF(B8="","",B8+IFERROR(D8,0)+IFERROR(E8,0)) | H8: =IF(B8="","",(B8*F8)+IFERROR(D8,0)+IFERROR(E8,0))
F9: 1.5 | G9: =IF(B9="","",B9+IFERROR(D9,0)+IFERROR(E9,0)) | H9: =IF(B9="","",(B9*F9)+IFERROR(D9,0)+IFERROR(E9,0))
F10: 1.5 | G10: =IF(B10="","",B10+IFERROR(D10,0)+IFERROR(E10,0)) | H10: =IF(B10="","",(B10*F10)+IFERROR(D10,0)+IFERROR(E10,0))
F11: 1.5 | G11: =IF(B11="","",B11+IFERROR(D11,0)+IFERROR(E11,0)) | H11: =IF(B11="","",(B11*F11)+IFERROR(D11,0)+IFERROR(E11,0))
F12: 1.5 | G12: =IF(B12="","",B12+IFERROR(D12,0)+IFERROR(E12,0)) | H12: =IF(B12="","",(B12*F12)+IFERROR(D12,0)+IFERROR(E12,0))
F13: 1.5 | G13: =IF(B13="","",B13+IFERROR(D13,0)+IFERROR(E13,0)) | H13: =IF(B13="","",(B13*F13)+IFERROR(D13,0)+IFERROR(E13,0))
F14: 1.5 | G14: =IF(B14="","",B14+IFERROR(D14,0)+IFERROR(E14,0)) | H14: =IF(B14="","",(B14*F14)+IFERROR(D14,0)+IFERROR(E14,0))
F15: 1.5 | G15: =IF(B15="","",B15+IFERROR(D15,0)+IFERROR(E15,0)) | H15: =IF(B15="","",(B15*F15)+IFERROR(D15,0)+IFERROR(E15,0))
F16: 1.5 | G16: =IF(B16="","",B16+IFERROR(D16,0)+IFERROR(E16,0)) | H16: =IF(B16="","",(B16*F16)+IFERROR(D16,0)+IFERROR(E16,0))
... F29: 1.5 | G29: =IF(B29="","",B29+IFERROR(D29,0)+IFERROR(E29,0)) | H29: =IF(B29="","",(B29*F29)+IFERROR(D29,0)+IFERROR(E29,0))

Sheet Workers Master
A1: WORKERS MASTER
A3: Worker Name | B3: Employee ID | C3: Classification | D3: Apprentice? | E3: Apprenticeship Reg No. | F3: Apprentice Year/Period | G3: Apprentice % of Journeyman | H3: Hire Date | I3: Status | J3: Notes

Sheet Weekly Payroll
A1: WEEKLY CERTIFIED PAYROLL — WH-347 Style
A2: Project: | B2: =ProjectName | F2: Payroll #: | G2: =PayrollNo | H2: Week Ending: | I2: =WeekEnding | J2: Subcontractor: | K2: =SubName | O2: Prime Contract: | P2: =PrimeContractNo
A4: # | B4: Worker Name | C4: Emp ID | D4: Classification | E4: Sun | F4: Mon | G4: Tue | H4: Wed | I4: Thu | J4: Fri | K4: Sat | L4: Total ST | M4: Total OT | N4: ST Rate | O4: OT Rate | P4: ST Gross | Q4: OT Gross | R4: Fringe (Cash) | S4: Total Gross | T4: Deductions | U4: Net Wages | V4: Notes
E5: ST | OT | F5: ST | OT | G5: ST | OT | H5: ST | OT | I5: ST | OT | J5: ST | OT | K5: ST | OT
A6: =IF(B6="","",ROW()-5) | L6: =SUM(E6:K6) | N6: =IFERROR((VLOOKUP(D6,WDTable,2,FALSE)*IFERROR(VLOOKUP(B6,'Workers Master'!A:G,7,FALSE),1))+VLOOKUP(D6,WDTable,4,FALSE),"") | O6: =IFERROR((VLOOKUP(D6,WDTable,2,FALSE)*IFERROR(VLOOKUP(B6,'Workers Master'!A:G,7,FALSE),1)*VLOOKUP(D6,WDTable,6,FALSE))+VLOOKUP(D6,WDTable,4,FALSE),"") | P6: =IF(N6="","",L6*N6) | Q6: =IF(O6="","",M6*O6) | R6: =IFERROR(VLOOKUP(D6,WDTable,5,FALSE)*(L6+M6),"") | S6: =IF(P6="","",IFERROR(P6,0)+IFERROR(Q6,0)) | U6: =IF(S6="","",IFERROR(S6,0)-IFERROR(T6,0))
A7: =IF(B7="","",ROW()-5) | L7: =SUM(E7:K7) | N7: =IFERROR((VLOOKUP(D7,WDTable,2,FALSE)*IFERROR(VLOOKUP(B7,'Workers Master'!A:G,7,FALSE),1))+VLOOKUP(D7,WDTable,4,FALSE),"") | O7: =IFERROR((VLOOKUP(D7,WDTable,2,FALSE)*IFERROR(VLOOKUP(B7,'Workers Master'!A:G,7,FALSE),1)*VLOOKUP(D7,WDTable,6,FALSE))+VLOOKUP(D7,WDTable,4,FALSE),"") | P7: =IF(N7="","",L7*N7) | Q7: =IF(O7="","",M7*O7) | R7: =IFERROR(VLOOKUP(D7,WDTable,5,FALSE)*(L7+M7),"") | S7: =IF(P7="","",IFERROR(P7,0)+IFERROR(Q7,0)) | U7: =IF(S7="","",IFERROR(S7,0)-IFERROR(T7,0))
A8: =IF(B8="","",ROW()-5) | L8: =SUM(E8:K8) | N8: =IFERROR((VLOOKUP(D8,WDTable,2,FALSE)*IFERROR(VLOOKUP(B8,'Workers Master'!A:G,7,FALSE),1))+VLOOKUP(D8,WDTable,4,FALSE),"") | O8: =IFERROR((VLOOKUP(D8,WDTable,2,FALSE)*IFERROR(VLOOKUP(B8,'Workers Master'!A:G,7,FALSE),1)*VLOOKUP(D8,WDTable,6,FALSE))+VLOOKUP(D8,WDTable,4,FALSE),"") | P8: =IF(N8="","",L8*N8) | Q8: =IF(O8="","",M8*O8) | R8: =IFERROR(VLOOKUP(D8,WDTable,5,FALSE)*(L8+M8),"") | S8: =IF(P8="","",IFERROR(P8,0)+IFERROR(Q8,0)) | U8: =IF(S8="","",IFERROR(S8,0)-IFERROR(T8,0))
A9: =IF(B9="","",ROW()-5) | L9: =SUM(E9:K9) | N9: =IFERROR((VLOOKUP(D9,WDTable,2,FALSE)*IFERROR(VLOOKUP(B9,'Workers Master'!A:G,7,FALSE),1))+VLOOKUP(D9,WDTable,4,FALSE),"") | O9: =IFERROR((VLOOKUP(D9,WDTable,2,FALSE)*IFERROR(VLOOKUP(B9,'Workers Master'!A:G,7,FALSE),1)*VLOOKUP(D9,WDTable,6,FALSE))+VLOOKUP(D9,WDTable,4,FALSE),"") | P9: =IF(N9="","",L9*N9) | Q9: =IF(O9="","",M9*O9) | R9: =IFERROR(VLOOKUP(D9,WDTable,5,FALSE)*(L9+M9),"") | S9: =IF(P9="","",IFERROR(P9,0)+IFERROR(Q9,0)) | U9: =IF(S9="","",IFERROR(S9,0)-IFERROR(T9,0))
A10: =IF(B10="","",ROW()-5) | L10: =SUM(E10:K10) | N10: =IFERROR((VLOOKUP(D10,WDTable,2,FALSE)*IFERROR(VLOOKUP(B10,'Workers Master'!A:G,7,FALSE),1))+VLOOKUP(D10,WDTable,4,FALSE),"") | O10: =IFERROR((VLOOKUP(D10,WDTable,2,FALSE)*IFERROR(VLOOKUP(B10,'Workers Master'!A:G,7,FALSE),1)*VLOOKUP(D10,WDTable,6,FALSE))+VLOOKUP(D10,WDTable,4,FALSE),"") | P10: =IF(N10="","",L10*N10) | Q10: =IF(O10="","",M10*O10) | R10: =IFERROR(VLOOKUP(D10,WDTable,5,FALSE)*(L10+M10),"") | S10: =IF(P10="","",IFERROR(P10,0)+IFERROR(Q10,0)) | U10: =IF(S10="","",IFERROR(S10,0)-IFERROR(T10,0))
A11: =IF(B11="","",ROW()-5) | L11: =SUM(E11:K11) | N11: =IFERROR((VLOOKUP(D11,WDTable,2,FALSE)*IFERROR(VLOOKUP(B11,'Workers Master'!A:G,7,FALSE),1))+VLOOKUP(D11,WDTable,4,FALSE),"") | O11: =IFERROR((VLOOKUP(D11,WDTable,2,FALSE)*IFERROR(VLOOKUP(B11,'Workers Master'!A:G,7,FALSE),1)*VLOOKUP(D11,WDTable,6,FALSE))+VLOOKUP(D11,WDTable,4,FALSE),"") | P11: =IF(N11="","",L11*N11) | Q11: =IF(O11="","",M11*O11) | R11: =IFERROR(VLOOKUP(D11,WDTable,5,FALSE)*(L11+M11),"") | S11: =IF(P11="","",IFERROR(P11,0)+IFERROR(Q11,0)) | U11: =IF(S11="","",IFERROR(S11,0)-IFERROR(T11,0))
A12: =IF(B12="","",ROW()-5) | L12: =SUM(E12:K12) | N12: =IFERROR((VLOOKUP(D12,WDTable,2,FALSE)*IFERROR(VLOOKUP(B12,'Workers Master'!A:G,7,FALSE),1))+VLOOKUP(D12,WDTable,4,FALSE),"") | O12: =IFERROR((VLOOKUP(D12,WDTable,2,FALSE)*IFERROR(VLOOKUP(B12,'Workers Master'!A:G,7,FALSE),1)*VLOOKUP(D12,WDTable,6,FALSE))+VLOOKUP(D12,WDTable,4,FALSE),"") | P12: =IF(N12="","",L12*N12) | Q12: =IF(O12="","",M12*O12) | R12: =IFERROR(VLOOKUP(D12,WDTable,5,FALSE)*(L12+M12),"") | S12: =IF(P12="","",IFERROR(P12,0)+IFERROR(Q12,0)) | U12: =IF(S12="","",IFERROR(S12,0)-IFERROR(T12,0))
A13: =IF(B13="","",ROW()-5) | L13: =SUM(E13:K13) | N13: =IFERROR((VLOOKUP(D13,WDTable,2,FALSE)*IFERROR(VLOOKUP(B13,'Workers Master'!A:G,7,FALSE),1))+VLOOKUP(D13,WDTable,4,FALSE),"") | O13: =IFERROR((VLOOKUP(D13,WDTable,2,FALSE)*IFERROR(VLOOKUP(B13,'Workers Master'!A:G,7,FALSE),1)*VLOOKUP(D13,WDTable,6,FALSE))+VLOOKUP(D13,WDTable,4,FALSE),"") | P13: =IF(N13="","",L13*N13) | Q13: =IF(O13="","",M13*O13) | R13: =IFERROR(VLOOKUP(D13,WDTable,5,FALSE)*(L13+M13),"") | S13: =IF(P13="","",IFERROR(P13,0)+IFERROR(Q13,0)) | U13: =IF(S13="","",IFERROR(S13,0)-IFERROR(T13,0))
A14: =IF(B14="","",ROW()-5) | L14: =SUM(E14:K14) | N14: =IFERROR((VLOOKUP(D14,WDTable,2,FALSE)*IFERROR(VLOOKUP(B14,'Workers Master'!A:G,7,FALSE),1))+VLOOKUP(D14,WDTable,4,FALSE),"") | O14: =IFERROR((VLOOKUP(D14,WDTable,2,FALSE)*IFERROR(VLOOKUP(B14,'Workers Master'!A:G,7,FALSE),1)*VLOOKUP(D14,WDTable,6,FALSE))+VLOOKUP(D14,WDTable,4,FALSE),"") | P14: =IF(N14="","",L14*N14) | Q14: =IF(O14="","",M14*O14) | R14: =IFERROR(VLOOKUP(D14,WDTable,5,FALSE)*(L14+M14),"") | S14: =IF(P14="","",IFERROR(P14,0)+IFERROR(Q14,0)) | U14: =IF(S14="","",IFERROR(S14,0)-IFERROR(T14,0))
A15: =IF(B15="","",ROW()-5) | L15: =SUM(E15:K15) | N15: =IFERROR((VLOOKUP(D15,WDTable,2,FALSE)*IFERROR(VLOOKUP(B15,'Workers Master'!A:G,7,FALSE),1))+VLOOKUP(D15,WDTable,4,FALSE),"") | O15: =IFERROR((VLOOKUP(D15,WDTable,2,FALSE)*IFERROR(VLOOKUP(B15,'Workers Master'!A:G,7,FALSE),1)*VLOOKUP(D15,WDTable,6,FALSE))+VLOOKUP(D15,WDTable,4,FALSE),"") | P15: =IF(N15="","",L15*N15) | Q15: =IF(O15="","",M15*O15) | R15: =IFERROR(VLOOKUP(D15,WDTable,5,FALSE)*(L15+M15),"") | S15: =IF(P15="","",IFERROR(P15,0)+IFERROR(Q15,0)) | U15: =IF(S15="","",IFERROR(S15,0)-IFERROR(T15,0))
A16: =IF(B16="","",ROW()-5) | L16: =SUM(E16:K16) | N16: =IFERROR((VLOOKUP(D16,WDTable,2,FALSE)*IFERROR(VLOOKUP(B16,'Workers Master'!A:G,7,FALSE),1))+VLOOKUP(D16,WDTable,4,FALSE),"") | O16: =IFERROR((VLOOKUP(D16,WDTable,2,FALSE)*IFERROR(VLOOKUP(B16,'Workers Master'!A:G,7,FALSE),1)*VLOOKUP(D16,WDTable,6,FALSE))+VLOOKUP(D16,WDTable,4,FALSE),"") | P16: =IF(N16="","",L16*N16) | Q16: =IF(O16="","",M16*O16) | R16: =IFERROR(VLOOKUP(D16,WDTable,5,FALSE)*(L16+M16),"") | S16: =IF(P16="","",IFERROR(P16,0)+IFERROR(Q16,0)) | U16: =IF(S16="","",IFERROR(S16,0)-IFERROR(T16,0))
A17: =IF(B17="","",ROW()-5) | L17: =SUM(E17:K17) | N17: =IFERROR((VLOOKUP(D17,WDTable,2,FALSE)*IFERROR(VLOOKUP(B17,'Workers Master'!A:G,7,FALSE),1))+VLOOKUP(D17,WDTable,4,FALSE),"") | O17: =IFERROR((VLOOKUP(D17,WDTable,2,FALSE)*IFERROR(VLOOKUP(B17,'Workers Master'!A:G,7,FALSE),1)*VLOOKUP(D17,WDTable,6,FALSE))+VLOOKUP(D17,WDTable,4,FALSE),"") | P17: =IF(N17="","",L17*N17) | Q17: =IF(O17="","",M17*O17) | R17: =IFERROR(VLOOKUP(D17,WDTable,5,FALSE)*(L17+M17),"") | S17: =IF(P17="","",IFERROR(P17,0)+IFERROR(Q17,0)) | U17: =IF(S17="","",IFERROR(S17,0)-IFERROR(T17,0))
... A35: =IF(B35="","",ROW()-5) | L35: =SUM(E35:K35) | N35: =IFERROR((VLOOKUP(D35,WDTable,2,FALSE)*IFERROR(VLOOKUP(B35,'Workers Master'!A:G,7,FALSE),1))+VLOOKUP(D35,WDTable,4,FALSE),"") | O35: =IFERROR((VLOOKUP(D35,WDTable,2,FALSE)*IFERROR(VLOOKUP(B35,'Workers Master'!A:G,7,FALSE),1)*VLOOKUP(D35,WDTable,6,FALSE))+VLOOKUP(D35,WDTable,4,FALSE),"") | P35: =IF(N35="","",L35*N35) | Q35: =IF(O35="","",M35*O35) | R35: =IFERROR(VLOOKUP(D35,WDTable,5,FALSE)*(L35+M35),"") | S35: =IF(P35="","",IFERROR(P35,0)+IFERROR(Q35,0)) | U35: =IF(S35="","",IFERROR(S35,0)-IFERROR(T35,0))
D37: WEEKLY TOTALS | L37: =SUM(L6:L35) | M37: =SUM(M6:M35) | P37: =SUM(P6:P35) | Q37: =SUM(Q6:Q35) | R37: =SUM(R6:R35) | S37: =SUM(S6:S35) | T37: =SUM(T6:T35) | U37: =SUM(U6:U35)

Sheet Statement of Compliance
B1: STATEMENT OF COMPLIANCE (WH-348-style)
B4: Date: ____________________ Payroll #: =PayrollNo Week Ending: =WeekEnding
B6: I, the undersigned, do hereby state, under penalty of perjury (18 U.S.C. § 1001 and 31 U.S.C. § 3729):
B8: (1) That I pay or supervise the payment of the persons employed by =SubName on the project identified as =ProjectName (Prime Contract No. =PrimeContractNo); that during the payroll period commencing on ____________________ and ending on =WeekEnding all persons employed on said project have been paid the full weekly wages earned, that no rebates have been or will be made either directly or indirectly to or on behalf of said =SubName from the full weekly wages earned by any person and that no deductions have been made either directly or indirectly from the full wages earned by any person, other than permissible deductions as defined in Regulations, Part 3 (29 C.F.R. Subtitle A), issued by the Secretary of Labor under the Copeland Act (40 U.S.C. § 3145), and described below: ____________________________________________________________________________
B10: (2) That any payrolls otherwise under this contract required to be submitted for the above period are correct and complete; that the wage rates for laborers or mechanics contained therein are not less than the applicable wage rates contained in any wage determination incorporated into the contract; that the classifications set forth therein for each laborer or mechanic conform with the work each performed.
B12: (3) That any apprentices employed in the above period are duly registered in a bona fide apprenticeship program registered with a State apprenticeship agency recognized by the Bureau of Apprenticeship and Training, United States Department of Labor, or if no such recognized agency exists in a State, are registered with the Bureau of Apprenticeship and Training, United States Department of Labor.
B14: (4) That: (a) WHERE FRINGE BENEFITS ARE PAID TO APPROVED PLANS, FUNDS, OR PROGRAMS — in addition to the basic hourly wage rates paid to each laborer or mechanic listed in the above referenced payroll, payments of fringe benefits as listed in the contract have been or will be made to appropriate programs for the benefit of such employees, except as noted in section 4(c) below. (b) WHERE FRINGE BENEFITS ARE PAID IN CASH — Each laborer or mechanic listed in the above referenced payroll has been paid, as indicated on the payroll, an amount not less than the sum of the applicable basic hourly wage rate plus the amount of the required fringe benefits as listed in the contract, except as noted in section 4(c) below. (c) EXCEPTIONS (specify by name of worker, basic hourly wage rate, fringe benefit method): _______________________________
B16: THE WILLFUL FALSIFICATION OF ANY OF THE ABOVE STATEMENTS MAY SUBJECT THE CONTRACTOR OR SUBCONTRACTOR TO CIVIL OR CRIMINAL PROSECUTION. SEE SECTION 1001 OF TITLE 18 AND SECTION 3729 OF TITLE 31 OF THE UNITED STATES CODE.
B19: Signature: _____________________________________ Date: ___________
B20: Printed Name: =SignatoryName
B21: Title: =SignatoryTitle
B22: Company: =SubName

Sheet CSI Reference
A1: CSI MasterFormat Divisions (reference only)
