Workbook
Name LaborOH: 'Project Info'!$C$10
Name LaborProfit: 'Project Info'!$C$11
Name MaterialMarkup: 'Project Info'!$C$12
Name EquipOwnedMarkup: 'Project Info'!$C$13
Name EquipRentedMarkup: 'Project Info'!$C$14
Name SubMarkup: 'Project Info'!$C$15
Name FringeBurden: 'Project Info'!$C$18
Name OTPremium: 'Project Info'!$C$19
Name DTPremium: 'Project Info'!$C$20
Name PrevailingWage: 'Project Info'!$C$21
Name LaborRates: 'Labor Rates'!$A$5:$G$24

Sheet Instructions
A1: T&M TRACKER — Instructions
A3: WHEN T&M APPLIES
A4: Time & Material billing is the default pricing method when changed Work is authorized without an agreed lump-sum price (a 'force-account' or 'directive' instruction). The GC's right to direct T&M work and the markup rates the sub may charge are governed by the Changes Article of the Subcontract and (on flow-down) the Prime Contract. Confirm both before invoicing.
A6: DAILY DISCIPLINE — THE FIVE INPUTS
A7: Each T&M day on the project must capture: (1) labor — every worker, classification, hours straight time and overtime, task; (2) equipment — every piece of equipment used and for how long; (3) materials — every material consumed or installed during the directed Work, with receipts; (4) subcontract — any lower-tier sub work performed under T&M; (5) GC field signature — a GC representative's same-day signature confirming the labor, equipment, and materials actually performed on directed Work. Without same-day signatures, T&M tickets are routinely disputed on billing.
A9: MARKUPS
A10: Industry-standard commercial markups, subject to Subcontract:
A11: - Labor: cost + fringe burden + 10-15% overhead + 10% profit
A12: - Material: cost + 10-15% markup (or as Subcontract specifies)
A13: - Equipment (owned): published rental rate (e.g., RS Means or AED) with no further markup, OR internal rate + 10% (Subcontract controls)
A14: - Equipment (rented): pass-through + 5-10% markup
A15: - Subcontract: cost + 5-7% markup (lower than self-performed because no direct supervision risk)
... A38: Keep paper tickets bundled by week, scanned into the project file. The XLSX is the working ledger; the paper is the evidence. In a dispute, the GC's PM will demand the original signed paper.

Sheet Project Info
B1: T&M PROJECT INFORMATION
B3: Project Name
B4: Subcontract No.
B5: GC
B6: Trade / Scope
B7: Subcontract Date
B9: MARKUP RATES — confirm against Subcontract
B10: Labor Overhead % | C10: 0.15
B11: Labor Profit % | C11: 0.1
B12: Material Markup % | C12: 0.15
B13: Equipment (Owned) Markup % | C13: 0.1
B14: Equipment (Rented) Markup % | C14: 0.1
B15: Subcontract Markup % | C15: 0.07
B17: LABOR — burdens and OT
B18: Fringe Burden % (on bare wage) | C18: 0.35
B19: OT Premium Multiplier (daily) | C19: 1.5
B20: DT Premium Multiplier (Sun / Holiday) | C20: 2
B21: Prevailing Wage Project? | C21: No
B23: APPROVAL
B24: Project Manager (Sub)
B25: Project Manager (GC)

Sheet Labor Rates
A1: LABOR RATE SCHEDULE
A2: Bare Wage = pre-burden hourly wage. Burdened = wage * (1 + fringe burden). Billed = burdened * (1 + LaborOH) * (1 + LaborProfit). On prevailing-wage projects, replace the default rates with the project-specific wage determination.
A4: Classification | B4: Bare Wage ($/hr) | C4: OT Multiplier | D4: Burdened Wage ($/hr) | E4: Burdened OT ($/hr) | F4: Billed ST Rate ($/hr) | G4: Billed OT Rate ($/hr) | H4: Notes
A5: Foreman | B5: 52 | C5: 1.5 | D5: =B5*(1+FringeBurden) | E5: =IF(PrevailingWage="Yes",(B5*C5)+(B5*FringeBurden),B5*C5*(1+FringeBurden)) | F5: =D5*(1+LaborOH)*(1+LaborProfit) | G5: =E5*(1+LaborOH)*(1+LaborProfit)
A6: Journeyman | B6: 42 | C6: 1.5 | D6: =B6*(1+FringeBurden) | E6: =IF(PrevailingWage="Yes",(B6*C6)+(B6*FringeBurden),B6*C6*(1+FringeBurden)) | F6: =D6*(1+LaborOH)*(1+LaborProfit) | G6: =E6*(1+LaborOH)*(1+LaborProfit)
A7: Apprentice — Year 4 | B7: 33 | C7: 1.5 | D7: =B7*(1+FringeBurden) | E7: =IF(PrevailingWage="Yes",(B7*C7)+(B7*FringeBurden),B7*C7*(1+FringeBurden)) | F7: =D7*(1+LaborOH)*(1+LaborProfit) | G7: =E7*(1+LaborOH)*(1+LaborProfit)
A8: Apprentice — Year 3 | B8: 28 | C8: 1.5 | D8: =B8*(1+FringeBurden) | E8: =IF(PrevailingWage="Yes",(B8*C8)+(B8*FringeBurden),B8*C8*(1+FringeBurden)) | F8: =D8*(1+LaborOH)*(1+LaborProfit) | G8: =E8*(1+LaborOH)*(1+LaborProfit)
A9: Apprentice — Year 2 | B9: 24 | C9: 1.5 | D9: =B9*(1+FringeBurden) | E9: =IF(PrevailingWage="Yes",(B9*C9)+(B9*FringeBurden),B9*C9*(1+FringeBurden)) | F9: =D9*(1+LaborOH)*(1+LaborProfit) | G9: =E9*(1+LaborOH)*(1+LaborProfit)
A10: Apprentice — Year 1 | B10: 20 | C10: 1.5 | D10: =B10*(1+FringeBurden) | E10: =IF(PrevailingWage="Yes",(B10*C10)+(B10*FringeBurden),B10*C10*(1+FringeBurden)) | F10: =D10*(1+LaborOH)*(1+LaborProfit) | G10: =E10*(1+LaborOH)*(1+LaborProfit)
A11: Helper / Laborer | B11: 22 | C11: 1.5 | D11: =B11*(1+FringeBurden) | E11: =IF(PrevailingWage="Yes",(B11*C11)+(B11*FringeBurden),B11*C11*(1+FringeBurden)) | F11: =D11*(1+LaborOH)*(1+LaborProfit) | G11: =E11*(1+LaborOH)*(1+LaborProfit)
A12: Operating Engineer | B12: 48 | C12: 1.5 | D12: =B12*(1+FringeBurden) | E12: =IF(PrevailingWage="Yes",(B12*C12)+(B12*FringeBurden),B12*C12*(1+FringeBurden)) | F12: =D12*(1+LaborOH)*(1+LaborProfit) | G12: =E12*(1+LaborOH)*(1+LaborProfit)
A13: Project Manager (T&M when authorized) | B13: 65 | C13: 1 | D13: =B13*(1+FringeBurden) | E13: =IF(PrevailingWage="Yes",(B13*C13)+(B13*FringeBurden),B13*C13*(1+FringeBurden)) | F13: =D13*(1+LaborOH)*(1+LaborProfit) | G13: =E13*(1+LaborOH)*(1+LaborProfit)
A14: Superintendent (T&M when authorized) | B14: 58 | C14: 1 | D14: =B14*(1+FringeBurden) | E14: =IF(PrevailingWage="Yes",(B14*C14)+(B14*FringeBurden),B14*C14*(1+FringeBurden)) | F14: =D14*(1+LaborOH)*(1+LaborProfit) | G14: =E14*(1+LaborOH)*(1+LaborProfit)

Sheet Labor Tickets
A1: LABOR TICKETS — Daily Force Account
A3: Date | B3: Ticket # | C3: Worker Name | D3: Classification | E3: Task / CO Ref | F3: ST Hours | G3: OT Hours | H3: Billed ST Rate | I3: Billed OT Rate | J3: Labor $ (ST) | K3: Labor $ (OT) | L3: Total Labor $ | M3: Status | N3: GC Signature | O3: Notes
H4: =IFERROR(VLOOKUP(D4,LaborRates,6,FALSE),"") | I4: =IFERROR(VLOOKUP(D4,LaborRates,7,FALSE),"") | J4: =IF(OR(F4="",H4=""),"",F4*H4) | K4: =IF(OR(G4="",I4=""),"",G4*I4) | L4: =IF(J4="",K4,IF(K4="",J4,J4+K4))
H5: =IFERROR(VLOOKUP(D5,LaborRates,6,FALSE),"") | I5: =IFERROR(VLOOKUP(D5,LaborRates,7,FALSE),"") | J5: =IF(OR(F5="",H5=""),"",F5*H5) | K5: =IF(OR(G5="",I5=""),"",G5*I5) | L5: =IF(J5="",K5,IF(K5="",J5,J5+K5))
H6: =IFERROR(VLOOKUP(D6,LaborRates,6,FALSE),"") | I6: =IFERROR(VLOOKUP(D6,LaborRates,7,FALSE),"") | J6: =IF(OR(F6="",H6=""),"",F6*H6) | K6: =IF(OR(G6="",I6=""),"",G6*I6) | L6: =IF(J6="",K6,IF(K6="",J6,J6+K6))
H7: =IFERROR(VLOOKUP(D7,LaborRates,6,FALSE),"") | I7: =IFERROR(VLOOKUP(D7,LaborRates,7,FALSE),"") | J7: =IF(OR(F7="",H7=""),"",F7*H7) | K7: =IF(OR(G7="",I7=""),"",G7*I7) | L7: =IF(J7="",K7,IF(K7="",J7,J7+K7))
H8: =IFERROR(VLOOKUP(D8,LaborRates,6,FALSE),"") | I8: =IFERROR(VLOOKUP(D8,LaborRates,7,FALSE),"") | J8: =IF(OR(F8="",H8=""),"",F8*H8) | K8: =IF(OR(G8="",I8=""),"",G8*I8) | L8: =IF(J8="",K8,IF(K8="",J8,J8+K8))
H9: =IFERROR(VLOOKUP(D9,LaborRates,6,FALSE),"") | I9: =IFERROR(VLOOKUP(D9,LaborRates,7,FALSE),"") | J9: =IF(OR(F9="",H9=""),"",F9*H9) | K9: =IF(OR(G9="",I9=""),"",G9*I9) | L9: =IF(J9="",K9,IF(K9="",J9,J9+K9))
H10: =IFERROR(VLOOKUP(D10,LaborRates,6,FALSE),"") | I10: =IFERROR(VLOOKUP(D10,LaborRates,7,FALSE),"") | J10: =IF(OR(F10="",H10=""),"",F10*H10) | K10: =IF(OR(G10="",I10=""),"",G10*I10) | L10: =IF(J10="",K10,IF(K10="",J10,J10+K10))
H11: =IFERROR(VLOOKUP(D11,LaborRates,6,FALSE),"") | I11: =IFERROR(VLOOKUP(D11,LaborRates,7,FALSE),"") | J11: =IF(OR(F11="",H11=""),"",F11*H11) | K11: =IF(OR(G11="",I11=""),"",G11*I11) | L11: =IF(J11="",K11,IF(K11="",J11,J11+K11))
H12: =IFERROR(VLOOKUP(D12,LaborRates,6,FALSE),"") | I12: =IFERROR(VLOOKUP(D12,LaborRates,7,FALSE),"") | J12: =IF(OR(F12="",H12=""),"",F12*H12) | K12: =IF(OR(G12="",I12=""),"",G12*I12) | L12: =IF(J12="",K12,IF(K12="",J12,J12+K12))
H13: =IFERROR(VLOOKUP(D13,LaborRates,6,FALSE),"") | I13: =IFERROR(VLOOKUP(D13,LaborRates,7,FALSE),"") | J13: =IF(OR(F13="",H13=""),"",F13*H13) | K13: =IF(OR(G13="",I13=""),"",G13*I13) | L13: =IF(J13="",K13,IF(K13="",J13,J13+K13))
H14: =IFERROR(VLOOKUP(D14,LaborRates,6,FALSE),"") | I14: =IFERROR(VLOOKUP(D14,LaborRates,7,FALSE),"") | J14: =IF(OR(F14="",H14=""),"",F14*H14) | K14: =IF(OR(G14="",I14=""),"",G14*I14) | L14: =IF(J14="",K14,IF(K14="",J14,J14+K14))
H15: =IFERROR(VLOOKUP(D15,LaborRates,6,FALSE),"") | I15: =IFERROR(VLOOKUP(D15,LaborRates,7,FALSE),"") | J15: =IF(OR(F15="",H15=""),"",F15*H15) | K15: =IF(OR(G15="",I15=""),"",G15*I15) | L15: =IF(J15="",K15,IF(K15="",J15,J15+K15))
... H203: =IFERROR(VLOOKUP(D203,LaborRates,6,FALSE),"") | I203: =IFERROR(VLOOKUP(D203,LaborRates,7,FALSE),"") | J203: =IF(OR(F203="",H203=""),"",F203*H203) | K203: =IF(OR(G203="",I203=""),"",G203*I203) | L203: =IF(J203="",K203,IF(K203="",J203,J203+K203))
E205: TOTALS | F205: =SUM(F4:F203) | G205: =SUM(G4:G203) | J205: =SUM(J4:J203) | K205: =SUM(K4:K203) | L205: =SUM(L4:L203)

Sheet Equipment Tickets
A1: EQUIPMENT TICKETS
A3: Date | B3: Ticket # | C3: Equipment | D3: Owned / Rented | E3: Task / CO Ref | F3: Hours | G3: Hourly Rate ($) | H3: Subtotal ($) | I3: Markup | J3: Billed Total ($) | K3: Status | L3: GC Signature | M3: Notes
H4: =IF(OR(F4="",G4=""),"",F4*G4) | I4: =IF(D4="Owned",EquipOwnedMarkup,IF(D4="Rented",EquipRentedMarkup,0)) | J4: =IF(H4="","",H4*(1+I4))
H5: =IF(OR(F5="",G5=""),"",F5*G5) | I5: =IF(D5="Owned",EquipOwnedMarkup,IF(D5="Rented",EquipRentedMarkup,0)) | J5: =IF(H5="","",H5*(1+I5))
H6: =IF(OR(F6="",G6=""),"",F6*G6) | I6: =IF(D6="Owned",EquipOwnedMarkup,IF(D6="Rented",EquipRentedMarkup,0)) | J6: =IF(H6="","",H6*(1+I6))
H7: =IF(OR(F7="",G7=""),"",F7*G7) | I7: =IF(D7="Owned",EquipOwnedMarkup,IF(D7="Rented",EquipRentedMarkup,0)) | J7: =IF(H7="","",H7*(1+I7))
H8: =IF(OR(F8="",G8=""),"",F8*G8) | I8: =IF(D8="Owned",EquipOwnedMarkup,IF(D8="Rented",EquipRentedMarkup,0)) | J8: =IF(H8="","",H8*(1+I8))
H9: =IF(OR(F9="",G9=""),"",F9*G9) | I9: =IF(D9="Owned",EquipOwnedMarkup,IF(D9="Rented",EquipRentedMarkup,0)) | J9: =IF(H9="","",H9*(1+I9))
H10: =IF(OR(F10="",G10=""),"",F10*G10) | I10: =IF(D10="Owned",EquipOwnedMarkup,IF(D10="Rented",EquipRentedMarkup,0)) | J10: =IF(H10="","",H10*(1+I10))
H11: =IF(OR(F11="",G11=""),"",F11*G11) | I11: =IF(D11="Owned",EquipOwnedMarkup,IF(D11="Rented",EquipRentedMarkup,0)) | J11: =IF(H11="","",H11*(1+I11))
H12: =IF(OR(F12="",G12=""),"",F12*G12) | I12: =IF(D12="Owned",EquipOwnedMarkup,IF(D12="Rented",EquipRentedMarkup,0)) | J12: =IF(H12="","",H12*(1+I12))
H13: =IF(OR(F13="",G13=""),"",F13*G13) | I13: =IF(D13="Owned",EquipOwnedMarkup,IF(D13="Rented",EquipRentedMarkup,0)) | J13: =IF(H13="","",H13*(1+I13))
H14: =IF(OR(F14="",G14=""),"",F14*G14) | I14: =IF(D14="Owned",EquipOwnedMarkup,IF(D14="Rented",EquipRentedMarkup,0)) | J14: =IF(H14="","",H14*(1+I14))
H15: =IF(OR(F15="",G15=""),"",F15*G15) | I15: =IF(D15="Owned",EquipOwnedMarkup,IF(D15="Rented",EquipRentedMarkup,0)) | J15: =IF(H15="","",H15*(1+I15))
... H123: =IF(OR(F123="",G123=""),"",F123*G123) | I123: =IF(D123="Owned",EquipOwnedMarkup,IF(D123="Rented",EquipRentedMarkup,0)) | J123: =IF(H123="","",H123*(1+I123))
E125: TOTALS | F125: =SUM(F4:F123) | H125: =SUM(H4:H123) | J125: =SUM(J4:J123)

Sheet Material Tickets
A1: MATERIAL TICKETS
A3: Date | B3: Ticket # | C3: Material / Description | D3: Supplier | E3: Invoice / PO # | F3: CSI Div | G3: Task / CO Ref | H3: Quantity | I3: Unit | J3: Unit Cost ($) | K3: Subtotal ($) | L3: Markup | M3: Billed ($) | N3: Status | O3: GC Signature
K4: =IF(OR(H4="",J4=""),"",H4*J4) | L4: =MaterialMarkup | M4: =IF(K4="","",K4*(1+L4))
K5: =IF(OR(H5="",J5=""),"",H5*J5) | L5: =MaterialMarkup | M5: =IF(K5="","",K5*(1+L5))
K6: =IF(OR(H6="",J6=""),"",H6*J6) | L6: =MaterialMarkup | M6: =IF(K6="","",K6*(1+L6))
K7: =IF(OR(H7="",J7=""),"",H7*J7) | L7: =MaterialMarkup | M7: =IF(K7="","",K7*(1+L7))
K8: =IF(OR(H8="",J8=""),"",H8*J8) | L8: =MaterialMarkup | M8: =IF(K8="","",K8*(1+L8))
K9: =IF(OR(H9="",J9=""),"",H9*J9) | L9: =MaterialMarkup | M9: =IF(K9="","",K9*(1+L9))
K10: =IF(OR(H10="",J10=""),"",H10*J10) | L10: =MaterialMarkup | M10: =IF(K10="","",K10*(1+L10))
K11: =IF(OR(H11="",J11=""),"",H11*J11) | L11: =MaterialMarkup | M11: =IF(K11="","",K11*(1+L11))
K12: =IF(OR(H12="",J12=""),"",H12*J12) | L12: =MaterialMarkup | M12: =IF(K12="","",K12*(1+L12))
K13: =IF(OR(H13="",J13=""),"",H13*J13) | L13: =MaterialMarkup | M13: =IF(K13="","",K13*(1+L13))
K14: =IF(OR(H14="",J14=""),"",H14*J14) | L14: =MaterialMarkup | M14: =IF(K14="","",K14*(1+L14))
K15: =IF(OR(H15="",J15=""),"",H15*J15) | L15: =MaterialMarkup | M15: =IF(K15="","",K15*(1+L15))
... K153: =IF(OR(H153="",J153=""),"",H153*J153) | L153: =MaterialMarkup | M153: =IF(K153="","",K153*(1+L153))
G155: TOTALS | K155: =SUM(K4:K153) | M155: =SUM(M4:M153)

Sheet Subcontract Tickets
A1: LOWER-TIER SUBCONTRACT TICKETS
A3: Date | B3: Ticket # | C3: Lower-Tier Sub | D3: Description of Work | E3: Task / CO Ref | F3: Sub's Invoice $ | G3: Markup | H3: Billed ($) | I3: Status | J3: GC Signature | K3: Notes
G4: =SubMarkup | H4: =IF(F4="","",F4*(1+G4))
G5: =SubMarkup | H5: =IF(F5="","",F5*(1+G5))
G6: =SubMarkup | H6: =IF(F6="","",F6*(1+G6))
G7: =SubMarkup | H7: =IF(F7="","",F7*(1+G7))
G8: =SubMarkup | H8: =IF(F8="","",F8*(1+G8))
G9: =SubMarkup | H9: =IF(F9="","",F9*(1+G9))
G10: =SubMarkup | H10: =IF(F10="","",F10*(1+G10))
G11: =SubMarkup | H11: =IF(F11="","",F11*(1+G11))
G12: =SubMarkup | H12: =IF(F12="","",F12*(1+G12))
G13: =SubMarkup | H13: =IF(F13="","",F13*(1+G13))
G14: =SubMarkup | H14: =IF(F14="","",F14*(1+G14))
G15: =SubMarkup | H15: =IF(F15="","",F15*(1+G15))
... G83: =SubMarkup | H83: =IF(F83="","",F83*(1+G83))
E85: TOTALS | F85: =SUM(F4:F83) | H85: =SUM(H4:H83)

Sheet Invoice Roll-Up
B1: T&M INVOICE ROLL-UP
B2: Roll-up by status. Approved totals feed the invoice; Disputed / Unsigned tracked separately.
B4: Category | C4: Approved | D4: Pending / Signed | E4: Disputed / Unsigned
B5: Labor | C5: =SUMIF('Labor Tickets'!M:M,"Approved",'Labor Tickets'!L:L)+SUMIF('Labor Tickets'!M:M,"Paid",'Labor Tickets'!L:L)+SUMIF('Labor Tickets'!M:M,"Invoiced",'Labor Tickets'!L:L) | D5: =SUMIF('Labor Tickets'!M:M,"Pending",'Labor Tickets'!L:L)+SUMIF('Labor Tickets'!M:M,"Signed",'Labor Tickets'!L:L) | E5: =SUMIF('Labor Tickets'!M:M,"Disputed",'Labor Tickets'!L:L)+SUMIF('Labor Tickets'!M:M,"Unsigned",'Labor Tickets'!L:L)
B6: Equipment | C6: =SUMIF('Equipment Tickets'!K:K,"Approved",'Equipment Tickets'!J:J)+SUMIF('Equipment Tickets'!K:K,"Paid",'Equipment Tickets'!J:J)+SUMIF('Equipment Tickets'!K:K,"Invoiced",'Equipment Tickets'!J:J) | D6: =SUMIF('Equipment Tickets'!K:K,"Pending",'Equipment Tickets'!J:J)+SUMIF('Equipment Tickets'!K:K,"Signed",'Equipment Tickets'!J:J) | E6: =SUMIF('Equipment Tickets'!K:K,"Disputed",'Equipment Tickets'!J:J)+SUMIF('Equipment Tickets'!K:K,"Unsigned",'Equipment Tickets'!J:J)
B7: Materials | C7: =SUMIF('Material Tickets'!N:N,"Approved",'Material Tickets'!M:M)+SUMIF('Material Tickets'!N:N,"Paid",'Material Tickets'!M:M)+SUMIF('Material Tickets'!N:N,"Invoiced",'Material Tickets'!M:M) | D7: =SUMIF('Material Tickets'!N:N,"Pending",'Material Tickets'!M:M)+SUMIF('Material Tickets'!N:N,"Signed",'Material Tickets'!M:M) | E7: =SUMIF('Material Tickets'!N:N,"Disputed",'Material Tickets'!M:M)+SUMIF('Material Tickets'!N:N,"Unsigned",'Material Tickets'!M:M)
B8: Subcontract | C8: =SUMIF('Subcontract Tickets'!I:I,"Approved",'Subcontract Tickets'!H:H)+SUMIF('Subcontract Tickets'!I:I,"Paid",'Subcontract Tickets'!H:H)+SUMIF('Subcontract Tickets'!I:I,"Invoiced",'Subcontract Tickets'!H:H) | D8: =SUMIF('Subcontract Tickets'!I:I,"Pending",'Subcontract Tickets'!H:H)+SUMIF('Subcontract Tickets'!I:I,"Signed",'Subcontract Tickets'!H:H) | E8: =SUMIF('Subcontract Tickets'!I:I,"Disputed",'Subcontract Tickets'!H:H)+SUMIF('Subcontract Tickets'!I:I,"Unsigned",'Subcontract Tickets'!H:H)
B9: TOTAL | C9: =SUM(C5:C8) | D9: =SUM(D5:D8) | E9: =SUM(E5:E8)
B12: INVOICE NEXT STEPS
B13: 1. Confirm Approved column totals match the signed-and-approved tickets.
B14: 2. Disputed / Unsigned column is the working dispute file; track preservation-of-claim notice dates.
B15: 3. Build the T&M invoice from Approved totals only. Pending / Signed remains on the next month's invoice.
B16: 4. After invoice is sent, change ticket statuses from Approved → Invoiced.
B17: 5. After payment is received, change ticket statuses from Invoiced → Paid.

Sheet CSI Reference
A1: CSI MasterFormat Divisions
A3: Div | B3: Name
A4: 01 | B4: General Requirements
A5: 02 | B5: Existing Conditions
A6: 03 | B6: Concrete
A7: 04 | B7: Masonry
A8: 05 | B8: Metals
A9: 06 | B9: Wood, Plastics, and Composites
A10: 07 | B10: Thermal and Moisture Protection
A11: 08 | B11: Openings
A12: 09 | B12: Finishes
A13: 10 | B13: Specialties
A14: 11 | B14: Equipment
... A29: 35 | B29: Waterway and Marine Construction
