Workbook
Name CSI_Divisions: 'CSI Reference'!$A$4:$A$38
Name CSI_Table: 'CSI Reference'!$A$4:$B$38

Sheet Instructions
B2: ContrPro - Accounts Payable (AP) Tracker
B3: Mirror image of the AR Tracker - what YOU owe vendors, subs, and suppliers. Cash flow and lien-waiver discipline live here.
B5: What this workbook is
B6: Five visible tabs plus a hidden CSI Reference. Company Info anchors your entity, Vendor Invoice Log is the main worksheet, Aging Summary buckets exposure by vendor type, and Dashboard surfaces the two metrics that wreck contractors: Subs Paid Without Lien Waiver and Subs On Site With Expired COIs.
B7: Every bill you receive goes in the Vendor Invoice Log. The aging math is automatic - you fill in dates and amounts, the workbook tells you what's due this week, what's late, and which payments carry risk.
B9: Vendor vs sub vs material supplier - tag every row
B10: Subcontractor - performs labor on site. Owes you a lien waiver before AND after payment. Must carry current COI naming you as additional insured. Highest risk per dollar - mechanic's-lien exposure.
B11: Material Supplier - delivers materials, no on-site labor. May still have lien rights (depends on state). Joint check agreements common when supplier sells through your sub.
B12: Equipment Rental - cranes, lifts, generators. Time-and-materials billing. Watch for damage waivers and fuel/run-time true-ups.
B13: Service - utilities, dumpsters, sanitation, professional services (engineer, surveyor, attorney).
B14: Other - catch-all. Use sparingly; re-tag when you can.
B16: Lien waiver workflow - DO NOT pay without one
... B69: ContrPro - built for builders. Questions: support@contrpro.com

Sheet Company Info
A1: Company Information
A3: Company Name | B3: EIN | C3: Primary State | D3: Notes
A4: EXAMPLE - Acme Construction LLC | B4: 12-3456789 | C4: TX | D4: Texas Construction Trust Fund Act applies - pay subs from project receipts first.

Sheet Vendor Invoice Log
A1: Vendor Invoice Log (CSI MasterFormat)
A3: Invoice / Bill Number | B3: Date Received | C3: Vendor / Supplier / Sub | D3: Vendor Type | E3: CSI Division | F3: CSI Code | G3: Division Name | H3: Project / Job | I3: Description | J3: Amount | K3: Retainage Withheld | L3: Net Payable | M3: Date Due | N3: Date Paid | O3: Amount Paid | P3: Outstanding | Q3: Days Outstanding | R3: Aging Bucket | S3: Lien Waiver Received? | T3: COI Current? | U3: Status | V3: Notes
A4: B-2001 | B4: 2026-03-15 | C4: Pacific Steel Erectors | D4: Subcontractor | E4: 05 | F4: 05 12 00 | G4: =IFERROR(VLOOKUP(E4,CSI_Table,2,FALSE),"") | H4: Riverside Office Bldg | I4: Pay App #2 - Structural steel erection, Level 1-2. | J4: 58400 | K4: 2920 | L4: =IFERROR(J4,0)-IFERROR(K4,0) | M4: 2026-04-14 | N4: 2026-04-12 | O4: 55480 | P4: =IFERROR(L4,0)-IFERROR(O4,0) | Q4: =IF(OR(M4="",IFERROR(P4,0)<=0),"",MAX(0,TODAY()-M4)) | R4: =IF(AND(N4<>"",IFERROR(O4,0)>=IFERROR(L4,0),IFERROR(L4,0)>0),"Paid",IF(M4="","",IF(TODAY()-M4<=0,"Current",IF(TODAY()-M4<=30,"1-30",IF(TODAY()-M4<=60,"31-60",IF(TODAY()-M4<=90,"61-90",IF(TODAY()-M4<=120,"91-120","120+"))))))) | S4: Unconditional Partial | T4: Yes | U4: Paid | V4: Paid via ACH. Conditional issued with invoice, unconditional received after funds cleared. COI on file thru 2026-09-30.
A5: B-2002 | B5: 2026-04-30 | C5: Apex Plumbing & Mechanical | D5: Subcontractor | E5: 22 | F5: 22 10 00 | G5: =IFERROR(VLOOKUP(E5,CSI_Table,2,FALSE),"") | H5: Riverside Office Bldg | I5: Pay App #3 - Plumbing rough-in, Level 2. | J5: 34200 | K5: 1710 | L5: =IFERROR(J5,0)-IFERROR(K5,0) | M5: 2026-05-30 | O5: 0 | P5: =IFERROR(L5,0)-IFERROR(O5,0) | Q5: =IF(OR(M5="",IFERROR(P5,0)<=0),"",MAX(0,TODAY()-M5)) | R5: =IF(AND(N5<>"",IFERROR(O5,0)>=IFERROR(L5,0),IFERROR(L5,0)>0),"Paid",IF(M5="","",IF(TODAY()-M5<=0,"Current",IF(TODAY()-M5<=30,"1-30",IF(TODAY()-M5<=60,"31-60",IF(TODAY()-M5<=90,"61-90",IF(TODAY()-M5<=120,"91-120","120+"))))))) | S5: Conditional | T5: Yes | U5: Approved for Payment | V5: Pay app reviewed and approved. Conditional waiver on file. Releasing check this week on receipt of unconditional partial.
A6: B-2003 | B6: 2026-03-02 | C6: Heartland Lumber Supply | D6: Material Supplier | E6: 06 | F6: 06 10 00 | G6: =IFERROR(VLOOKUP(E6,CSI_Table,2,FALSE),"") | H6: Riverside Office Bldg | I6: Framing lumber package - Level 2 partitions. | J6: 11850 | K6: 0 | L6: =IFERROR(J6,0)-IFERROR(K6,0) | M6: 2026-04-01 | O6: 0 | P6: =IFERROR(L6,0)-IFERROR(O6,0) | Q6: =IF(OR(M6="",IFERROR(P6,0)<=0),"",MAX(0,TODAY()-M6)) | R6: =IF(AND(N6<>"",IFERROR(O6,0)>=IFERROR(L6,0),IFERROR(L6,0)>0),"Paid",IF(M6="","",IF(TODAY()-M6<=0,"Current",IF(TODAY()-M6<=30,"1-30",IF(TODAY()-M6<=60,"31-60",IF(TODAY()-M6<=90,"61-90",IF(TODAY()-M6<=120,"91-120","120+"))))))) | S6: N/A | T6: N/A | U6: Received | V6: Material supplier - no retainage, no COI required (off-site delivery). Disputing 12 sticks short on tally. Hold check pending credit memo.
A7: B-2004 | B7: 2026-02-12 | C7: Bayside Electric LLC | D7: Subcontractor | E7: 26 | F7: 26 50 00 | G7: =IFERROR(VLOOKUP(E7,CSI_Table,2,FALSE),"") | H7: Pinnacle Tower Renovation | I7: Pay App #1 - Lighting rough-in & fixture install Level 3. | J7: 22600 | K7: 1130 | L7: =IFERROR(J7,0)-IFERROR(K7,0) | M7: 2026-03-14 | O7: 10000 | P7: =IFERROR(L7,0)-IFERROR(O7,0) | Q7: =IF(OR(M7="",IFERROR(P7,0)<=0),"",MAX(0,TODAY()-M7)) | R7: =IF(AND(N7<>"",IFERROR(O7,0)>=IFERROR(L7,0),IFERROR(L7,0)>0),"Paid",IF(M7="","",IF(TODAY()-M7<=0,"Current",IF(TODAY()-M7<=30,"1-30",IF(TODAY()-M7<=60,"31-60",IF(TODAY()-M7<=90,"61-90",IF(TODAY()-M7<=120,"91-120","120+"))))))) | S7: Conditional | T7: Expired | U7: On Hold | V7: RISK: Sub COI expired 2026-04-30. Required new cert before next payment. Partial payment was released before expiry. Follow-up sent 2026-05-05; no response. Stop further on-site work.
A8: B-2005 | B8: 2026-01-22 | C8: Granite Concrete Cutters | D8: Subcontractor | E8: 03 | F8: 03 30 00 | G8: =IFERROR(VLOOKUP(E8,CSI_Table,2,FALSE),"") | H8: Pinnacle Tower Renovation | I8: Saw-cut & remove existing SOG for new MEP chase. | J8: 8650 | K8: 0 | L8: =IFERROR(J8,0)-IFERROR(K8,0) | M8: 2026-02-21 | N8: 2026-02-19 | O8: 8650 | P8: =IFERROR(L8,0)-IFERROR(O8,0) | Q8: =IF(OR(M8="",IFERROR(P8,0)<=0),"",MAX(0,TODAY()-M8)) | R8: =IF(AND(N8<>"",IFERROR(O8,0)>=IFERROR(L8,0),IFERROR(L8,0)>0),"Paid",IF(M8="","",IF(TODAY()-M8<=0,"Current",IF(TODAY()-M8<=30,"1-30",IF(TODAY()-M8<=60,"31-60",IF(TODAY()-M8<=90,"61-90",IF(TODAY()-M8<=120,"91-120","120+"))))))) | S8: None | T8: Yes | U8: Paid | V8: RISK: Paid in full without any lien waiver received. Followed up twice for unconditional final - radio silence. Lien exposure window still open per state statute. Escalate to attorney if not resolved by 5/20.
G9: =IFERROR(VLOOKUP(E9,CSI_Table,2,FALSE),"") | L9: =IFERROR(J9,0)-IFERROR(K9,0) | P9: =IFERROR(L9,0)-IFERROR(O9,0) | Q9: =IF(OR(M9="",IFERROR(P9,0)<=0),"",MAX(0,TODAY()-M9)) | R9: =IF(AND(N9<>"",IFERROR(O9,0)>=IFERROR(L9,0),IFERROR(L9,0)>0),"Paid",IF(M9="","",IF(TODAY()-M9<=0,"Current",IF(TODAY()-M9<=30,"1-30",IF(TODAY()-M9<=60,"31-60",IF(TODAY()-M9<=90,"61-90",IF(TODAY()-M9<=120,"91-120","120+")))))))
G10: =IFERROR(VLOOKUP(E10,CSI_Table,2,FALSE),"") | L10: =IFERROR(J10,0)-IFERROR(K10,0) | P10: =IFERROR(L10,0)-IFERROR(O10,0) | Q10: =IF(OR(M10="",IFERROR(P10,0)<=0),"",MAX(0,TODAY()-M10)) | R10: =IF(AND(N10<>"",IFERROR(O10,0)>=IFERROR(L10,0),IFERROR(L10,0)>0),"Paid",IF(M10="","",IF(TODAY()-M10<=0,"Current",IF(TODAY()-M10<=30,"1-30",IF(TODAY()-M10<=60,"31-60",IF(TODAY()-M10<=90,"61-90",IF(TODAY()-M10<=120,"91-120","120+")))))))
G11: =IFERROR(VLOOKUP(E11,CSI_Table,2,FALSE),"") | L11: =IFERROR(J11,0)-IFERROR(K11,0) | P11: =IFERROR(L11,0)-IFERROR(O11,0) | Q11: =IF(OR(M11="",IFERROR(P11,0)<=0),"",MAX(0,TODAY()-M11)) | R11: =IF(AND(N11<>"",IFERROR(O11,0)>=IFERROR(L11,0),IFERROR(L11,0)>0),"Paid",IF(M11="","",IF(TODAY()-M11<=0,"Current",IF(TODAY()-M11<=30,"1-30",IF(TODAY()-M11<=60,"31-60",IF(TODAY()-M11<=90,"61-90",IF(TODAY()-M11<=120,"91-120","120+")))))))
G12: =IFERROR(VLOOKUP(E12,CSI_Table,2,FALSE),"") | L12: =IFERROR(J12,0)-IFERROR(K12,0) | P12: =IFERROR(L12,0)-IFERROR(O12,0) | Q12: =IF(OR(M12="",IFERROR(P12,0)<=0),"",MAX(0,TODAY()-M12)) | R12: =IF(AND(N12<>"",IFERROR(O12,0)>=IFERROR(L12,0),IFERROR(L12,0)>0),"Paid",IF(M12="","",IF(TODAY()-M12<=0,"Current",IF(TODAY()-M12<=30,"1-30",IF(TODAY()-M12<=60,"31-60",IF(TODAY()-M12<=90,"61-90",IF(TODAY()-M12<=120,"91-120","120+")))))))
G13: =IFERROR(VLOOKUP(E13,CSI_Table,2,FALSE),"") | L13: =IFERROR(J13,0)-IFERROR(K13,0) | P13: =IFERROR(L13,0)-IFERROR(O13,0) | Q13: =IF(OR(M13="",IFERROR(P13,0)<=0),"",MAX(0,TODAY()-M13)) | R13: =IF(AND(N13<>"",IFERROR(O13,0)>=IFERROR(L13,0),IFERROR(L13,0)>0),"Paid",IF(M13="","",IF(TODAY()-M13<=0,"Current",IF(TODAY()-M13<=30,"1-30",IF(TODAY()-M13<=60,"31-60",IF(TODAY()-M13<=90,"61-90",IF(TODAY()-M13<=120,"91-120","120+")))))))
G14: =IFERROR(VLOOKUP(E14,CSI_Table,2,FALSE),"") | L14: =IFERROR(J14,0)-IFERROR(K14,0) | P14: =IFERROR(L14,0)-IFERROR(O14,0) | Q14: =IF(OR(M14="",IFERROR(P14,0)<=0),"",MAX(0,TODAY()-M14)) | R14: =IF(AND(N14<>"",IFERROR(O14,0)>=IFERROR(L14,0),IFERROR(L14,0)>0),"Paid",IF(M14="","",IF(TODAY()-M14<=0,"Current",IF(TODAY()-M14<=30,"1-30",IF(TODAY()-M14<=60,"31-60",IF(TODAY()-M14<=90,"61-90",IF(TODAY()-M14<=120,"91-120","120+")))))))
G15: =IFERROR(VLOOKUP(E15,CSI_Table,2,FALSE),"") | L15: =IFERROR(J15,0)-IFERROR(K15,0) | P15: =IFERROR(L15,0)-IFERROR(O15,0) | Q15: =IF(OR(M15="",IFERROR(P15,0)<=0),"",MAX(0,TODAY()-M15)) | R15: =IF(AND(N15<>"",IFERROR(O15,0)>=IFERROR(L15,0),IFERROR(L15,0)>0),"Paid",IF(M15="","",IF(TODAY()-M15<=0,"Current",IF(TODAY()-M15<=30,"1-30",IF(TODAY()-M15<=60,"31-60",IF(TODAY()-M15<=90,"61-90",IF(TODAY()-M15<=120,"91-120","120+")))))))
G16: =IFERROR(VLOOKUP(E16,CSI_Table,2,FALSE),"") | L16: =IFERROR(J16,0)-IFERROR(K16,0) | P16: =IFERROR(L16,0)-IFERROR(O16,0) | Q16: =IF(OR(M16="",IFERROR(P16,0)<=0),"",MAX(0,TODAY()-M16)) | R16: =IF(AND(N16<>"",IFERROR(O16,0)>=IFERROR(L16,0),IFERROR(L16,0)>0),"Paid",IF(M16="","",IF(TODAY()-M16<=0,"Current",IF(TODAY()-M16<=30,"1-30",IF(TODAY()-M16<=60,"31-60",IF(TODAY()-M16<=90,"61-90",IF(TODAY()-M16<=120,"91-120","120+")))))))
G17: =IFERROR(VLOOKUP(E17,CSI_Table,2,FALSE),"") | L17: =IFERROR(J17,0)-IFERROR(K17,0) | P17: =IFERROR(L17,0)-IFERROR(O17,0) | Q17: =IF(OR(M17="",IFERROR(P17,0)<=0),"",MAX(0,TODAY()-M17)) | R17: =IF(AND(N17<>"",IFERROR(O17,0)>=IFERROR(L17,0),IFERROR(L17,0)>0),"Paid",IF(M17="","",IF(TODAY()-M17<=0,"Current",IF(TODAY()-M17<=30,"1-30",IF(TODAY()-M17<=60,"31-60",IF(TODAY()-M17<=90,"61-90",IF(TODAY()-M17<=120,"91-120","120+")))))))
G18: =IFERROR(VLOOKUP(E18,CSI_Table,2,FALSE),"") | L18: =IFERROR(J18,0)-IFERROR(K18,0) | P18: =IFERROR(L18,0)-IFERROR(O18,0) | Q18: =IF(OR(M18="",IFERROR(P18,0)<=0),"",MAX(0,TODAY()-M18)) | R18: =IF(AND(N18<>"",IFERROR(O18,0)>=IFERROR(L18,0),IFERROR(L18,0)>0),"Paid",IF(M18="","",IF(TODAY()-M18<=0,"Current",IF(TODAY()-M18<=30,"1-30",IF(TODAY()-M18<=60,"31-60",IF(TODAY()-M18<=90,"61-90",IF(TODAY()-M18<=120,"91-120","120+")))))))
G19: =IFERROR(VLOOKUP(E19,CSI_Table,2,FALSE),"") | L19: =IFERROR(J19,0)-IFERROR(K19,0) | P19: =IFERROR(L19,0)-IFERROR(O19,0) | Q19: =IF(OR(M19="",IFERROR(P19,0)<=0),"",MAX(0,TODAY()-M19)) | R19: =IF(AND(N19<>"",IFERROR(O19,0)>=IFERROR(L19,0),IFERROR(L19,0)>0),"Paid",IF(M19="","",IF(TODAY()-M19<=0,"Current",IF(TODAY()-M19<=30,"1-30",IF(TODAY()-M19<=60,"31-60",IF(TODAY()-M19<=90,"61-90",IF(TODAY()-M19<=120,"91-120","120+")))))))
G20: =IFERROR(VLOOKUP(E20,CSI_Table,2,FALSE),"") | L20: =IFERROR(J20,0)-IFERROR(K20,0) | P20: =IFERROR(L20,0)-IFERROR(O20,0) | Q20: =IF(OR(M20="",IFERROR(P20,0)<=0),"",MAX(0,TODAY()-M20)) | R20: =IF(AND(N20<>"",IFERROR(O20,0)>=IFERROR(L20,0),IFERROR(L20,0)>0),"Paid",IF(M20="","",IF(TODAY()-M20<=0,"Current",IF(TODAY()-M20<=30,"1-30",IF(TODAY()-M20<=60,"31-60",IF(TODAY()-M20<=90,"61-90",IF(TODAY()-M20<=120,"91-120","120+")))))))
... G33: =IFERROR(VLOOKUP(E33,CSI_Table,2,FALSE),"") | L33: =IFERROR(J33,0)-IFERROR(K33,0) | P33: =IFERROR(L33,0)-IFERROR(O33,0) | Q33: =IF(OR(M33="",IFERROR(P33,0)<=0),"",MAX(0,TODAY()-M33)) | R33: =IF(AND(N33<>"",IFERROR(O33,0)>=IFERROR(L33,0),IFERROR(L33,0)>0),"Paid",IF(M33="","",IF(TODAY()-M33<=0,"Current",IF(TODAY()-M33<=30,"1-30",IF(TODAY()-M33<=60,"31-60",IF(TODAY()-M33<=90,"61-90",IF(TODAY()-M33<=120,"91-120","120+")))))))
I35: TOTALS | J35: =SUM(J4:J33) | K35: =SUM(K4:K33) | L35: =SUM(L4:L33) | O35: =SUM(O4:O33) | P35: =SUM(P4:P33)

Sheet Aging Summary by Type
A1: AP Aging Summary by Vendor Type
A2: Reads from Vendor Invoice Log via COUNTIFS / SUMIFS - do not edit. Cross-tabs aging bucket by vendor type. Material Supplier + Equipment Rental + Service + Other are rolled into the 'Other' columns.
A3: Aging Bucket | B3: Subcontractor Count | C3: Sub $ | D3: Supplier Count | E3: Supplier $ | F3: Other Count | G3: Other $
A4: Current | B4: =COUNTIFS('Vendor Invoice Log'!$R$4:$R$33,A4,'Vendor Invoice Log'!$D$4:$D$33,"Subcontractor") | C4: =SUMIFS('Vendor Invoice Log'!$P$4:$P$33,'Vendor Invoice Log'!$R$4:$R$33,A4,'Vendor Invoice Log'!$D$4:$D$33,"Subcontractor") | D4: =COUNTIFS('Vendor Invoice Log'!$R$4:$R$33,A4,'Vendor Invoice Log'!$D$4:$D$33,"Material Supplier") | E4: =SUMIFS('Vendor Invoice Log'!$P$4:$P$33,'Vendor Invoice Log'!$R$4:$R$33,A4,'Vendor Invoice Log'!$D$4:$D$33,"Material Supplier") | F4: =COUNTIF('Vendor Invoice Log'!$R$4:$R$33,A4)-COUNTIFS('Vendor Invoice Log'!$R$4:$R$33,A4,'Vendor Invoice Log'!$D$4:$D$33,"Subcontractor")-COUNTIFS('Vendor Invoice Log'!$R$4:$R$33,A4,'Vendor Invoice Log'!$D$4:$D$33,"Material Supplier") | G4: =SUMIFS('Vendor Invoice Log'!$P$4:$P$33,'Vendor Invoice Log'!$R$4:$R$33,A4)-SUMIFS('Vendor Invoice Log'!$P$4:$P$33,'Vendor Invoice Log'!$R$4:$R$33,A4,'Vendor Invoice Log'!$D$4:$D$33,"Subcontractor")-SUMIFS('Vendor Invoice Log'!$P$4:$P$33,'Vendor Invoice Log'!$R$4:$R$33,A4,'Vendor Invoice Log'!$D$4:$D$33,"Material Supplier")
A5: 1-30 | B5: =COUNTIFS('Vendor Invoice Log'!$R$4:$R$33,A5,'Vendor Invoice Log'!$D$4:$D$33,"Subcontractor") | C5: =SUMIFS('Vendor Invoice Log'!$P$4:$P$33,'Vendor Invoice Log'!$R$4:$R$33,A5,'Vendor Invoice Log'!$D$4:$D$33,"Subcontractor") | D5: =COUNTIFS('Vendor Invoice Log'!$R$4:$R$33,A5,'Vendor Invoice Log'!$D$4:$D$33,"Material Supplier") | E5: =SUMIFS('Vendor Invoice Log'!$P$4:$P$33,'Vendor Invoice Log'!$R$4:$R$33,A5,'Vendor Invoice Log'!$D$4:$D$33,"Material Supplier") | F5: =COUNTIF('Vendor Invoice Log'!$R$4:$R$33,A5)-COUNTIFS('Vendor Invoice Log'!$R$4:$R$33,A5,'Vendor Invoice Log'!$D$4:$D$33,"Subcontractor")-COUNTIFS('Vendor Invoice Log'!$R$4:$R$33,A5,'Vendor Invoice Log'!$D$4:$D$33,"Material Supplier") | G5: =SUMIFS('Vendor Invoice Log'!$P$4:$P$33,'Vendor Invoice Log'!$R$4:$R$33,A5)-SUMIFS('Vendor Invoice Log'!$P$4:$P$33,'Vendor Invoice Log'!$R$4:$R$33,A5,'Vendor Invoice Log'!$D$4:$D$33,"Subcontractor")-SUMIFS('Vendor Invoice Log'!$P$4:$P$33,'Vendor Invoice Log'!$R$4:$R$33,A5,'Vendor Invoice Log'!$D$4:$D$33,"Material Supplier")
A6: 31-60 | B6: =COUNTIFS('Vendor Invoice Log'!$R$4:$R$33,A6,'Vendor Invoice Log'!$D$4:$D$33,"Subcontractor") | C6: =SUMIFS('Vendor Invoice Log'!$P$4:$P$33,'Vendor Invoice Log'!$R$4:$R$33,A6,'Vendor Invoice Log'!$D$4:$D$33,"Subcontractor") | D6: =COUNTIFS('Vendor Invoice Log'!$R$4:$R$33,A6,'Vendor Invoice Log'!$D$4:$D$33,"Material Supplier") | E6: =SUMIFS('Vendor Invoice Log'!$P$4:$P$33,'Vendor Invoice Log'!$R$4:$R$33,A6,'Vendor Invoice Log'!$D$4:$D$33,"Material Supplier") | F6: =COUNTIF('Vendor Invoice Log'!$R$4:$R$33,A6)-COUNTIFS('Vendor Invoice Log'!$R$4:$R$33,A6,'Vendor Invoice Log'!$D$4:$D$33,"Subcontractor")-COUNTIFS('Vendor Invoice Log'!$R$4:$R$33,A6,'Vendor Invoice Log'!$D$4:$D$33,"Material Supplier") | G6: =SUMIFS('Vendor Invoice Log'!$P$4:$P$33,'Vendor Invoice Log'!$R$4:$R$33,A6)-SUMIFS('Vendor Invoice Log'!$P$4:$P$33,'Vendor Invoice Log'!$R$4:$R$33,A6,'Vendor Invoice Log'!$D$4:$D$33,"Subcontractor")-SUMIFS('Vendor Invoice Log'!$P$4:$P$33,'Vendor Invoice Log'!$R$4:$R$33,A6,'Vendor Invoice Log'!$D$4:$D$33,"Material Supplier")
A7: 61-90 | B7: =COUNTIFS('Vendor Invoice Log'!$R$4:$R$33,A7,'Vendor Invoice Log'!$D$4:$D$33,"Subcontractor") | C7: =SUMIFS('Vendor Invoice Log'!$P$4:$P$33,'Vendor Invoice Log'!$R$4:$R$33,A7,'Vendor Invoice Log'!$D$4:$D$33,"Subcontractor") | D7: =COUNTIFS('Vendor Invoice Log'!$R$4:$R$33,A7,'Vendor Invoice Log'!$D$4:$D$33,"Material Supplier") | E7: =SUMIFS('Vendor Invoice Log'!$P$4:$P$33,'Vendor Invoice Log'!$R$4:$R$33,A7,'Vendor Invoice Log'!$D$4:$D$33,"Material Supplier") | F7: =COUNTIF('Vendor Invoice Log'!$R$4:$R$33,A7)-COUNTIFS('Vendor Invoice Log'!$R$4:$R$33,A7,'Vendor Invoice Log'!$D$4:$D$33,"Subcontractor")-COUNTIFS('Vendor Invoice Log'!$R$4:$R$33,A7,'Vendor Invoice Log'!$D$4:$D$33,"Material Supplier") | G7: =SUMIFS('Vendor Invoice Log'!$P$4:$P$33,'Vendor Invoice Log'!$R$4:$R$33,A7)-SUMIFS('Vendor Invoice Log'!$P$4:$P$33,'Vendor Invoice Log'!$R$4:$R$33,A7,'Vendor Invoice Log'!$D$4:$D$33,"Subcontractor")-SUMIFS('Vendor Invoice Log'!$P$4:$P$33,'Vendor Invoice Log'!$R$4:$R$33,A7,'Vendor Invoice Log'!$D$4:$D$33,"Material Supplier")
A8: 91-120 | B8: =COUNTIFS('Vendor Invoice Log'!$R$4:$R$33,A8,'Vendor Invoice Log'!$D$4:$D$33,"Subcontractor") | C8: =SUMIFS('Vendor Invoice Log'!$P$4:$P$33,'Vendor Invoice Log'!$R$4:$R$33,A8,'Vendor Invoice Log'!$D$4:$D$33,"Subcontractor") | D8: =COUNTIFS('Vendor Invoice Log'!$R$4:$R$33,A8,'Vendor Invoice Log'!$D$4:$D$33,"Material Supplier") | E8: =SUMIFS('Vendor Invoice Log'!$P$4:$P$33,'Vendor Invoice Log'!$R$4:$R$33,A8,'Vendor Invoice Log'!$D$4:$D$33,"Material Supplier") | F8: =COUNTIF('Vendor Invoice Log'!$R$4:$R$33,A8)-COUNTIFS('Vendor Invoice Log'!$R$4:$R$33,A8,'Vendor Invoice Log'!$D$4:$D$33,"Subcontractor")-COUNTIFS('Vendor Invoice Log'!$R$4:$R$33,A8,'Vendor Invoice Log'!$D$4:$D$33,"Material Supplier") | G8: =SUMIFS('Vendor Invoice Log'!$P$4:$P$33,'Vendor Invoice Log'!$R$4:$R$33,A8)-SUMIFS('Vendor Invoice Log'!$P$4:$P$33,'Vendor Invoice Log'!$R$4:$R$33,A8,'Vendor Invoice Log'!$D$4:$D$33,"Subcontractor")-SUMIFS('Vendor Invoice Log'!$P$4:$P$33,'Vendor Invoice Log'!$R$4:$R$33,A8,'Vendor Invoice Log'!$D$4:$D$33,"Material Supplier")
A9: 120+ | B9: =COUNTIFS('Vendor Invoice Log'!$R$4:$R$33,A9,'Vendor Invoice Log'!$D$4:$D$33,"Subcontractor") | C9: =SUMIFS('Vendor Invoice Log'!$P$4:$P$33,'Vendor Invoice Log'!$R$4:$R$33,A9,'Vendor Invoice Log'!$D$4:$D$33,"Subcontractor") | D9: =COUNTIFS('Vendor Invoice Log'!$R$4:$R$33,A9,'Vendor Invoice Log'!$D$4:$D$33,"Material Supplier") | E9: =SUMIFS('Vendor Invoice Log'!$P$4:$P$33,'Vendor Invoice Log'!$R$4:$R$33,A9,'Vendor Invoice Log'!$D$4:$D$33,"Material Supplier") | F9: =COUNTIF('Vendor Invoice Log'!$R$4:$R$33,A9)-COUNTIFS('Vendor Invoice Log'!$R$4:$R$33,A9,'Vendor Invoice Log'!$D$4:$D$33,"Subcontractor")-COUNTIFS('Vendor Invoice Log'!$R$4:$R$33,A9,'Vendor Invoice Log'!$D$4:$D$33,"Material Supplier") | G9: =SUMIFS('Vendor Invoice Log'!$P$4:$P$33,'Vendor Invoice Log'!$R$4:$R$33,A9)-SUMIFS('Vendor Invoice Log'!$P$4:$P$33,'Vendor Invoice Log'!$R$4:$R$33,A9,'Vendor Invoice Log'!$D$4:$D$33,"Subcontractor")-SUMIFS('Vendor Invoice Log'!$P$4:$P$33,'Vendor Invoice Log'!$R$4:$R$33,A9,'Vendor Invoice Log'!$D$4:$D$33,"Material Supplier")
A10: TOTAL OUTSTANDING | B10: =SUM(B4:B9) | C10: =SUM(C4:C9) | D10: =SUM(D4:D9) | E10: =SUM(E4:E9) | F10: =SUM(F4:F9) | G10: =SUM(G4:G9)

Sheet Dashboard
A1: Accounts Payable Dashboard
A2: Auto-calculated from Company Info and Vendor Invoice Log. Update those tabs - this one stays in sync. Pay extra attention to the two RISK rows: paying subs without lien waivers and subs on site with expired COIs.
A4: AP Headline
A5: Total Outstanding AP | D5: =SUM('Vendor Invoice Log'!$P$4:$P$33)
A6: Total Retainage Held (from subs) | D6: =SUMIFS('Vendor Invoice Log'!$K$4:$K$33,'Vendor Invoice Log'!$D$4:$D$33,"Subcontractor")
A7: Total Paid YTD | D7: =SUMPRODUCT(('Vendor Invoice Log'!$N$4:$N$33<>"")*(IFERROR(YEAR('Vendor Invoice Log'!$N$4:$N$33),0)=YEAR(TODAY()))*IFERROR('Vendor Invoice Log'!$O$4:$O$33+0,0))
A8: Avg Days to Pay (DPO equivalent) | D8: =IFERROR(SUMPRODUCT(('Vendor Invoice Log'!$N$4:$N$33<>"")*('Vendor Invoice Log'!$B$4:$B$33<>"")*IFERROR('Vendor Invoice Log'!$N$4:$N$33-'Vendor Invoice Log'!$B$4:$B$33,0))/MAX(1,SUMPRODUCT(('Vendor Invoice Log'!$N$4:$N$33<>"")*('Vendor Invoice Log'!$B$4:$B$33<>"")*1)),0)
A10: Risk Flags - These Are Where CFOs Lose Sleep
A11: Subs without current COI (open exposure) | D11: =COUNTIFS('Vendor Invoice Log'!$D$4:$D$33,"Subcontractor",'Vendor Invoice Log'!$T$4:$T$33,"No",'Vendor Invoice Log'!$P$4:$P$33,">0")+COUNTIFS('Vendor Invoice Log'!$D$4:$D$33,"Subcontractor",'Vendor Invoice Log'!$T$4:$T$33,"Expired",'Vendor Invoice Log'!$P$4:$P$33,">0")
A12: Subs paid without lien waiver - count | D12: =COUNTIFS('Vendor Invoice Log'!$D$4:$D$33,"Subcontractor",'Vendor Invoice Log'!$U$4:$U$33,"Paid",'Vendor Invoice Log'!$S$4:$S$33,"None")
A13: Subs paid without lien waiver - $ exposure | D13: =SUMIFS('Vendor Invoice Log'!$O$4:$O$33,'Vendor Invoice Log'!$D$4:$D$33,"Subcontractor",'Vendor Invoice Log'!$U$4:$U$33,"Paid",'Vendor Invoice Log'!$S$4:$S$33,"None")
A15: Aging Breakdown
A16: Aging Bucket | B16: Count | C16: Outstanding
A17: Current | C17: =COUNTIF('Vendor Invoice Log'!$R$4:$R$33,"Current") | D17: =SUMIFS('Vendor Invoice Log'!$P$4:$P$33,'Vendor Invoice Log'!$R$4:$R$33,"Current") | E17: =IFERROR(SUMIFS('Vendor Invoice Log'!$P$4:$P$33,'Vendor Invoice Log'!$R$4:$R$33,"Current")/SUM('Vendor Invoice Log'!$P$4:$P$33),0)
A18: 1-30 | C18: =COUNTIF('Vendor Invoice Log'!$R$4:$R$33,"1-30") | D18: =SUMIFS('Vendor Invoice Log'!$P$4:$P$33,'Vendor Invoice Log'!$R$4:$R$33,"1-30") | E18: =IFERROR(SUMIFS('Vendor Invoice Log'!$P$4:$P$33,'Vendor Invoice Log'!$R$4:$R$33,"1-30")/SUM('Vendor Invoice Log'!$P$4:$P$33),0)
A19: 31-60 | C19: =COUNTIF('Vendor Invoice Log'!$R$4:$R$33,"31-60") | D19: =SUMIFS('Vendor Invoice Log'!$P$4:$P$33,'Vendor Invoice Log'!$R$4:$R$33,"31-60") | E19: =IFERROR(SUMIFS('Vendor Invoice Log'!$P$4:$P$33,'Vendor Invoice Log'!$R$4:$R$33,"31-60")/SUM('Vendor Invoice Log'!$P$4:$P$33),0)
A20: 61-90 | C20: =COUNTIF('Vendor Invoice Log'!$R$4:$R$33,"61-90") | D20: =SUMIFS('Vendor Invoice Log'!$P$4:$P$33,'Vendor Invoice Log'!$R$4:$R$33,"61-90") | E20: =IFERROR(SUMIFS('Vendor Invoice Log'!$P$4:$P$33,'Vendor Invoice Log'!$R$4:$R$33,"61-90")/SUM('Vendor Invoice Log'!$P$4:$P$33),0)
A21: 91-120 | C21: =COUNTIF('Vendor Invoice Log'!$R$4:$R$33,"91-120") | D21: =SUMIFS('Vendor Invoice Log'!$P$4:$P$33,'Vendor Invoice Log'!$R$4:$R$33,"91-120") | E21: =IFERROR(SUMIFS('Vendor Invoice Log'!$P$4:$P$33,'Vendor Invoice Log'!$R$4:$R$33,"91-120")/SUM('Vendor Invoice Log'!$P$4:$P$33),0)
A22: 120+ | C22: =COUNTIF('Vendor Invoice Log'!$R$4:$R$33,"120+") | D22: =SUMIFS('Vendor Invoice Log'!$P$4:$P$33,'Vendor Invoice Log'!$R$4:$R$33,"120+") | E22: =IFERROR(SUMIFS('Vendor Invoice Log'!$P$4:$P$33,'Vendor Invoice Log'!$R$4:$R$33,"120+")/SUM('Vendor Invoice Log'!$P$4:$P$33),0)
A23: TOTAL OUTSTANDING | C23: =COUNTIF('Vendor Invoice Log'!$R$4:$R$33,"Current")+COUNTIF('Vendor Invoice Log'!$R$4:$R$33,"1-30")+COUNTIF('Vendor Invoice Log'!$R$4:$R$33,"31-60")+COUNTIF('Vendor Invoice Log'!$R$4:$R$33,"61-90")+COUNTIF('Vendor Invoice Log'!$R$4:$R$33,"91-120")+COUNTIF('Vendor Invoice Log'!$R$4:$R$33,"120+") | D23: =SUM('Vendor Invoice Log'!$P$4:$P$33) | E23: =1

Sheet CSI Reference
A1: CSI MasterFormat Division Reference
A2: Pulled from the same canonical list as ContrPro Job Costing. Do not edit.
A3: CSI Division | B3: Division Name
A4: 01 | B4: General Requirements
A5: 02 | B5: Existing Conditions
A6: 03 | B6: Concrete
A7: 04 | B7: Masonry
A8: 05 | B8: Metals
A9: 06 | B9: Wood, Plastics, and Composites
A10: 07 | B10: Thermal and Moisture Protection
A11: 08 | B11: Openings
A12: 09 | B12: Finishes
A13: 10 | B13: Specialties
A14: 11 | B14: Equipment
... A38: 49 | B38: Reserved
