Workbook
Name CSI_Divisions: 'CSI Reference'!$A$4:$A$38
Name CSI_Table: 'CSI Reference'!$A$4:$B$38

Sheet Instructions
B2: ContrPro - Change Order Log
B3: CSI MasterFormat-coded log of every change to a construction contract - the receipt drawer for the job.
B5: What this workbook is
B6: Six tabs work together: Project Info pins the contract, Change Order Log is where every CO lives, CO Summary by Division rolls them up by trade, and Dashboard shows contract impact at a glance. CSI Reference is a hidden-ish lookup list - leave it alone.
B7: Every row in Change Order Log is one paper trail: written description, dollar amount, schedule impact, and approval status. If it is not in this log, it did not happen.
B9: Change Order vs Scope Creep vs RFI - know the difference
B10: Change Order (CO) - A WRITTEN amendment to the contract that adjusts price, schedule, or scope. It is bilateral (owner and GC both sign) and binding. This log only tracks COs.
B11: Scope Creep - Owner or architect asks for 'just one more thing' verbally and you do it. DO NOT track scope creep here, track it as a CO the moment you sense it. Verbal is not a CO; verbal is unpaid work waiting to happen.
B12: RFI (Request for Information) - A question to the design team. Not a CO. But the answer often TRIGGERS a CO when the response changes scope or quantities. Log the resulting CO here and reference the RFI number in Notes.
B14: When to issue a formal CO vs a T&M ticket
B15: Formal CO (Lump Sum / Unit Price / Allowance / Deductive) - Use when scope is defined enough to price up-front. Get it signed BEFORE the work starts. This is the cleanest path and protects your margin.
B16: T&M (Time and Material) ticket - Use when scope is unclear or urgent (emergency repair, hidden condition). Track labor hours and material receipts daily, get signed T&M tickets each day, and roll them into a CO weekly. Type = T&M on the row.
... B59: ContrPro - built for builders. Questions: support@contrpro.com

Sheet Project Info
A1: Project Information
A3: Project Name | B3: Project Number | C3: Client | D3: Original Contract Amount | E3: Project Manager | F3: Architect / Engineer | G3: Notes
A4: EXAMPLE - Riverside Office Bldg | B4: 2026-014 | C4: Riverside Holdings LLC | D4: 1850000 | E4: Sample PM | F4: Apex Architects + WSP Structural | G4: Example row - replace with your project.

Sheet Change Order Log
A1: Change Order Log (CSI MasterFormat)
A3: CO Number | B3: Date Issued | C3: Date Approved | D3: Project / Job | E3: CSI Division | F3: CSI Code | G3: Division Name | H3: Description of Change | I3: Reason | J3: Type | K3: Amount | L3: Schedule Impact (days) | M3: Status | N3: Approved By | O3: Notes
A4: CO-001 | B4: 2026-03-12 | C4: 2026-03-18 | D4: Riverside Office Bldg | E4: 03 | F4: 03 30 00 | G4: =IFERROR(VLOOKUP(E4,CSI_Table,2,FALSE),"") | H4: Add 12 CY structural concrete at column footings F-4 to F-7 per RFI-024. | I4: Field Condition | J4: Lump Sum | K4: 8450 | L4: 2 | M4: Approved | N4: K. Holmes (Owner Rep) | O4: Soft soil discovered at depth; required oversized footings.
A5: CO-002 | B5: 2026-03-20 | C5: 2026-03-25 | D5: Riverside Office Bldg | E5: 23 | F5: 23 30 00 | G5: =IFERROR(VLOOKUP(E5,CSI_Table,2,FALSE),"") | H5: Upgrade VAV boxes Level 2 from std to digital controls. | I5: Owner Request | J5: Lump Sum | K5: 14275 | L5: 0 | M5: Approved | N5: K. Holmes (Owner Rep) | O5: Owner spec upgrade after value-engineering pass.
A6: CO-003 | B6: 2026-04-02 | D6: Riverside Office Bldg | E6: 09 | F6: 09 60 00 | G6: =IFERROR(VLOOKUP(E6,CSI_Table,2,FALSE),"") | H6: Substitute LVT flooring for spec'd carpet tile in open office. | I6: Owner Request | J6: Deductive | K6: -6320 | L6: 0 | M6: Pending | O6: Awaiting owner sign-off on LVT sample.
A7: CO-004 | B7: 2026-04-10 | C7: 2026-04-15 | D7: Riverside Office Bldg | E7: 26 | F7: 26 50 00 | G7: =IFERROR(VLOOKUP(E7,CSI_Table,2,FALSE),"") | H7: Add emergency lighting at stair towers per code review. | I7: Code Change | J7: T&M | K7: 3940 | L7: 1 | M7: Approved | N7: K. Holmes (Owner Rep) | O7: Updated IBC interpretation from building dept.
A8: CO-005 | B8: 2026-04-22 | D8: Riverside Office Bldg | E8: 07 | F8: 07 50 00 | G8: =IFERROR(VLOOKUP(E8,CSI_Table,2,FALSE),"") | H8: Replace damaged membrane after wind event (40 sq). | I8: Force Majeure | J8: Unit Price | K8: 11200 | L8: 5 | M8: Submitted | O8: Wind event 2026-04-19; insurance claim filed in parallel.
G9: =IFERROR(VLOOKUP(E9,CSI_Table,2,FALSE),"")
G10: =IFERROR(VLOOKUP(E10,CSI_Table,2,FALSE),"")
G11: =IFERROR(VLOOKUP(E11,CSI_Table,2,FALSE),"")
G12: =IFERROR(VLOOKUP(E12,CSI_Table,2,FALSE),"")
G13: =IFERROR(VLOOKUP(E13,CSI_Table,2,FALSE),"")
G14: =IFERROR(VLOOKUP(E14,CSI_Table,2,FALSE),"")
G15: =IFERROR(VLOOKUP(E15,CSI_Table,2,FALSE),"")
G16: =IFERROR(VLOOKUP(E16,CSI_Table,2,FALSE),"")
G17: =IFERROR(VLOOKUP(E17,CSI_Table,2,FALSE),"")
G18: =IFERROR(VLOOKUP(E18,CSI_Table,2,FALSE),"")
G19: =IFERROR(VLOOKUP(E19,CSI_Table,2,FALSE),"")
G20: =IFERROR(VLOOKUP(E20,CSI_Table,2,FALSE),"")
... G28: =IFERROR(VLOOKUP(E28,CSI_Table,2,FALSE),"")
J30: TOTALS | K30: =SUM(K4:K28) | L30: =SUM(L4:L28)

Sheet CO Summary by Division
A1: CO Summary by Division (auto roll-up)
A2: Reads from Change Order Log via SUMIFS - do not edit this tab directly. One row per CSI Division.
A3: CSI Division | B3: Division Name | C3: CO Count | D3: Approved Amount | E3: Pending Amount | F3: Rejected Amount | G3: Net Approved Amount | H3: Schedule Impact (Approved)
A4: 01 | B4: General Requirements | C4: =COUNTIF('Change Order Log'!$E$4:$E$28,A4) | D4: =SUMIFS('Change Order Log'!$K$4:$K$28,'Change Order Log'!$E$4:$E$28,A4,'Change Order Log'!$M$4:$M$28,"Approved") | E4: =SUMIFS('Change Order Log'!$K$4:$K$28,'Change Order Log'!$E$4:$E$28,A4,'Change Order Log'!$M$4:$M$28,"Pending")+SUMIFS('Change Order Log'!$K$4:$K$28,'Change Order Log'!$E$4:$E$28,A4,'Change Order Log'!$M$4:$M$28,"Submitted") | F4: =SUMIFS('Change Order Log'!$K$4:$K$28,'Change Order Log'!$E$4:$E$28,A4,'Change Order Log'!$M$4:$M$28,"Rejected") | G4: =SUMIFS('Change Order Log'!$K$4:$K$28,'Change Order Log'!$E$4:$E$28,A4,'Change Order Log'!$M$4:$M$28,"Approved") | H4: =SUMIFS('Change Order Log'!$L$4:$L$28,'Change Order Log'!$E$4:$E$28,A4,'Change Order Log'!$M$4:$M$28,"Approved")
A5: 02 | B5: Existing Conditions | C5: =COUNTIF('Change Order Log'!$E$4:$E$28,A5) | D5: =SUMIFS('Change Order Log'!$K$4:$K$28,'Change Order Log'!$E$4:$E$28,A5,'Change Order Log'!$M$4:$M$28,"Approved") | E5: =SUMIFS('Change Order Log'!$K$4:$K$28,'Change Order Log'!$E$4:$E$28,A5,'Change Order Log'!$M$4:$M$28,"Pending")+SUMIFS('Change Order Log'!$K$4:$K$28,'Change Order Log'!$E$4:$E$28,A5,'Change Order Log'!$M$4:$M$28,"Submitted") | F5: =SUMIFS('Change Order Log'!$K$4:$K$28,'Change Order Log'!$E$4:$E$28,A5,'Change Order Log'!$M$4:$M$28,"Rejected") | G5: =SUMIFS('Change Order Log'!$K$4:$K$28,'Change Order Log'!$E$4:$E$28,A5,'Change Order Log'!$M$4:$M$28,"Approved") | H5: =SUMIFS('Change Order Log'!$L$4:$L$28,'Change Order Log'!$E$4:$E$28,A5,'Change Order Log'!$M$4:$M$28,"Approved")
A6: 03 | B6: Concrete | C6: =COUNTIF('Change Order Log'!$E$4:$E$28,A6) | D6: =SUMIFS('Change Order Log'!$K$4:$K$28,'Change Order Log'!$E$4:$E$28,A6,'Change Order Log'!$M$4:$M$28,"Approved") | E6: =SUMIFS('Change Order Log'!$K$4:$K$28,'Change Order Log'!$E$4:$E$28,A6,'Change Order Log'!$M$4:$M$28,"Pending")+SUMIFS('Change Order Log'!$K$4:$K$28,'Change Order Log'!$E$4:$E$28,A6,'Change Order Log'!$M$4:$M$28,"Submitted") | F6: =SUMIFS('Change Order Log'!$K$4:$K$28,'Change Order Log'!$E$4:$E$28,A6,'Change Order Log'!$M$4:$M$28,"Rejected") | G6: =SUMIFS('Change Order Log'!$K$4:$K$28,'Change Order Log'!$E$4:$E$28,A6,'Change Order Log'!$M$4:$M$28,"Approved") | H6: =SUMIFS('Change Order Log'!$L$4:$L$28,'Change Order Log'!$E$4:$E$28,A6,'Change Order Log'!$M$4:$M$28,"Approved")
A7: 04 | B7: Masonry | C7: =COUNTIF('Change Order Log'!$E$4:$E$28,A7) | D7: =SUMIFS('Change Order Log'!$K$4:$K$28,'Change Order Log'!$E$4:$E$28,A7,'Change Order Log'!$M$4:$M$28,"Approved") | E7: =SUMIFS('Change Order Log'!$K$4:$K$28,'Change Order Log'!$E$4:$E$28,A7,'Change Order Log'!$M$4:$M$28,"Pending")+SUMIFS('Change Order Log'!$K$4:$K$28,'Change Order Log'!$E$4:$E$28,A7,'Change Order Log'!$M$4:$M$28,"Submitted") | F7: =SUMIFS('Change Order Log'!$K$4:$K$28,'Change Order Log'!$E$4:$E$28,A7,'Change Order Log'!$M$4:$M$28,"Rejected") | G7: =SUMIFS('Change Order Log'!$K$4:$K$28,'Change Order Log'!$E$4:$E$28,A7,'Change Order Log'!$M$4:$M$28,"Approved") | H7: =SUMIFS('Change Order Log'!$L$4:$L$28,'Change Order Log'!$E$4:$E$28,A7,'Change Order Log'!$M$4:$M$28,"Approved")
A8: 05 | B8: Metals | C8: =COUNTIF('Change Order Log'!$E$4:$E$28,A8) | D8: =SUMIFS('Change Order Log'!$K$4:$K$28,'Change Order Log'!$E$4:$E$28,A8,'Change Order Log'!$M$4:$M$28,"Approved") | E8: =SUMIFS('Change Order Log'!$K$4:$K$28,'Change Order Log'!$E$4:$E$28,A8,'Change Order Log'!$M$4:$M$28,"Pending")+SUMIFS('Change Order Log'!$K$4:$K$28,'Change Order Log'!$E$4:$E$28,A8,'Change Order Log'!$M$4:$M$28,"Submitted") | F8: =SUMIFS('Change Order Log'!$K$4:$K$28,'Change Order Log'!$E$4:$E$28,A8,'Change Order Log'!$M$4:$M$28,"Rejected") | G8: =SUMIFS('Change Order Log'!$K$4:$K$28,'Change Order Log'!$E$4:$E$28,A8,'Change Order Log'!$M$4:$M$28,"Approved") | H8: =SUMIFS('Change Order Log'!$L$4:$L$28,'Change Order Log'!$E$4:$E$28,A8,'Change Order Log'!$M$4:$M$28,"Approved")
A9: 06 | B9: Wood, Plastics, and Composites | C9: =COUNTIF('Change Order Log'!$E$4:$E$28,A9) | D9: =SUMIFS('Change Order Log'!$K$4:$K$28,'Change Order Log'!$E$4:$E$28,A9,'Change Order Log'!$M$4:$M$28,"Approved") | E9: =SUMIFS('Change Order Log'!$K$4:$K$28,'Change Order Log'!$E$4:$E$28,A9,'Change Order Log'!$M$4:$M$28,"Pending")+SUMIFS('Change Order Log'!$K$4:$K$28,'Change Order Log'!$E$4:$E$28,A9,'Change Order Log'!$M$4:$M$28,"Submitted") | F9: =SUMIFS('Change Order Log'!$K$4:$K$28,'Change Order Log'!$E$4:$E$28,A9,'Change Order Log'!$M$4:$M$28,"Rejected") | G9: =SUMIFS('Change Order Log'!$K$4:$K$28,'Change Order Log'!$E$4:$E$28,A9,'Change Order Log'!$M$4:$M$28,"Approved") | H9: =SUMIFS('Change Order Log'!$L$4:$L$28,'Change Order Log'!$E$4:$E$28,A9,'Change Order Log'!$M$4:$M$28,"Approved")
A10: 07 | B10: Thermal and Moisture Protection | C10: =COUNTIF('Change Order Log'!$E$4:$E$28,A10) | D10: =SUMIFS('Change Order Log'!$K$4:$K$28,'Change Order Log'!$E$4:$E$28,A10,'Change Order Log'!$M$4:$M$28,"Approved") | E10: =SUMIFS('Change Order Log'!$K$4:$K$28,'Change Order Log'!$E$4:$E$28,A10,'Change Order Log'!$M$4:$M$28,"Pending")+SUMIFS('Change Order Log'!$K$4:$K$28,'Change Order Log'!$E$4:$E$28,A10,'Change Order Log'!$M$4:$M$28,"Submitted") | F10: =SUMIFS('Change Order Log'!$K$4:$K$28,'Change Order Log'!$E$4:$E$28,A10,'Change Order Log'!$M$4:$M$28,"Rejected") | G10: =SUMIFS('Change Order Log'!$K$4:$K$28,'Change Order Log'!$E$4:$E$28,A10,'Change Order Log'!$M$4:$M$28,"Approved") | H10: =SUMIFS('Change Order Log'!$L$4:$L$28,'Change Order Log'!$E$4:$E$28,A10,'Change Order Log'!$M$4:$M$28,"Approved")
A11: 08 | B11: Openings | C11: =COUNTIF('Change Order Log'!$E$4:$E$28,A11) | D11: =SUMIFS('Change Order Log'!$K$4:$K$28,'Change Order Log'!$E$4:$E$28,A11,'Change Order Log'!$M$4:$M$28,"Approved") | E11: =SUMIFS('Change Order Log'!$K$4:$K$28,'Change Order Log'!$E$4:$E$28,A11,'Change Order Log'!$M$4:$M$28,"Pending")+SUMIFS('Change Order Log'!$K$4:$K$28,'Change Order Log'!$E$4:$E$28,A11,'Change Order Log'!$M$4:$M$28,"Submitted") | F11: =SUMIFS('Change Order Log'!$K$4:$K$28,'Change Order Log'!$E$4:$E$28,A11,'Change Order Log'!$M$4:$M$28,"Rejected") | G11: =SUMIFS('Change Order Log'!$K$4:$K$28,'Change Order Log'!$E$4:$E$28,A11,'Change Order Log'!$M$4:$M$28,"Approved") | H11: =SUMIFS('Change Order Log'!$L$4:$L$28,'Change Order Log'!$E$4:$E$28,A11,'Change Order Log'!$M$4:$M$28,"Approved")
A12: 09 | B12: Finishes | C12: =COUNTIF('Change Order Log'!$E$4:$E$28,A12) | D12: =SUMIFS('Change Order Log'!$K$4:$K$28,'Change Order Log'!$E$4:$E$28,A12,'Change Order Log'!$M$4:$M$28,"Approved") | E12: =SUMIFS('Change Order Log'!$K$4:$K$28,'Change Order Log'!$E$4:$E$28,A12,'Change Order Log'!$M$4:$M$28,"Pending")+SUMIFS('Change Order Log'!$K$4:$K$28,'Change Order Log'!$E$4:$E$28,A12,'Change Order Log'!$M$4:$M$28,"Submitted") | F12: =SUMIFS('Change Order Log'!$K$4:$K$28,'Change Order Log'!$E$4:$E$28,A12,'Change Order Log'!$M$4:$M$28,"Rejected") | G12: =SUMIFS('Change Order Log'!$K$4:$K$28,'Change Order Log'!$E$4:$E$28,A12,'Change Order Log'!$M$4:$M$28,"Approved") | H12: =SUMIFS('Change Order Log'!$L$4:$L$28,'Change Order Log'!$E$4:$E$28,A12,'Change Order Log'!$M$4:$M$28,"Approved")
A13: 10 | B13: Specialties | C13: =COUNTIF('Change Order Log'!$E$4:$E$28,A13) | D13: =SUMIFS('Change Order Log'!$K$4:$K$28,'Change Order Log'!$E$4:$E$28,A13,'Change Order Log'!$M$4:$M$28,"Approved") | E13: =SUMIFS('Change Order Log'!$K$4:$K$28,'Change Order Log'!$E$4:$E$28,A13,'Change Order Log'!$M$4:$M$28,"Pending")+SUMIFS('Change Order Log'!$K$4:$K$28,'Change Order Log'!$E$4:$E$28,A13,'Change Order Log'!$M$4:$M$28,"Submitted") | F13: =SUMIFS('Change Order Log'!$K$4:$K$28,'Change Order Log'!$E$4:$E$28,A13,'Change Order Log'!$M$4:$M$28,"Rejected") | G13: =SUMIFS('Change Order Log'!$K$4:$K$28,'Change Order Log'!$E$4:$E$28,A13,'Change Order Log'!$M$4:$M$28,"Approved") | H13: =SUMIFS('Change Order Log'!$L$4:$L$28,'Change Order Log'!$E$4:$E$28,A13,'Change Order Log'!$M$4:$M$28,"Approved")
A14: 11 | B14: Equipment | C14: =COUNTIF('Change Order Log'!$E$4:$E$28,A14) | D14: =SUMIFS('Change Order Log'!$K$4:$K$28,'Change Order Log'!$E$4:$E$28,A14,'Change Order Log'!$M$4:$M$28,"Approved") | E14: =SUMIFS('Change Order Log'!$K$4:$K$28,'Change Order Log'!$E$4:$E$28,A14,'Change Order Log'!$M$4:$M$28,"Pending")+SUMIFS('Change Order Log'!$K$4:$K$28,'Change Order Log'!$E$4:$E$28,A14,'Change Order Log'!$M$4:$M$28,"Submitted") | F14: =SUMIFS('Change Order Log'!$K$4:$K$28,'Change Order Log'!$E$4:$E$28,A14,'Change Order Log'!$M$4:$M$28,"Rejected") | G14: =SUMIFS('Change Order Log'!$K$4:$K$28,'Change Order Log'!$E$4:$E$28,A14,'Change Order Log'!$M$4:$M$28,"Approved") | H14: =SUMIFS('Change Order Log'!$L$4:$L$28,'Change Order Log'!$E$4:$E$28,A14,'Change Order Log'!$M$4:$M$28,"Approved")
A15: 12 | B15: Furnishings | C15: =COUNTIF('Change Order Log'!$E$4:$E$28,A15) | D15: =SUMIFS('Change Order Log'!$K$4:$K$28,'Change Order Log'!$E$4:$E$28,A15,'Change Order Log'!$M$4:$M$28,"Approved") | E15: =SUMIFS('Change Order Log'!$K$4:$K$28,'Change Order Log'!$E$4:$E$28,A15,'Change Order Log'!$M$4:$M$28,"Pending")+SUMIFS('Change Order Log'!$K$4:$K$28,'Change Order Log'!$E$4:$E$28,A15,'Change Order Log'!$M$4:$M$28,"Submitted") | F15: =SUMIFS('Change Order Log'!$K$4:$K$28,'Change Order Log'!$E$4:$E$28,A15,'Change Order Log'!$M$4:$M$28,"Rejected") | G15: =SUMIFS('Change Order Log'!$K$4:$K$28,'Change Order Log'!$E$4:$E$28,A15,'Change Order Log'!$M$4:$M$28,"Approved") | H15: =SUMIFS('Change Order Log'!$L$4:$L$28,'Change Order Log'!$E$4:$E$28,A15,'Change Order Log'!$M$4:$M$28,"Approved")
... A38: 49 | B38: Reserved | C38: =COUNTIF('Change Order Log'!$E$4:$E$28,A38) | D38: =SUMIFS('Change Order Log'!$K$4:$K$28,'Change Order Log'!$E$4:$E$28,A38,'Change Order Log'!$M$4:$M$28,"Approved") | E38: =SUMIFS('Change Order Log'!$K$4:$K$28,'Change Order Log'!$E$4:$E$28,A38,'Change Order Log'!$M$4:$M$28,"Pending")+SUMIFS('Change Order Log'!$K$4:$K$28,'Change Order Log'!$E$4:$E$28,A38,'Change Order Log'!$M$4:$M$28,"Submitted") | F38: =SUMIFS('Change Order Log'!$K$4:$K$28,'Change Order Log'!$E$4:$E$28,A38,'Change Order Log'!$M$4:$M$28,"Rejected") | G38: =SUMIFS('Change Order Log'!$K$4:$K$28,'Change Order Log'!$E$4:$E$28,A38,'Change Order Log'!$M$4:$M$28,"Approved") | H38: =SUMIFS('Change Order Log'!$L$4:$L$28,'Change Order Log'!$E$4:$E$28,A38,'Change Order Log'!$M$4:$M$28,"Approved")
B40: TOTALS | C40: =SUM(C4:C38) | D40: =SUM(D4:D38) | E40: =SUM(E4:E38) | F40: =SUM(F4:F38) | G40: =SUM(G4:G38) | H40: =SUM(H4:H38)

Sheet Dashboard
A1: Change Order Dashboard
A2: Auto-calculated from Project Info and Change Order Log. Update those tabs - this one stays in sync.
A4: Contract Impact
A5: Original Contract Amount | D5: ='Project Info'!D4
A6: Total Approved CO Amount | D6: =SUMIF('Change Order Log'!$M$4:$M$28,"Approved",'Change Order Log'!$K$4:$K$28)
A7: Total Pending CO Amount | D7: =SUMIF('Change Order Log'!$M$4:$M$28,"Pending",'Change Order Log'!$K$4:$K$28)+SUMIF('Change Order Log'!$M$4:$M$28,"Submitted",'Change Order Log'!$K$4:$K$28)
A8: Total Rejected CO Amount | D8: =SUMIF('Change Order Log'!$M$4:$M$28,"Rejected",'Change Order Log'!$K$4:$K$28)
A9: Adjusted Contract Amount (Original + Approved) | D9: ='Project Info'!D4+SUMIF('Change Order Log'!$M$4:$M$28,"Approved",'Change Order Log'!$K$4:$K$28)
A10: Approved CO % of Original Contract | D10: =IFERROR(SUMIF('Change Order Log'!$M$4:$M$28,"Approved",'Change Order Log'!$K$4:$K$28)/'Project Info'!D4,0)
A11: Total Schedule Impact - Approved (days) | D11: =SUMIF('Change Order Log'!$M$4:$M$28,"Approved",'Change Order Log'!$L$4:$L$28)
A14: CO Counts by Status
A15: Status | B15: Count | C15: Amount | D15: % of Total CO $
A16: Approved | C16: =COUNTIF('Change Order Log'!$M$4:$M$28,"Approved") | D16: =SUMIF('Change Order Log'!$M$4:$M$28,"Approved",'Change Order Log'!$K$4:$K$28) | E16: =IFERROR(SUMIF('Change Order Log'!$M$4:$M$28,"Approved",'Change Order Log'!$K$4:$K$28)/SUMIF('Change Order Log'!$M$4:$M$28,"<>",'Change Order Log'!$K$4:$K$28),0)
A17: Pending | C17: =COUNTIF('Change Order Log'!$M$4:$M$28,"Pending") | D17: =SUMIF('Change Order Log'!$M$4:$M$28,"Pending",'Change Order Log'!$K$4:$K$28) | E17: =IFERROR(SUMIF('Change Order Log'!$M$4:$M$28,"Pending",'Change Order Log'!$K$4:$K$28)/SUMIF('Change Order Log'!$M$4:$M$28,"<>",'Change Order Log'!$K$4:$K$28),0)
A18: Submitted | C18: =COUNTIF('Change Order Log'!$M$4:$M$28,"Submitted") | D18: =SUMIF('Change Order Log'!$M$4:$M$28,"Submitted",'Change Order Log'!$K$4:$K$28) | E18: =IFERROR(SUMIF('Change Order Log'!$M$4:$M$28,"Submitted",'Change Order Log'!$K$4:$K$28)/SUMIF('Change Order Log'!$M$4:$M$28,"<>",'Change Order Log'!$K$4:$K$28),0)
A19: Rejected | C19: =COUNTIF('Change Order Log'!$M$4:$M$28,"Rejected") | D19: =SUMIF('Change Order Log'!$M$4:$M$28,"Rejected",'Change Order Log'!$K$4:$K$28) | E19: =IFERROR(SUMIF('Change Order Log'!$M$4:$M$28,"Rejected",'Change Order Log'!$K$4:$K$28)/SUMIF('Change Order Log'!$M$4:$M$28,"<>",'Change Order Log'!$K$4:$K$28),0)
A20: Disputed | C20: =COUNTIF('Change Order Log'!$M$4:$M$28,"Disputed") | D20: =SUMIF('Change Order Log'!$M$4:$M$28,"Disputed",'Change Order Log'!$K$4:$K$28) | E20: =IFERROR(SUMIF('Change Order Log'!$M$4:$M$28,"Disputed",'Change Order Log'!$K$4:$K$28)/SUMIF('Change Order Log'!$M$4:$M$28,"<>",'Change Order Log'!$K$4:$K$28),0)
A21: Voided | C21: =COUNTIF('Change Order Log'!$M$4:$M$28,"Voided") | D21: =SUMIF('Change Order Log'!$M$4:$M$28,"Voided",'Change Order Log'!$K$4:$K$28) | E21: =IFERROR(SUMIF('Change Order Log'!$M$4:$M$28,"Voided",'Change Order Log'!$K$4:$K$28)/SUMIF('Change Order Log'!$M$4:$M$28,"<>",'Change Order Log'!$K$4:$K$28),0)
A23: ALL COs (any status) | C23: =COUNTA('Change Order Log'!$A$4:$A$28) | D23: =SUM('Change Order Log'!$K$4:$K$28) | E23: =1

Sheet CSI Reference
A1: CSI MasterFormat Division Reference
A2: Pulled from the same canonical list as ContrPro Job Costing. Do not edit.
A3: CSI Division | B3: Division Name
A4: 01 | B4: General Requirements
A5: 02 | B5: Existing Conditions
A6: 03 | B6: Concrete
A7: 04 | B7: Masonry
A8: 05 | B8: Metals
A9: 06 | B9: Wood, Plastics, and Composites
A10: 07 | B10: Thermal and Moisture Protection
A11: 08 | B11: Openings
A12: 09 | B12: Finishes
A13: 10 | B13: Specialties
A14: 11 | B14: Equipment
... A38: 49 | B38: Reserved
