Workbook
Name CSI_Divisions: 'CSI Reference'!$A$4:$A$38
Name CSI_Table: 'CSI Reference'!$A$4:$B$38
Name States_List: 'CSI Reference'!$D$4:$D$54

Sheet Instructions
B2: ContrPro - Project Tracker (Portfolio View)
B3: Portfolio-level tracker for every open job at once. The view a GC owner needs Monday morning.
B5: What this workbook is (and what it is NOT)
B6: This is a PORTFOLIO tracker - one row per project, all your active jobs in one view. Use Job_Costing_Spreadsheet.xlsx (per-job, CSI-coded) for the deep cost detail on any single job. Use Change_Order_Log.xlsx for the CO paper trail. This file is the bird's-eye view.
B7: Six tabs work together: Company Info pins your company metadata, Project Portfolio holds the rows, Portfolio Summary by Status auto-rolls, and Dashboard surfaces the KPIs that matter. CSI Reference is hidden - it feeds the dropdowns.
B9: KPIs explained (read this once - it changes how you use this file)
B10: Backlog = Adjusted Contract minus Earned Value. The work you have under contract but haven't billed yet. This is what banks and bonding companies care about most. Healthy backlog = 6-12 months of revenue at your current burn rate.
B11: Burn Rate = Cost to Date divided by elapsed days. Tells you how fast a job is consuming cash. Compare against EAC / total duration to spot jobs that are eating themselves.
B12: Projected Margin % = (Adjusted Contract - Estimated Cost at Completion) / Adjusted Contract. Green > 10%, yellow 0-10%, RED < 0. A red row means you are losing money on that job - call your PM today.
B13: % Complete = self-reported field assessment, dollar-weighted on the Dashboard. Use the field PM's number, not a calculated one - the gap between field % and earned % is a leading indicator of trouble.
B14: Earned Value = Adjusted Contract * %Complete. This is what you SHOULD have billed by now if your schedule of values is honest.
B16: How to use the Project Portfolio tab
... B49: ContrPro - built for builders. Questions: support@contrpro.com

Sheet Company Info
A1: Company Information
A2: Shared metadata referenced by future ContrPro workbooks (COI, Subcontractor, etc.).
A3: Company Name | B3: EIN | C3: Primary State | D3: Workers' Comp Carrier | E3: Bond Carrier | F3: GL Carrier | G3: Notes
A4: EXAMPLE - Carolina Builders LLC | B4: 00-0000000 | C4: TN | D4: Travelers (WC) | E4: Liberty Mutual Surety | F4: The Hartford (GL) | G4: Example row - replace with your company info.

Sheet Project Portfolio
A1: Project Portfolio (one row per job)
A3: Project Number | B3: Project Name | C3: Client | D3: Project Type | E3: Primary CSI Division | F3: State | G3: City | H3: Start Date | I3: Target Completion | J3: Actual Completion | K3: Status | L3: Contract Amount | M3: Approved CO Net | N3: Adjusted Contract | O3: Cost to Date | P3: Estimated Cost at Completion | Q3: Projected Gross Margin | R3: Projected Margin % | S3: % Complete | T3: Earned Value | U3: Backlog | V3: Project Manager | W3: Notes
A4: 2026-014 | B4: Riverside Office Bldg | C4: Riverside Holdings LLC | D4: New Construction | E4: 03 | F4: TN | G4: Knoxville | H4: 2026-03-01 | I4: 2026-11-30 | K4: Active | L4: 1850000 | M4: 22725 | N4: =IFERROR(L4+M4,0) | O4: 540000 | P4: 1720000 | Q4: =IFERROR(N4-P4,0) | R4: =IFERROR(Q4/N4,0) | S4: 30 | T4: =IFERROR(N4*S4/100,0) | U4: =IFERROR(N4-T4,0) | V4: M. Reyes | W4: On schedule; concrete topping out next month.
A5: 2026-021 | B5: Maple Plaza TI Buildout | C5: Maple Capital Partners | D5: Tenant Improvement | E5: 09 | F5: TN | G5: Nashville | H5: 2026-04-15 | I5: 2026-09-15 | K5: Mobilizing | L5: 425000 | M5: 0 | N5: =IFERROR(L5+M5,0) | O5: 18000 | P5: 390000 | Q5: =IFERROR(N5-P5,0) | R5: =IFERROR(Q5/N5,0) | S5: 5 | T5: =IFERROR(N5*S5/100,0) | U5: =IFERROR(N5-T5,0) | V5: M. Reyes | W5: Permits in hand; demo starts next week.
A6: 2026-009 | B6: Hillcrest Medical Remodel | C6: Hillcrest Health System | D6: Remodel | E6: 23 | F6: GA | G6: Atlanta | H6: 2026-01-10 | I6: 2026-04-30 | J6: 2026-05-08 | K6: Substantial Completion | L6: 1240000 | M6: 41200 | N6: =IFERROR(L6+M6,0) | O6: 1198000 | P6: 1215000 | Q6: =IFERROR(N6-P6,0) | R6: =IFERROR(Q6/N6,0) | S6: 98 | T6: =IFERROR(N6*S6/100,0) | U6: =IFERROR(N6-T6,0) | V6: S. Patel | W6: Punchlist in progress; final inspection scheduled.
A7: 2026-027 | B7: Eastside Warehouse Roof Repair | C7: Eastside Logistics Inc | D7: Repair | E7: 07 | F7: AL | G7: Birmingham | H7: 2026-05-05 | I7: 2026-05-20 | K7: Awarded | L7: 87500 | M7: 0 | N7: =IFERROR(L7+M7,0) | O7: 0 | P7: 76000 | Q7: =IFERROR(N7-P7,0) | R7: =IFERROR(Q7/N7,0) | S7: 0 | T7: =IFERROR(N7*S7/100,0) | U7: =IFERROR(N7-T7,0) | V7: J. Cole | W7: Insurance claim cleared; mob next Monday.
A8: 2026-031 | B8: Civic Center Expansion (BID) | C8: City of Greenville | D8: New Construction | E8: 01 | F8: SC | G8: Greenville | K8: Bidding | L8: 0 | M8: 0 | N8: =IFERROR(L8+M8,0) | O8: 0 | P8: 0 | Q8: =IFERROR(N8-P8,0) | R8: =IFERROR(Q8/N8,0) | S8: 0 | T8: =IFERROR(N8*S8/100,0) | U8: =IFERROR(N8-T8,0) | V8: M. Reyes | W8: Bid due 2026-06-02; preconstruction cost estimate $4.2M.
N9: =IFERROR(L9+M9,0) | Q9: =IFERROR(N9-P9,0) | R9: =IFERROR(Q9/N9,0) | T9: =IFERROR(N9*S9/100,0) | U9: =IFERROR(N9-T9,0)
N10: =IFERROR(L10+M10,0) | Q10: =IFERROR(N10-P10,0) | R10: =IFERROR(Q10/N10,0) | T10: =IFERROR(N10*S10/100,0) | U10: =IFERROR(N10-T10,0)
N11: =IFERROR(L11+M11,0) | Q11: =IFERROR(N11-P11,0) | R11: =IFERROR(Q11/N11,0) | T11: =IFERROR(N11*S11/100,0) | U11: =IFERROR(N11-T11,0)
N12: =IFERROR(L12+M12,0) | Q12: =IFERROR(N12-P12,0) | R12: =IFERROR(Q12/N12,0) | T12: =IFERROR(N12*S12/100,0) | U12: =IFERROR(N12-T12,0)
N13: =IFERROR(L13+M13,0) | Q13: =IFERROR(N13-P13,0) | R13: =IFERROR(Q13/N13,0) | T13: =IFERROR(N13*S13/100,0) | U13: =IFERROR(N13-T13,0)
N14: =IFERROR(L14+M14,0) | Q14: =IFERROR(N14-P14,0) | R14: =IFERROR(Q14/N14,0) | T14: =IFERROR(N14*S14/100,0) | U14: =IFERROR(N14-T14,0)
N15: =IFERROR(L15+M15,0) | Q15: =IFERROR(N15-P15,0) | R15: =IFERROR(Q15/N15,0) | T15: =IFERROR(N15*S15/100,0) | U15: =IFERROR(N15-T15,0)
N16: =IFERROR(L16+M16,0) | Q16: =IFERROR(N16-P16,0) | R16: =IFERROR(Q16/N16,0) | T16: =IFERROR(N16*S16/100,0) | U16: =IFERROR(N16-T16,0)
N17: =IFERROR(L17+M17,0) | Q17: =IFERROR(N17-P17,0) | R17: =IFERROR(Q17/N17,0) | T17: =IFERROR(N17*S17/100,0) | U17: =IFERROR(N17-T17,0)
N18: =IFERROR(L18+M18,0) | Q18: =IFERROR(N18-P18,0) | R18: =IFERROR(Q18/N18,0) | T18: =IFERROR(N18*S18/100,0) | U18: =IFERROR(N18-T18,0)
N19: =IFERROR(L19+M19,0) | Q19: =IFERROR(N19-P19,0) | R19: =IFERROR(Q19/N19,0) | T19: =IFERROR(N19*S19/100,0) | U19: =IFERROR(N19-T19,0)
N20: =IFERROR(L20+M20,0) | Q20: =IFERROR(N20-P20,0) | R20: =IFERROR(Q20/N20,0) | T20: =IFERROR(N20*S20/100,0) | U20: =IFERROR(N20-T20,0)
... N28: =IFERROR(L28+M28,0) | Q28: =IFERROR(N28-P28,0) | R28: =IFERROR(Q28/N28,0) | T28: =IFERROR(N28*S28/100,0) | U28: =IFERROR(N28-T28,0)
K30: TOTALS | L30: =SUM(L4:L28) | M30: =SUM(M4:M28) | N30: =SUM(N4:N28) | O30: =SUM(O4:O28) | P30: =SUM(P4:P28) | Q30: =SUM(Q4:Q28) | R30: =IFERROR(SUM(Q4:Q28)/SUM(N4:N28),0) | S30: =IFERROR(SUMPRODUCT(N4:N28,S4:S28)/SUM(N4:N28),0) | T30: =SUM(T4:T28) | U30: =SUM(U4:U28)

Sheet Portfolio Summary by Status
A1: Portfolio Summary by Status (auto roll-up)
A2: Reads from Project Portfolio via COUNTIF/SUMIFS - do not edit. One row per status bucket.
A3: Status | B3: Count | C3: Total Contract | D3: Total Earned Value | E3: Total Cost to Date | F3: Total Backlog | G3: Avg Margin %
A4: Bidding | B4: =COUNTIF('Project Portfolio'!$K$4:$K$28,A4) | C4: =SUMIFS('Project Portfolio'!$N$4:$N$28,'Project Portfolio'!$K$4:$K$28,A4) | D4: =SUMIFS('Project Portfolio'!$T$4:$T$28,'Project Portfolio'!$K$4:$K$28,A4) | E4: =SUMIFS('Project Portfolio'!$O$4:$O$28,'Project Portfolio'!$K$4:$K$28,A4) | F4: =SUMIFS('Project Portfolio'!$U$4:$U$28,'Project Portfolio'!$K$4:$K$28,A4) | G4: =IFERROR(AVERAGEIFS('Project Portfolio'!$R$4:$R$28,'Project Portfolio'!$K$4:$K$28,A4,'Project Portfolio'!$N$4:$N$28,">0"),0)
A5: Awarded | B5: =COUNTIF('Project Portfolio'!$K$4:$K$28,A5) | C5: =SUMIFS('Project Portfolio'!$N$4:$N$28,'Project Portfolio'!$K$4:$K$28,A5) | D5: =SUMIFS('Project Portfolio'!$T$4:$T$28,'Project Portfolio'!$K$4:$K$28,A5) | E5: =SUMIFS('Project Portfolio'!$O$4:$O$28,'Project Portfolio'!$K$4:$K$28,A5) | F5: =SUMIFS('Project Portfolio'!$U$4:$U$28,'Project Portfolio'!$K$4:$K$28,A5) | G5: =IFERROR(AVERAGEIFS('Project Portfolio'!$R$4:$R$28,'Project Portfolio'!$K$4:$K$28,A5,'Project Portfolio'!$N$4:$N$28,">0"),0)
A6: Mobilizing | B6: =COUNTIF('Project Portfolio'!$K$4:$K$28,A6) | C6: =SUMIFS('Project Portfolio'!$N$4:$N$28,'Project Portfolio'!$K$4:$K$28,A6) | D6: =SUMIFS('Project Portfolio'!$T$4:$T$28,'Project Portfolio'!$K$4:$K$28,A6) | E6: =SUMIFS('Project Portfolio'!$O$4:$O$28,'Project Portfolio'!$K$4:$K$28,A6) | F6: =SUMIFS('Project Portfolio'!$U$4:$U$28,'Project Portfolio'!$K$4:$K$28,A6) | G6: =IFERROR(AVERAGEIFS('Project Portfolio'!$R$4:$R$28,'Project Portfolio'!$K$4:$K$28,A6,'Project Portfolio'!$N$4:$N$28,">0"),0)
A7: Active | B7: =COUNTIF('Project Portfolio'!$K$4:$K$28,A7) | C7: =SUMIFS('Project Portfolio'!$N$4:$N$28,'Project Portfolio'!$K$4:$K$28,A7) | D7: =SUMIFS('Project Portfolio'!$T$4:$T$28,'Project Portfolio'!$K$4:$K$28,A7) | E7: =SUMIFS('Project Portfolio'!$O$4:$O$28,'Project Portfolio'!$K$4:$K$28,A7) | F7: =SUMIFS('Project Portfolio'!$U$4:$U$28,'Project Portfolio'!$K$4:$K$28,A7) | G7: =IFERROR(AVERAGEIFS('Project Portfolio'!$R$4:$R$28,'Project Portfolio'!$K$4:$K$28,A7,'Project Portfolio'!$N$4:$N$28,">0"),0)
A8: Substantial Completion | B8: =COUNTIF('Project Portfolio'!$K$4:$K$28,A8) | C8: =SUMIFS('Project Portfolio'!$N$4:$N$28,'Project Portfolio'!$K$4:$K$28,A8) | D8: =SUMIFS('Project Portfolio'!$T$4:$T$28,'Project Portfolio'!$K$4:$K$28,A8) | E8: =SUMIFS('Project Portfolio'!$O$4:$O$28,'Project Portfolio'!$K$4:$K$28,A8) | F8: =SUMIFS('Project Portfolio'!$U$4:$U$28,'Project Portfolio'!$K$4:$K$28,A8) | G8: =IFERROR(AVERAGEIFS('Project Portfolio'!$R$4:$R$28,'Project Portfolio'!$K$4:$K$28,A8,'Project Portfolio'!$N$4:$N$28,">0"),0)
A9: Final | B9: =COUNTIF('Project Portfolio'!$K$4:$K$28,A9) | C9: =SUMIFS('Project Portfolio'!$N$4:$N$28,'Project Portfolio'!$K$4:$K$28,A9) | D9: =SUMIFS('Project Portfolio'!$T$4:$T$28,'Project Portfolio'!$K$4:$K$28,A9) | E9: =SUMIFS('Project Portfolio'!$O$4:$O$28,'Project Portfolio'!$K$4:$K$28,A9) | F9: =SUMIFS('Project Portfolio'!$U$4:$U$28,'Project Portfolio'!$K$4:$K$28,A9) | G9: =IFERROR(AVERAGEIFS('Project Portfolio'!$R$4:$R$28,'Project Portfolio'!$K$4:$K$28,A9,'Project Portfolio'!$N$4:$N$28,">0"),0)
A10: Closed | B10: =COUNTIF('Project Portfolio'!$K$4:$K$28,A10) | C10: =SUMIFS('Project Portfolio'!$N$4:$N$28,'Project Portfolio'!$K$4:$K$28,A10) | D10: =SUMIFS('Project Portfolio'!$T$4:$T$28,'Project Portfolio'!$K$4:$K$28,A10) | E10: =SUMIFS('Project Portfolio'!$O$4:$O$28,'Project Portfolio'!$K$4:$K$28,A10) | F10: =SUMIFS('Project Portfolio'!$U$4:$U$28,'Project Portfolio'!$K$4:$K$28,A10) | G10: =IFERROR(AVERAGEIFS('Project Portfolio'!$R$4:$R$28,'Project Portfolio'!$K$4:$K$28,A10,'Project Portfolio'!$N$4:$N$28,">0"),0)
A11: Lost | B11: =COUNTIF('Project Portfolio'!$K$4:$K$28,A11) | C11: =SUMIFS('Project Portfolio'!$N$4:$N$28,'Project Portfolio'!$K$4:$K$28,A11) | D11: =SUMIFS('Project Portfolio'!$T$4:$T$28,'Project Portfolio'!$K$4:$K$28,A11) | E11: =SUMIFS('Project Portfolio'!$O$4:$O$28,'Project Portfolio'!$K$4:$K$28,A11) | F11: =SUMIFS('Project Portfolio'!$U$4:$U$28,'Project Portfolio'!$K$4:$K$28,A11) | G11: =IFERROR(AVERAGEIFS('Project Portfolio'!$R$4:$R$28,'Project Portfolio'!$K$4:$K$28,A11,'Project Portfolio'!$N$4:$N$28,">0"),0)
A13: TOTALS | B13: =SUM(B4:B11) | C13: =SUM(C4:C11) | D13: =SUM(D4:D11) | E13: =SUM(E4:E11) | F13: =SUM(F4:F11) | G13: =IFERROR(SUMPRODUCT(C4:C11,G4:G11)/SUM(C4:C11),0)

Sheet Dashboard
A1: Portfolio Dashboard
A2: Auto-calculated from Project Portfolio. Update that tab - this one stays in sync.
A4: Portfolio KPIs
A5: Total Active Backlog | D5: =SUMIFS('Project Portfolio'!$U$4:$U$28,'Project Portfolio'!$K$4:$K$28,"Active") + SUMIFS('Project Portfolio'!$U$4:$U$28,'Project Portfolio'!$K$4:$K$28,"Mobilizing") + SUMIFS('Project Portfolio'!$U$4:$U$28,'Project Portfolio'!$K$4:$K$28,"Substantial Completion") + SUMIFS('Project Portfolio'!$U$4:$U$28,'Project Portfolio'!$K$4:$K$28,"Awarded")
A6: Total Cost to Date (Active) | D6: =SUMIFS('Project Portfolio'!$O$4:$O$28,'Project Portfolio'!$K$4:$K$28,"Active") + SUMIFS('Project Portfolio'!$O$4:$O$28,'Project Portfolio'!$K$4:$K$28,"Mobilizing") + SUMIFS('Project Portfolio'!$O$4:$O$28,'Project Portfolio'!$K$4:$K$28,"Substantial Completion") + SUMIFS('Project Portfolio'!$O$4:$O$28,'Project Portfolio'!$K$4:$K$28,"Awarded")
A7: Weighted Avg Margin % (Active) | D7: =IFERROR((SUMIFS('Project Portfolio'!$Q$4:$Q$28,'Project Portfolio'!$K$4:$K$28,"Active") + SUMIFS('Project Portfolio'!$Q$4:$Q$28,'Project Portfolio'!$K$4:$K$28,"Mobilizing") + SUMIFS('Project Portfolio'!$Q$4:$Q$28,'Project Portfolio'!$K$4:$K$28,"Substantial Completion") + SUMIFS('Project Portfolio'!$Q$4:$Q$28,'Project Portfolio'!$K$4:$K$28,"Awarded"))/(SUMIFS('Project Portfolio'!$N$4:$N$28,'Project Portfolio'!$K$4:$K$28,"Active") + SUMIFS('Project Portfolio'!$N$4:$N$28,'Project Portfolio'!$K$4:$K$28,"Mobilizing") + SUMIFS('Project Portfolio'!$N$4:$N$28,'Project Portfolio'!$K$4:$K$28,"Substantial Completion") + SUMIFS('Project Portfolio'!$N$4:$N$28,'Project Portfolio'!$K$4:$K$28,"Awarded")),0)
A8: Active Project Count | D8: =COUNTIF('Project Portfolio'!$K$4:$K$28,"Active") + COUNTIF('Project Portfolio'!$K$4:$K$28,"Mobilizing") + COUNTIF('Project Portfolio'!$K$4:$K$28,"Substantial Completion") + COUNTIF('Project Portfolio'!$K$4:$K$28,"Awarded")
A9: All Statuses - Total Contract | D9: =SUM('Project Portfolio'!$N$4:$N$28)
A10: All Statuses - Total Backlog | D10: =SUM('Project Portfolio'!$U$4:$U$28)
A13: Top 5 Largest Backlogs
A14: Rank | B14: Project Name | D14: Backlog
A15: 1 | B15: =IFERROR(INDEX('Project Portfolio'!$B$4:$B$28,MATCH(LARGE('Project Portfolio'!$U$4:$U$28,1),'Project Portfolio'!$U$4:$U$28,0)),"") | D15: =IFERROR(INDEX('Project Portfolio'!$K$4:$K$28,MATCH(LARGE('Project Portfolio'!$U$4:$U$28,1),'Project Portfolio'!$U$4:$U$28,0)),"") | E15: =IFERROR(LARGE('Project Portfolio'!$U$4:$U$28,1),0)
A16: 2 | B16: =IFERROR(INDEX('Project Portfolio'!$B$4:$B$28,MATCH(LARGE('Project Portfolio'!$U$4:$U$28,2),'Project Portfolio'!$U$4:$U$28,0)),"") | D16: =IFERROR(INDEX('Project Portfolio'!$K$4:$K$28,MATCH(LARGE('Project Portfolio'!$U$4:$U$28,2),'Project Portfolio'!$U$4:$U$28,0)),"") | E16: =IFERROR(LARGE('Project Portfolio'!$U$4:$U$28,2),0)
A17: 3 | B17: =IFERROR(INDEX('Project Portfolio'!$B$4:$B$28,MATCH(LARGE('Project Portfolio'!$U$4:$U$28,3),'Project Portfolio'!$U$4:$U$28,0)),"") | D17: =IFERROR(INDEX('Project Portfolio'!$K$4:$K$28,MATCH(LARGE('Project Portfolio'!$U$4:$U$28,3),'Project Portfolio'!$U$4:$U$28,0)),"") | E17: =IFERROR(LARGE('Project Portfolio'!$U$4:$U$28,3),0)
A18: 4 | B18: =IFERROR(INDEX('Project Portfolio'!$B$4:$B$28,MATCH(LARGE('Project Portfolio'!$U$4:$U$28,4),'Project Portfolio'!$U$4:$U$28,0)),"") | D18: =IFERROR(INDEX('Project Portfolio'!$K$4:$K$28,MATCH(LARGE('Project Portfolio'!$U$4:$U$28,4),'Project Portfolio'!$U$4:$U$28,0)),"") | E18: =IFERROR(LARGE('Project Portfolio'!$U$4:$U$28,4),0)
A19: 5 | B19: =IFERROR(INDEX('Project Portfolio'!$B$4:$B$28,MATCH(LARGE('Project Portfolio'!$U$4:$U$28,5),'Project Portfolio'!$U$4:$U$28,0)),"") | D19: =IFERROR(INDEX('Project Portfolio'!$K$4:$K$28,MATCH(LARGE('Project Portfolio'!$U$4:$U$28,5),'Project Portfolio'!$U$4:$U$28,0)),"") | E19: =IFERROR(LARGE('Project Portfolio'!$U$4:$U$28,5),0)
A22: Aged Projects (past Target Completion, not yet Final/Closed)
A23: Count of aged projects | D23: =SUMPRODUCT(('Project Portfolio'!$I$4:$I$28<TODAY())*('Project Portfolio'!$I$4:$I$28<>"")*('Project Portfolio'!$K$4:$K$28<>"Final")*('Project Portfolio'!$K$4:$K$28<>"Closed")*('Project Portfolio'!$K$4:$K$28<>"Lost")*('Project Portfolio'!$K$4:$K$28<>"Bidding"))
A24: Backlog tied up in aged projects | D24: =SUMPRODUCT(('Project Portfolio'!$I$4:$I$28<TODAY())*('Project Portfolio'!$I$4:$I$28<>"")*('Project Portfolio'!$K$4:$K$28<>"Final")*('Project Portfolio'!$K$4:$K$28<>"Closed")*('Project Portfolio'!$K$4:$K$28<>"Lost")*('Project Portfolio'!$K$4:$K$28<>"Bidding")*'Project Portfolio'!$U$4:$U$28)
A26: To see which projects are aged: open Project Portfolio, filter Target Completion < today and Status not Final/Closed/Lost/Bidding.

Sheet CSI Reference
A1: CSI MasterFormat + Reference Lists
A2: Pulled from the same canonical lists as ContrPro Job Costing and Change Order Log. Do not edit.
A3: CSI Division | B3: Division Name | D3: State
A4: 01 | B4: General Requirements | D4: AL
A5: 02 | B5: Existing Conditions | D5: AK
A6: 03 | B6: Concrete | D6: AZ
A7: 04 | B7: Masonry | D7: AR
A8: 05 | B8: Metals | D8: CA
A9: 06 | B9: Wood, Plastics, and Composites | D9: CO
A10: 07 | B10: Thermal and Moisture Protection | D10: CT
A11: 08 | B11: Openings | D11: DE
A12: 09 | B12: Finishes | D12: DC
A13: 10 | B13: Specialties | D13: FL
A14: 11 | B14: Equipment | D14: GA
... A38: 49 | B38: Reserved | D38: ND
D39: OH
D40: OK
D41: OR
D42: PA
D43: RI
D44: SC
D45: SD
D46: TN
D47: TX
D48: UT
D49: VT
D50: VA
... D54: WY
