Workbook

Sheet Instructions
A1: MECHANICAL BID ESTIMATOR — INSTRUCTIONS
A4: PURPOSE
A5: Production estimating tool for commercial mechanical (HVAC + hydronic + refrigeration)
A6: contractors. Combines per-equipment + per-ton + per-CFM + per-LF of pipe / per-SF of
A7: sheet-metal anchors. CSI Division 23 primary with cross-references to 22 (plumbing),
A8: 26 (electrical), and 27 (BAS / controls).
A10: WORKFLOW
A11: 1. Project Info — fill every blue field.
A12: 2. Wage Rates — set base + fringe + burden by classification.
A13: 3. Material Takeoff — quantities by CSI line item.
A14: 4. Labor Estimate — productivity defaults assume average commercial conditions.
A15: 5. Equipment — daily/weekly rentals + tools.
... A33: ContrPro Complete Tier · Mechanical Trade Pack

Sheet Bid Summary
A1: BID SUMMARY — Mechanical Trade Pack
B3: Material total (incl. tax) | C3: ='Material Takeoff'!$F$106
B4: Labor total | C4: ='Labor Estimate'!$H$66
B5: Equipment total | C5: ='Equipment'!$F$21
B6: Subcontract total | C6: ='Subcontract'!$E$17
B7: Premiums $ | C7: ='Premiums'!$D$17
B8: Direct cost subtotal | C8: =SUM(C3:C7)
B9: Premium % applied | C9: ='Premiums'!$D$18
B10: Premium % adder $ | C10: =C8*C9
B11: Direct + premium % | C11: =C8+C10
B12: Contingency % | C12: 0.05
B13: Contingency $ | C13: =C11*C12
B14: Direct + contingency | C14: =C11+C13
B15: Overhead % | C15: 0.1
B16: Overhead $ | C16: =C14*C15
B17: Profit % | C17: 0.1
B18: Profit $ | C18: =(C14+C16)*C17
B19: Bond % | C19: 0.012
B20: Bond $ | C20: =(C14+C16+C18)*C19
B21: Insurance / GL % | C21: 0.018
B22: Insurance $ | C22: =(C14+C16+C18)*C21
B23: FINAL BID | C23: =C14+C16+C18+C20+C22

Sheet Project Info
A1: PROJECT INFORMATION
A3: Project Name
A4: Project Address
A5: Owner
A6: General Contractor
A7: Architect / Engineer
A8: Bid Due Date
A9: Bid Reference / Number
A10: Project Type | B10: (New / Renovation / Tenant fit-out / Adaptive reuse)
A11: Building Use | B11: (Office / Retail / Healthcare / Education / Multi-family / Hospitality / Industrial)
A12: Approx. Square Footage
A13: Stories
A14: Total Tonnage (cooling)
A15: Total CFM (supply / return / OA)
A16: AHJ — Mechanical Inspector
A17: Applicable Mechanical Code | B17: (IMC 2024 / UMC 2024 / local amendments)
A18: Applicable Energy Code | B18: (IECC 2021 / ASHRAE 90.1-2019 / state amendments)
A19: Estimator Name
A20: Date Prepared
A21: Internal Bid Number
A22: Notes / Assumptions

Sheet Wage Rates
A1: WAGE RATES (calibrate to your market)
A3: Classification | B3: Base Rate ($/hr) | C3: Fringe ($/hr) | D3: Burden % (WC/GL/FICA) | E3: OT Premium (1.5×) | F3: Loaded Rate ($/hr)
A4: Mechanical Foreman | B4: 62 | C4: 19.5 | D4: 0.32 | E4: =B4*1.5 | F4: =(B4+C4)*(1+D4)
A5: Sheet Metal Journeyman | B5: 50 | C5: 18.5 | D5: 0.32 | E5: =B5*1.5 | F5: =(B5+C5)*(1+D5)
A6: Pipefitter Journeyman | B6: 54 | C6: 19.5 | D6: 0.32 | E6: =B6*1.5 | F6: =(B6+C6)*(1+D6)
A7: Steamfitter Journeyman | B7: 56 | C7: 19.5 | D7: 0.32 | E7: =B7*1.5 | F7: =(B7+C7)*(1+D7)
A8: Refrigeration Tech (EPA 608) | B8: 58 | C8: 19.5 | D8: 0.32 | E8: =B8*1.5 | F8: =(B8+C8)*(1+D8)
A9: HVAC Tech | B9: 50 | C9: 18.5 | D9: 0.32 | E9: =B9*1.5 | F9: =(B9+C9)*(1+D9)
A10: Apprentice (Yr 4) | B10: 38 | C10: 14 | D10: 0.32 | E10: =B10*1.5 | F10: =(B10+C10)*(1+D10)
A11: Apprentice (Yr 2) | B11: 28 | C11: 12 | D11: 0.32 | E11: =B11*1.5 | F11: =(B11+C11)*(1+D11)
A12: Insulator | B12: 42 | C12: 16 | D12: 0.32 | E12: =B12*1.5 | F12: =(B12+C12)*(1+D12)
A13: Helper / Material Handler | B13: 22 | C13: 9.5 | D13: 0.32 | E13: =B13*1.5 | F13: =(B13+C13)*(1+D13)
A14: Controls Tech / BAS | B14: 60 | C14: 19 | D14: 0.32 | E14: =B14*1.5 | F14: =(B14+C14)*(1+D14)
A15: TAB Technician | B15: 55 | C15: 18 | D15: 0.32 | E15: =B15*1.5 | F15: =(B15+C15)*(1+D15)

Sheet Material Takeoff
A1: MATERIAL TAKEOFF (CSI Division 23)
A3: CSI Code | B3: Description | C3: QTY | D3: UOM | E3: Unit Cost ($) | F3: Material Subtotal ($) | G3: Notes
A4: 23 05 13 | B4: Pipe hangers + supports — clevis 1" - 4" | C4: 0 | D4: EA | E4: 9.5 | F4: =C4*E4
A5: 23 05 13 | B5: Trapeze + unistrut assembly (multi-pipe) | C5: 0 | D5: EA | E5: 38 | F5: =C5*E5
A6: 23 05 17 | B6: Sleeves + escutcheons (per assembly) | C6: 0 | D6: EA | E6: 6.5 | F6: =C6*E6
A7: 23 05 23 | B7: Valve — ball, bronze, 1" | C7: 0 | D7: EA | E7: 28 | F7: =C7*E7
A8: 23 05 23 | B8: Valve — ball, bronze, 2" | C8: 0 | D8: EA | E8: 65 | F8: =C8*E8
A9: 23 05 23 | B9: Valve — globe, bronze, 1" | C9: 0 | D9: EA | E9: 65 | F9: =C9*E9
A10: 23 05 23 | B10: Valve — butterfly, cast iron, 4" | C10: 0 | D10: EA | E10: 185 | F10: =C10*E10
A11: 23 05 23 | B11: Valve — gate, cast iron, 6" | C11: 0 | D11: EA | E11: 425 | F11: =C11*E11
A12: 23 07 13 | B12: Duct insulation — fiberglass wrap, 1.5" w/ FRK | C12: 0 | D12: SF | E12: 1.85 | F12: =C12*E12
A13: 23 07 13 | B13: Duct insulation — fiberglass duct liner, 1" | C13: 0 | D13: SF | E13: 2.65 | F13: =C13*E13
A14: 23 07 19 | B14: Pipe insulation — fiberglass, 1" pipe | C14: 0 | D14: LF | E14: 2.85 | F14: =C14*E14
A15: 23 07 19 | B15: Pipe insulation — fiberglass, 2" pipe | C15: 0 | D15: LF | E15: 4.2 | F15: =C15*E15
... A100: 23 83 13 | B100: Radiant manifold — 6 loop | C100: 0 | D100: EA | E100: 685 | F100: =C100*E100
A101: 23 00 10 | B101: Permit — mechanical | C101: 0 | D101: LS | E101: 0 | F101: =C101*E101 | G101: Allowance
E103: Material Subtotal | F103: =SUM(F4:F101)
E104: Sales tax % | F104: 0.07
E105: Sales tax $ | F105: =F103*F104
E106: Material TOTAL (incl tax) | F106: =F103+F105

Sheet Labor Estimate
A1: LABOR ESTIMATE (MCAA/SMACNA-style)
A3: CSI Code | B3: Activity | C3: QTY | D3: UOM | E3: Hours / UOM | F3: Subtotal Hours | G3: Crew Loaded Rate ($/hr) | H3: Subtotal Labor ($)
A4: 23 31 13 | B4: Install galvanized rectangular duct (24ga) | C4: 0 | D4: SF | E4: 0.18 | F4: =C4*E4 | G4: 68 | H4: =F4*G4
A5: 23 31 13 | B5: Install galvanized rectangular duct (20ga) | C5: 0 | D5: SF | E5: 0.25 | F5: =C5*E5 | G5: 68 | H5: =F5*G5
A6: 23 31 13 | B6: Install round spiral duct | C6: 0 | D6: SF | E6: 0.13 | F6: =C6*E6 | G6: 68 | H6: =F6*G6
A7: 23 31 16 | B7: Install stainless kitchen exhaust | C7: 0 | D7: SF | E7: 0.45 | F7: =C7*E7 | G7: 68 | H7: =F7*G7
A8: 23 31 19 | B8: Install flex duct + connect | C8: 0 | D8: LF | E8: 0.18 | F8: =C8*E8 | G8: 68 | H8: =F8*G8
A9: 23 33 13 | B9: Install volume damper | C9: 0 | D9: EA | E9: 0.4 | F9: =C9*E9 | G9: 68 | H9: =F9*G9
A10: 23 33 33 | B10: Install fire damper (per UL system) | C10: 0 | D10: EA | E10: 0.65 | F10: =C10*E10 | G10: 68 | H10: =F10*G10
A11: 23 33 33 | B11: Install smoke/combination damper | C11: 0 | D11: EA | E11: 0.85 | F11: =C11*E11 | G11: 68 | H11: =F11*G11
A12: 23 34 13 | B12: Hang exhaust fan inline | C12: 0 | D12: EA | E12: 1.5 | F12: =C12*E12 | G12: 68 | H12: =F12*G12
A13: 23 34 13 | B13: Set roof-mount exhaust fan | C13: 0 | D13: EA | E13: 4.5 | F13: =C13*E13 | G13: 68 | H13: =F13*G13
A14: 23 37 13 | B14: Install supply diffuser | C14: 0 | D14: EA | E14: 0.3 | F14: =C14*E14 | G14: 68 | H14: =F14*G14
A15: 23 37 13 | B15: Install return grille | C15: 0 | D15: EA | E15: 0.25 | F15: =C15*E15 | G15: 68 | H15: =F15*G15
... A63: 23 08 00 | B63: Cx — integration testing | C63: 0 | D63: LS | E63: 16 | F63: =C63*E63 | G63: 78 | H63: =F63*G63
G65: Productivity factor | H65: 1
G66: Labor Subtotal | H66: =SUM(H4:H63)*H65

Sheet Equipment
A1: EQUIPMENT ESTIMATE
A3: Equipment | B3: Days | C3: Daily Rate ($) | D3: Weeks | E3: Weekly Rate ($) | F3: Subtotal ($)
A4: Sheet-metal brake / shear (rental) | B4: 0 | C4: 145 | D4: 0 | E4: 485 | F4: =(B4*C4)+(D4*E4)
A5: Threading machine 1" - 2" | B5: 0 | C5: 145 | D5: 0 | E5: 525 | F5: =(B5*C5)+(D5*E5)
A6: Pipe-bending machine — hydronic | B6: 0 | C6: 95 | D6: 0 | E6: 285 | F6: =(B6*C6)+(D6*E6)
A7: Refrigerant recovery machine + cylinders | B7: 0 | C7: 95 | D7: 0 | E7: 285 | F7: =(B7*C7)+(D7*E7)
A8: Vacuum pump — 2-stage 8 CFM | B8: 0 | C8: 65 | D8: 0 | E8: 195 | F8: =(B8*C8)+(D8*E8)
A9: Nitrogen tank + regulator | B9: 0 | C9: 35 | D9: 0 | E9: 105 | F9: =(B9*C9)+(D9*E9)
A10: Brazing torch + tank set | B10: 0 | C10: 45 | D10: 0 | E10: 145 | F10: =(B10*C10)+(D10*E10)
A11: Manifold gauge set + scale | B11: 0 | C11: 35 | D11: 0 | E11: 105 | F11: =(B11*C11)+(D11*E11)
A12: Hydronic flush kit | B12: 0 | C12: 95 | D12: 0 | E12: 285 | F12: =(B12*C12)+(D12*E12)
A13: Boom lift — 45' | B13: 0 | C13: 425 | D13: 0 | E13: 1485 | F13: =(B13*C13)+(D13*E13)
A14: Scissor lift — 19' | B14: 0 | C14: 145 | D14: 0 | E14: 485 | F14: =(B14*C14)+(D14*E14)
A15: Forklift — 5000 lb pneumatic | B15: 0 | C15: 285 | D15: 0 | E15: 985 | F15: =(B15*C15)+(D15*E15)
... A19: Truck / van allocation | B19: 0 | C19: 0 | D19: 0 | E19: 425 | F19: =(B19*C19)+(D19*E19)
E21: Equipment Subtotal | F21: =SUM(F4:F19)

Sheet Subcontract
A1: SUBCONTRACT ESTIMATE
A3: Scope (if subbed) | B3: Vendor / Quote | C3: Quote $ | D3: Markup % | E3: Subtotal ($)
A4: Test, Adjust, Balance (TAB) — NEBB / AABC | C4: 0 | D4: 0.1 | E4: =C4*(1+D4)
A5: Commissioning (Cx) — third-party CxA | C5: 0 | D5: 0.1 | E5: =C5*(1+D5)
A6: BAS / DDC programming | C6: 0 | D6: 0.1 | E6: =C6*(1+D6)
A7: Refrigerant charging + commissioning (EPA 608) | C7: 0 | D7: 0.1 | E7: =C7*(1+D7)
A8: Boiler / chiller start-up — vendor | C8: 0 | D8: 0.05 | E8: =C8*(1+D8)
A9: Insulation (if subbed) | C9: 0 | D9: 0.1 | E9: =C9*(1+D9)
A10: Sheet-metal pre-fab (if subbed) | C10: 0 | D10: 0.1 | E10: =C10*(1+D10)
A11: Crane / rigging — specialty heavy lift | C11: 0 | D11: 0.1 | E11: =C11*(1+D11)
A12: Roof curbs + flashing | C12: 0 | D12: 0.1 | E12: =C12*(1+D12)
A13: Hazmat / asbestos abatement (legacy MEP) | C13: 0 | D13: 0.1 | E13: =C13*(1+D13)
A14: Concrete saw-cutting / core drilling | C14: 0 | D14: 0.1 | E14: =C14*(1+D14)
A15: Hot-tap / live-cutover (gas / chilled water) | C15: 0 | D15: 0.1 | E15: =C15*(1+D15)
D17: Subcontract Subtotal | E17: =SUM(E4:E15)

Sheet Premiums
A1: PREMIUMS & CONDITIONS
A3: Premium | B3: Applies? (Y/N) | C3: Adder % | D3: Adder $ (overrides %)
A4: Prevailing wage | B4: N | C4: 0.15 | D4: 0
A5: Occupied building / live-cutover | B5: N | C5: 0.1 | D5: 0
A6: Hospital ICRA tier 3+ | B6: N | C6: 0.1 | D6: 0
A7: Heights > 14 ft (lift / crane) | B7: N | C7: 0.05 | D7: 0
A8: Roof-top set requiring crane lift | B8: N | C8: 0.06 | D8: 0
A9: Tight mechanical room (extended labor) | B9: N | C9: 0.05 | D9: 0
A10: Hazardous-area (refrigerant + flammable) | B10: N | C10: 0.06 | D10: 0
A11: After-hours / weekend / night shift | B11: N | C11: 0.2 | D11: 0
A12: Travel / per diem | B12: N | C12: 0.03 | D12: 0
A13: Winter / cold-weather working | B13: N | C13: 0.04 | D13: 0
A14: LEED / Cx documentation | B14: N | C14: 0.04 | D14: 0
A15: Owner-direct equipment (no markup) | B15: N | C15: -0.1 | D15: 0
A17: Premium $ total (applies-Y only) | D17: =SUMPRODUCT((B4:B15="Y")*D4:D15)
A18: Premium % total (applies-Y only) | D18: =SUMPRODUCT((B4:B15="Y")*C4:C15)

Sheet CSI Reference
A1: CSI MASTERFORMAT — DIVISION 23 HEATING / VENTILATING / AIR-CONDITIONING
A3: 23 00 00 | B3: HEATING, VENTILATING, AND AIR-CONDITIONING (HVAC)
A4: 23 05 00 | B4: Common Work Results for HVAC
A5: 23 05 13 | B5: Common Motor Requirements for HVAC Equipment
A6: 23 05 17 | B6: Sleeves and Sleeve Seals for HVAC Piping
A7: 23 05 19 | B7: Meters and Gauges for HVAC Piping
A8: 23 05 23 | B8: General-Duty Valves for HVAC Piping
A9: 23 05 29 | B9: Hangers and Supports for HVAC Piping and Equipment
A10: 23 05 53 | B10: Identification for HVAC Piping and Equipment
A11: 23 05 93 | B11: Testing, Adjusting, and Balancing for HVAC
A12: 23 07 00 | B12: HVAC Insulation
A13: 23 07 13 | B13: Duct Insulation
A14: 23 07 19 | B14: HVAC Piping Insulation
... A54: 27 21 / 27 22 | B54: BAS Communications (cross-ref)
