Workbook
Name ASM_Starting_monthly_revenue: Assumptions!$B$5
Name ASM_Monthly_revenue_growth_pct: Assumptions!$B$6
Name ASM_Year_2_revenue_growth: Assumptions!$B$7
Name ASM_Year_3_revenue_growth: Assumptions!$B$8
Name ASM_Direct_labor_cost_pct_of_revenue: Assumptions!$B$10
Name ASM_Direct_materials_pct_of_revenue: Assumptions!$B$11
Name ASM_Direct_subcontractor_pct_of_revenue: Assumptions!$B$12
Name ASM_Burden___fringes___WC_on_labor_pct: Assumptions!$B$13
Name ASM_Overhead_pct_of_revenue: Assumptions!$B$15
Name ASM_Days_Sales_Outstanding: Assumptions!$B$17
Name ASM_Retainage_pct_held: Assumptions!$B$18
Name ASM_Retainage_release_days_postcompletion: Assumptions!$B$19
Name ASM_Days_Payable_Outstanding: Assumptions!$B$20
Name ASM_Inventory_days: Assumptions!$B$21
Name ASM_Owner_monthly_salary___draw: Assumptions!$B$23
Name ASM_Nonowner_payroll_Y1: Assumptions!$B$24
Name ASM_Payroll_Y23_growth_pct: Assumptions!$B$25
Name ASM_Existing_equipment_book_value: Assumptions!$B$27
Name ASM_Annual_depreciation_pct: Assumptions!$B$28
Name ASM_New_equipment_purchase_Y1: Assumptions!$B$29
Name ASM_Section_179___bonus_depreciation_Y1: Assumptions!$B$30
Name ASM_Requested_loan_amount: Assumptions!$B$32
Name ASM_Interest_rate: Assumptions!$B$33
Name ASM_Amortization: Assumptions!$B$34
Name ASM_SBA_guarantee_fee_pct: Assumptions!$B$35
Name ASM_Owner_cash_injection_at_closing: Assumptions!$B$36

Sheet Instructions
A1: FINANCIAL PROJECTION TEMPLATES — INSTRUCTIONS
A4: PURPOSE
A5: A 3-year financial projection workbook formatted to SBA loan-officer expectations,
A6: tuned for construction-industry realities (work-in-progress accounting, retainage
A7: receivables, progress billing, equipment-heavy depreciation). Designed so a contractor
A8: can fill in the ONE assumptions tab and have a complete projection package ready for
A9: an SBA 7(a) / 504 / Express loan application.
A11: WORKFLOW
A12: 1. Open the ASSUMPTIONS tab. Fill every CREAM-colored input cell.
A13: - Starting revenue + monthly growth rate
A14: - Direct cost ratio (labor + materials as % of revenue)
A15: - Indirect cost ratio (overhead)
... A53: ContrPro Complete Tier · SBA Bonus

Sheet Assumptions
A1: ASSUMPTIONS — fill every CREAM cell
A3: Assumption | B3: Value | C3: Notes
A4: --- REVENUE ---
A5: Starting monthly revenue (M1) | B5: 50000 | C5: Your current run-rate or first month projected
A6: Monthly revenue growth % | B6: 0.03 | C6: 3%/mo = ~43%/yr compounded; tune to your reality
A7: Year 2 revenue growth (annualized) | B7: 0.2 | C7: Slower in Y2 as you stabilize
A8: Year 3 revenue growth (annualized) | B8: 0.15 | C8: Maturing growth
A9: --- COST STRUCTURE ---
A10: Direct labor cost % of revenue | B10: 0.3 | C10: Field crews + foremen labor
A11: Direct materials % of revenue | B11: 0.32 | C11: Materials passed through to job
A12: Direct subcontractor % of revenue | B12: 0.05 | C12: Subbed-out scopes
A13: Burden / fringes / WC on labor % | B13: 0.35 | C13: On direct labor
A14: Overhead % of revenue (Y1) | B14: 0.18 | C14: Office, insurance, owner+PM salaries
A15: Overhead % of revenue (Y2-3) | B15: 0.15 | C15: Scales down as revenue grows
A16: --- WORKING CAPITAL ---
A17: Days Sales Outstanding (DSO) | B17: 60 | C17: Pay-app cycle (30 days net + 30 days slip = 60)
A18: Retainage % held | B18: 0.05 | C18: 5-10% typical; commercial higher than residential
A19: Retainage release days post-completion | B19: 60 | C19: Time from sub-completion to retainage check
A20: Days Payable Outstanding (DPO) | B20: 35 | C20: How long you stretch suppliers
A21: Inventory days | B21: 12 | C21: Materials staged before install
A22: --- OWNER + PAYROLL ---
A23: Owner monthly salary / draw | B23: 8000 | C23: S-Corp salary or LLC owner draw
A24: Non-owner payroll Y1 (annual) | B24: 180000 | C24: Sum of all non-owner W-2 wages
A25: Payroll Y2-3 growth % | B25: 0.1 | C25: Add staff as revenue grows
A26: --- EQUIPMENT ---
A27: Existing equipment book value | B27: 75000 | C27: Trucks + tools + heavy equipment
A28: Annual depreciation % (avg) | B28: 0.2 | C28: 5-yr MACRS-ish; vehicles + light equipment
A29: New equipment purchase Y1 | B29: 50000 | C29: Major purchases in next 12 months
A30: Section 179 / bonus depreciation Y1? | B30: Y | C30: Y = expense full purchase in Y1; N = depreciate
A31: --- SBA LOAN ---
A32: Requested loan amount | B32: 250000 | C32: Working capital + equipment combined
A33: Interest rate (annual) | B33: 0.105 | C33: SBA 7(a) recent range = WSJ Prime + 1.5-2.75%
A34: Amortization (months) | B34: 84 | C34: 84 mo (7 yr) for WC; 240 mo (20 yr) for real estate
A35: SBA guarantee fee % | B35: 0.029 | C35: Lender adds this for 7(a) loans > $150K
A36: Owner cash injection at closing | B36: 25000 | C36: Lender typically requires 10% equity

Sheet P&L Y1-Y3
A1: PROFIT & LOSS — Year 1 monthly + Year 2/Year 3 annual
A3: Item | B3: M1 | C3: M2 | D3: M3 | E3: M4 | F3: M5 | G3: M6 | H3: M7 | I3: M8 | J3: M9 | K3: M10 | L3: M11 | M3: M12 | N3: Y1 Total | O3: Y2 Total | P3: Y3 Total
A4: REVENUE
A5: Revenue | B5: =Assumptions!$B$5 | C5: =B5*(1+Assumptions!$B$6) | D5: =C5*(1+Assumptions!$B$6) | E5: =D5*(1+Assumptions!$B$6) | F5: =E5*(1+Assumptions!$B$6) | G5: =F5*(1+Assumptions!$B$6) | H5: =G5*(1+Assumptions!$B$6) | I5: =H5*(1+Assumptions!$B$6) | J5: =I5*(1+Assumptions!$B$6) | ... M5: =L5*(1+Assumptions!$B$6) | N5: =SUM(B5:M5) | O5: =N5*(1+Assumptions!$B$7) | P5: =O5*(1+Assumptions!$B$8)
A7: DIRECT COSTS
A8: Direct labor | B8: =B5*Assumptions!$B$11 | C8: =C5*Assumptions!$B$11 | D8: =D5*Assumptions!$B$11 | E8: =E5*Assumptions!$B$11 | F8: =F5*Assumptions!$B$11 | G8: =G5*Assumptions!$B$11 | H8: =H5*Assumptions!$B$11 | I8: =I5*Assumptions!$B$11 | ... M8: =M5*Assumptions!$B$11 | N8: =SUM(B8:M8) | O8: =O5*Assumptions!$B$11 | P8: =P5*Assumptions!$B$11
A9: Burden on labor | B9: =B8*Assumptions!$B$14 | C9: =C8*Assumptions!$B$14 | D9: =D8*Assumptions!$B$14 | E9: =E8*Assumptions!$B$14 | F9: =F8*Assumptions!$B$14 | G9: =G8*Assumptions!$B$14 | H9: =H8*Assumptions!$B$14 | I9: =I8*Assumptions!$B$14 | ... M9: =M8*Assumptions!$B$14 | N9: =SUM(B9:M9) | O9: =O8*Assumptions!$B$14 | P9: =P8*Assumptions!$B$14
A10: Direct materials | B10: =B5*Assumptions!$B$12 | C10: =C5*Assumptions!$B$12 | D10: =D5*Assumptions!$B$12 | E10: =E5*Assumptions!$B$12 | F10: =F5*Assumptions!$B$12 | G10: =G5*Assumptions!$B$12 | H10: =H5*Assumptions!$B$12 | I10: =I5*Assumptions!$B$12 | ... M10: =M5*Assumptions!$B$12 | N10: =SUM(B10:M10) | O10: =O5*Assumptions!$B$12 | P10: =P5*Assumptions!$B$12
A11: Direct subs | B11: =B5*Assumptions!$B$13 | C11: =C5*Assumptions!$B$13 | D11: =D5*Assumptions!$B$13 | E11: =E5*Assumptions!$B$13 | F11: =F5*Assumptions!$B$13 | G11: =G5*Assumptions!$B$13 | H11: =H5*Assumptions!$B$13 | I11: =I5*Assumptions!$B$13 | ... M11: =M5*Assumptions!$B$13 | N11: =SUM(B11:M11) | O11: =O5*Assumptions!$B$13 | P11: =P5*Assumptions!$B$13
A12: Total direct costs | B12: =B8+B9+B10+B11 | C12: =C8+C9+C10+C11 | D12: =D8+D9+D10+D11 | E12: =E8+E9+E10+E11 | F12: =F8+F9+F10+F11 | G12: =G8+G9+G10+G11 | H12: =H8+H9+H10+H11 | I12: =I8+I9+I10+I11 | ... M12: =M8+M9+M10+M11 | N12: =SUM(B12:M12) | O12: =O8+O9+O10+O11 | P12: =P8+P9+P10+P11
A13: Gross profit | B13: =B5-B12 | C13: =C5-C12 | D13: =D5-D12 | E13: =E5-E12 | F13: =F5-F12 | G13: =G5-G12 | H13: =H5-H12 | I13: =I5-I12 | ... P13: =P5-P12
A14: GP margin % | B14: =IFERROR(B13/B5,0) | C14: =IFERROR(C13/C5,0) | D14: =IFERROR(D13/D5,0) | E14: =IFERROR(E13/E5,0) | F14: =IFERROR(F13/F5,0) | G14: =IFERROR(G13/G5,0) | H14: =IFERROR(H13/H5,0) | I14: =IFERROR(I13/I5,0) | ... P14: =IFERROR(P13/P5,0)
A15: OVERHEAD
A16: Owner salary/draw | B16: =Assumptions!$B$24 | C16: =Assumptions!$B$24 | D16: =Assumptions!$B$24 | E16: =Assumptions!$B$24 | F16: =Assumptions!$B$24 | G16: =Assumptions!$B$24 | H16: =Assumptions!$B$24 | I16: =Assumptions!$B$24 | ... M16: =Assumptions!$B$24 | N16: =Assumptions!$B$24*12 | O16: =N16*(1+Assumptions!$B$26) | P16: =O16*(1+Assumptions!$B$26)
A17: Non-owner payroll (monthly avg) | B17: =Assumptions!$B$25/12 | C17: =Assumptions!$B$25/12 | D17: =Assumptions!$B$25/12 | E17: =Assumptions!$B$25/12 | F17: =Assumptions!$B$25/12 | G17: =Assumptions!$B$25/12 | H17: =Assumptions!$B$25/12 | I17: =Assumptions!$B$25/12 | ... M17: =Assumptions!$B$25/12 | N17: =Assumptions!$B$25 | O17: =N17*(1+Assumptions!$B$26) | P17: =O17*(1+Assumptions!$B$26)
A18: Other overhead (utilities, ins, etc.) | B18: =(B5*Assumptions!$B$15)-B16-B17 | C18: =(C5*Assumptions!$B$15)-C16-C17 | D18: =(D5*Assumptions!$B$15)-D16-D17 | E18: =(E5*Assumptions!$B$15)-E16-E17 | F18: =(F5*Assumptions!$B$15)-F16-F17 | G18: =(G5*Assumptions!$B$15)-G16-G17 | H18: =(H5*Assumptions!$B$15)-H16-H17 | I18: =(I5*Assumptions!$B$15)-I16-I17 | ... N18: =(N5*Assumptions!$B$15)-N16-N17 | O18: =(O5*Assumptions!$B$16)-O16-O17 | P18: =(P5*Assumptions!$B$16)-P16-P17
A19: Depreciation | B19: =(Assumptions!$B$29/12)*(Assumptions!$B$28+Assumptions!$B$30) | C19: =(Assumptions!$B$29/12)*(Assumptions!$B$28+Assumptions!$B$30) | D19: =(Assumptions!$B$29/12)*(Assumptions!$B$28+Assumptions!$B$30) | E19: =(Assumptions!$B$29/12)*(Assumptions!$B$28+Assumptions!$B$30) | F19: =(Assumptions!$B$29/12)*(Assumptions!$B$28+Assumptions!$B$30) | G19: =(Assumptions!$B$29/12)*(Assumptions!$B$28+Assumptions!$B$30) | H19: =(Assumptions!$B$29/12)*(Assumptions!$B$28+Assumptions!$B$30) | I19: =(Assumptions!$B$29/12)*(Assumptions!$B$28+Assumptions!$B$30) | ... M19: =(Assumptions!$B$29/12)*(Assumptions!$B$28+Assumptions!$B$30) | N19: =Assumptions!$B$29*(Assumptions!$B$28+Assumptions!$B$30) | O19: =Assumptions!$B$29*Assumptions!$B$28 | P19: =Assumptions!$B$29*Assumptions!$B$28
A20: Total OH | B20: =B16+B17+B18+B19 | C20: =C16+C17+C18+C19 | D20: =D16+D17+D18+D19 | E20: =E16+E17+E18+E19 | F20: =F16+F17+F18+F19 | G20: =G16+G17+G18+G19 | H20: =H16+H17+H18+H19 | I20: =I16+I17+I18+I19 | ... P20: =P16+P17+P18+P19
A21: Operating profit | B21: =B13-B20 | C21: =C13-C20 | D21: =D13-D20 | E21: =E13-E20 | F21: =F13-F20 | G21: =G13-G20 | H21: =H13-H20 | I21: =I13-I20 | ... P21: =P13-P20
A22: OP margin % | B22: =IFERROR(B21/B5,0) | C22: =IFERROR(C21/C5,0) | D22: =IFERROR(D21/D5,0) | E22: =IFERROR(E21/E5,0) | F22: =IFERROR(F21/F5,0) | G22: =IFERROR(G21/G5,0) | H22: =IFERROR(H21/H5,0) | I22: =IFERROR(I21/I5,0) | ... P22: =IFERROR(P21/P5,0)
A23: INTEREST
A24: Interest expense (SBA loan) | B24: =(Assumptions!$B$32*Assumptions!$B$33)/12 | C24: =(Assumptions!$B$32*Assumptions!$B$33)/12 | D24: =(Assumptions!$B$32*Assumptions!$B$33)/12 | E24: =(Assumptions!$B$32*Assumptions!$B$33)/12 | F24: =(Assumptions!$B$32*Assumptions!$B$33)/12 | G24: =(Assumptions!$B$32*Assumptions!$B$33)/12 | H24: =(Assumptions!$B$32*Assumptions!$B$33)/12 | I24: =(Assumptions!$B$32*Assumptions!$B$33)/12 | ... M24: =(Assumptions!$B$32*Assumptions!$B$33)/12 | N24: =Assumptions!$B$32*1.0*Assumptions!$B$33 | O24: =Assumptions!$B$32*0.85*Assumptions!$B$33 | P24: =Assumptions!$B$32*0.65*Assumptions!$B$33
A25: Net profit before tax | B25: =B21-B24 | C25: =C21-C24 | D25: =D21-D24 | E25: =E21-E24 | F25: =F21-F24 | G25: =G21-G24 | H25: =H21-H24 | I25: =I21-I24 | ... P25: =P21-P24
A26: Net margin % | B26: =IFERROR(B25/B5,0) | C26: =IFERROR(C25/C5,0) | D26: =IFERROR(D25/D5,0) | E26: =IFERROR(E25/E5,0) | F26: =IFERROR(F25/F5,0) | G26: =IFERROR(G25/G5,0) | H26: =IFERROR(H25/H5,0) | I26: =IFERROR(I25/I5,0) | ... P26: =IFERROR(P25/P5,0)

Sheet Cashflow Y1-Y3
A1: CASHFLOW SUMMARY — Annual
A3: Line Item | B3: Year 1 | C3: Year 2 | D3: Year 3
A4: Operating cash inflow (revenue × collection rate) | B4: ='P&L Y1-Y3'!N5*0.92 | C4: ='P&L Y1-Y3'!O5*0.95 | D4: ='P&L Y1-Y3'!P5*0.96
A5: Less: direct costs paid | B5: ='P&L Y1-Y3'!N12 | C5: ='P&L Y1-Y3'!O12 | D5: ='P&L Y1-Y3'!P12
A6: Less: overhead paid (cash) | B6: ='P&L Y1-Y3'!N20-'P&L Y1-Y3'!N19 | C6: ='P&L Y1-Y3'!O20-'P&L Y1-Y3'!O19 | D6: ='P&L Y1-Y3'!P20-'P&L Y1-Y3'!P19
A7: Less: interest paid | B7: ='P&L Y1-Y3'!N24 | C7: ='P&L Y1-Y3'!O24 | D7: ='P&L Y1-Y3'!P24
A8: Operating cashflow | B8: =B4-B5-B6-B7 | C8: =C4-C5-C6-C7 | D8: =D4-D5-D6-D7
A10: SBA loan proceeds | B10: =Assumptions!$B$32 | C10: 0 | D10: 0
A11: Owner cash injection | B11: =Assumptions!$B$36 | C11: 0 | D11: 0
A12: Equipment purchases | B12: =-Assumptions!$B$30 | C12: =-Assumptions!$B$30*0.5 | D12: =-Assumptions!$B$30*0.5
A13: Loan principal payments | B13: =-Assumptions!$B$32/(Assumptions!$B$34/12)*12+'P&L Y1-Y3'!N24 | C13: =-Assumptions!$B$32/(Assumptions!$B$34/12)*12+'P&L Y1-Y3'!O24 | D13: =-Assumptions!$B$32/(Assumptions!$B$34/12)*12+'P&L Y1-Y3'!P24
A14: Net cashflow | B14: =B8+SUM(B10:B13) | C14: =C8+SUM(C10:C13) | D14: =D8+SUM(D10:D13)
A15: Cumulative cash | B15: =B14 | C15: =B15+C14 | D15: =C15+D14

Sheet Balance Sheet
A1: BALANCE SHEET — End of Y1 / Y2 / Y3
A3: Account | B3: End of Y1 | C3: End of Y2 | D3: End of Y3
A4: --- ASSETS ---
A5: Cash | B5: ='Cashflow Y1-Y3'!B15 | C5: ='Cashflow Y1-Y3'!C15 | D5: ='Cashflow Y1-Y3'!D15
A6: Accounts receivable (current) | B6: ='P&L Y1-Y3'!N5/12*(Assumptions!$B$18/30) | C6: ='P&L Y1-Y3'!O5/12*(Assumptions!$B$18/30) | D6: ='P&L Y1-Y3'!P5/12*(Assumptions!$B$18/30)
A7: Retainage receivable | B7: ='P&L Y1-Y3'!N5*Assumptions!$B$19 | C7: ='P&L Y1-Y3'!O5*Assumptions!$B$19 | D7: ='P&L Y1-Y3'!P5*Assumptions!$B$19
A8: Inventory / WIP | B8: ='P&L Y1-Y3'!N5/12*(Assumptions!$B$21/30) | C8: ='P&L Y1-Y3'!O5/12*(Assumptions!$B$21/30) | D8: ='P&L Y1-Y3'!P5/12*(Assumptions!$B$21/30)
A9: Equipment + vehicles (net of depr) | B9: =Assumptions!$B$28+Assumptions!$B$30-'P&L Y1-Y3'!N19 | C9: =B8-'P&L Y1-Y3'!O19 | D9: =C8-'P&L Y1-Y3'!P19
A10: Total assets | B10: =SUM(B5:B8) | C10: =SUM(C5:C8) | D10: =SUM(D5:D8)
A11: --- LIABILITIES ---
A12: Accounts payable | B12: ='P&L Y1-Y3'!N12/12*(Assumptions!$B$20/30) | C12: ='P&L Y1-Y3'!O12/12*(Assumptions!$B$20/30) | D12: ='P&L Y1-Y3'!P12/12*(Assumptions!$B$20/30)
A13: SBA loan balance | B13: =Assumptions!$B$32-Assumptions!$B$32/(Assumptions!$B$34/12)*12 | C13: =B12-Assumptions!$B$32/(Assumptions!$B$34/12)*12 | D13: =C12-Assumptions!$B$32/(Assumptions!$B$34/12)*12
A14: Total liabilities | B14: =B11+B12 | C14: =C11+C12 | D14: =D11+D12
A15: --- EQUITY ---
A16: Owner equity (starting + injection + retained) | B16: =Assumptions!$B$36+'P&L Y1-Y3'!N25 | C16: =B15+'P&L Y1-Y3'!O25 | D16: =C15+'P&L Y1-Y3'!P25
A17: --- CHECK ---
A18: Total liab + equity | B18: =B13+B15 | C18: =C13+C15 | D18: =D13+D15
A19: Balance check (should equal Total assets) | B19: =B17-B9 | C19: =C17-C9 | D19: =D17-D9

Sheet Ratios
A1: RATIOS + COVERAGE
A3: Ratio | B3: Y1 | C3: Y2 | D3: Y3 | E3: Lender target
A4: Debt Service Coverage Ratio (DSCR) | B4: =('P&L Y1-Y3'!N21+'P&L Y1-Y3'!N19)/(Assumptions!$B$32/(Assumptions!$B$34/12)*12) | C4: =('P&L Y1-Y3'!O21+'P&L Y1-Y3'!O19)/(Assumptions!$B$32/(Assumptions!$B$34/12)*12) | D4: =('P&L Y1-Y3'!P21+'P&L Y1-Y3'!P19)/(Assumptions!$B$32/(Assumptions!$B$34/12)*12) | E4: SBA wants ≥ 1.25 (1.15 minimum)
A5: Current ratio | B5: =('Balance Sheet'!B5+'Balance Sheet'!B6+'Balance Sheet'!B7+'Balance Sheet'!B8)/'Balance Sheet'!B11 | C5: =('Balance Sheet'!C5+'Balance Sheet'!C6+'Balance Sheet'!C7+'Balance Sheet'!C8)/'Balance Sheet'!C11 | D5: =('Balance Sheet'!D5+'Balance Sheet'!D6+'Balance Sheet'!D7+'Balance Sheet'!D8)/'Balance Sheet'!D11 | E5: Target ≥ 1.5
A6: Debt-to-equity | B6: ='Balance Sheet'!B13/'Balance Sheet'!B15 | C6: ='Balance Sheet'!C13/'Balance Sheet'!C15 | D6: ='Balance Sheet'!D13/'Balance Sheet'!D15 | E6: Target ≤ 3.0 (≤ 2.0 ideal)
A7: Gross margin % | B7: ='P&L Y1-Y3'!N14 | C7: ='P&L Y1-Y3'!O14 | D7: ='P&L Y1-Y3'!P14 | E7: Construction: 20-35% typical
A8: Net margin % | B8: ='P&L Y1-Y3'!N26 | C8: ='P&L Y1-Y3'!O26 | D8: ='P&L Y1-Y3'!P26 | E8: Construction: 5-12% typical
A9: Working capital | B9: ='Balance Sheet'!B5+'Balance Sheet'!B6+'Balance Sheet'!B7+'Balance Sheet'!B8-'Balance Sheet'!B11 | C9: ='Balance Sheet'!C5+'Balance Sheet'!C6+'Balance Sheet'!C7+'Balance Sheet'!C8-'Balance Sheet'!C11 | D9: ='Balance Sheet'!D5+'Balance Sheet'!D6+'Balance Sheet'!D7+'Balance Sheet'!D8-'Balance Sheet'!D11 | E9: Positive + growing

Sheet Sources & Uses
A1: SBA LOAN — SOURCES & USES
A3: Item | B3: Amount
A4: SOURCES
A5: SBA loan proceeds (net of guarantee fee) | B5: =Assumptions!$B$32*(1-Assumptions!$B$35)
A6: Owner cash injection | B6: =Assumptions!$B$36
A7: Existing cash on hand | B7: 0
A8: Total sources | B8: =SUM(B5:B7)
A10: USES
A11: Working capital (12-month operating reserve) | B11: ='Cashflow Y1-Y3'!B5*-1*0.25
A12: Equipment purchases | B12: =Assumptions!$B$30
A13: Refinance existing high-rate debt | B13: 0
A14: Acquisition / goodwill (if applicable) | B14: 0
A15: SBA guarantee fee + closing costs | B15: =Assumptions!$B$32*(Assumptions!$B$35+0.01)
A16: Total uses | B16: =SUM(B11:B15)
A18: Difference (should be 0) | B18: =B8-B16

Sheet Lender Summary
A1: LENDER SUBMISSION SUMMARY (1-page)
A3: Borrower legal name
A4: EIN
A5: Business address
A6: Years in business
A7: NAICS code | B7: 236220 = Commercial
A8: Number of employees
A10: Loan amount requested | B10: =Assumptions!$B$32
A11: Loan type (7a / 504 / Express / Microloan) | B11: 7(a)
A12: Loan use (primary) | B12: Working capital + equipment
A13: Amortization | B13: =Assumptions!$B$34&" months"
A14: Owner equity injection | B14: =Assumptions!$B$36
A16: Y1 revenue (projected) | B16: ='P&L Y1-Y3'!N5
A17: Y1 EBITDA (≈ OP + Depr) | B17: ='P&L Y1-Y3'!N21+'P&L Y1-Y3'!N19
A18: Y1 DSCR | B18: =Ratios!B4
A19: Y2 DSCR | B19: =Ratios!C4
A20: Y3 DSCR | B20: =Ratios!D4
A22: Existing senior debt (total) | B22: 0
A23: Personal credit score (owner)
A24: Personal liquidity (owner)
A25: Real estate collateral available? | B25: Y/N
A26: UCC collateral available? | B26: Y/N
A28: Prepared by
A29: Date prepared
