Workbook
Name CSI_Divisions: 'CSI Reference'!$A$4:$A$38
Name CSI_Table: 'CSI Reference'!$A$4:$B$38

Sheet Instructions
B2: ContrPro - Accounts Receivable (AR) Tracker
B3: CSI MasterFormat-coded invoice tracker - who owes you what, how old it is, and when to start pulling on the line.
B5: What this workbook is
B6: Five visible tabs plus a hidden CSI Reference. Project Info pins the contract, Invoice Log is the main worksheet, Aging Summary buckets every dollar by how late it is, and Dashboard shows the headline numbers (Total Outstanding, DSO, retainage held).
B7: Every invoice you cut goes in the Invoice Log. The aging math is automatic - you fill in dates and amounts, the workbook tells you who is current, who is 30 days late, and who is past 90 and burning.
B9: Aging buckets - the cadence
B10: Current - not yet past due. Healthy. Do nothing.
B11: 1-30 - 1 to 30 days past due. Standard reminder call/email. Most owners pay in this window.
B12: 31-60 - 31 to 60 days past due. Escalate to the PM and copy the owner's accountant.
B13: 61-90 - 61 to 90 days past due. CFO-level conversation. Stop further work if contract allows.
B14: 91-120 - 91 to 120 days past due. Formal demand letter. Pre-lien notices in many states.
B15: 120+ - over 120 days. Mechanic's lien window or attorney referral. Statute clock is ticking.
... B67: ContrPro - built for builders. Questions: support@contrpro.com

Sheet Project Info
A1: Project Information
A3: Project Name | B3: Project Number | C3: Client | D3: Contract Amount | E3: Project Manager | F3: Notes
A4: EXAMPLE - Riverside Office Bldg | B4: 2026-014 | C4: Riverside Holdings LLC | D4: 1850000 | E4: Sample PM | F4: Example row - replace with your project.

Sheet Invoice Log
A1: Invoice Log (CSI MasterFormat)
A3: Invoice Number | B3: Date Issued | C3: Customer / Job | D3: CSI Division | E3: CSI Code | F3: Division Name | G3: Description | H3: Base Amount | I3: Retainage Withheld | J3: Total Invoice | K3: Date Due | L3: Date Paid | M3: Amount Paid | N3: Outstanding | O3: Aging Bucket | P3: Days Outstanding | Q3: Lien Waiver Received? | R3: Status | S3: Notes
A4: INV-1001 | B4: 2026-03-20 | C4: Riverside Holdings LLC | D4: 03 | E4: 03 30 00 | F4: =IFERROR(VLOOKUP(D4,CSI_Table,2,FALSE),"") | G4: Pay App #2 - Cast-in-place concrete, footings & SOG. | H4: 48500 | I4: 2425 | J4: =IFERROR(H4,0) | K4: 2026-04-19 | L4: 2026-04-17 | M4: 48500 | N4: =IFERROR(J4-IFERROR(M4,0),0) | O4: =IF(AND(L4<>"",IFERROR(M4,0)>=IFERROR(J4,0),IFERROR(J4,0)>0),"Paid",IF(K4="","",IF(TODAY()-K4<=0,"Current",IF(TODAY()-K4<=30,"1-30",IF(TODAY()-K4<=60,"31-60",IF(TODAY()-K4<=90,"61-90",IF(TODAY()-K4<=120,"91-120","120+"))))))) | P4: =IF(OR(K4="",IFERROR(N4,0)<=0),"",MAX(0,TODAY()-K4)) | Q4: Yes | R4: Paid | S4: Paid in full. Unconditional lien waiver on file.
A5: INV-1002 | B5: 2026-04-25 | C5: Riverside Holdings LLC | D5: 05 | E5: 05 12 00 | F5: =IFERROR(VLOOKUP(D5,CSI_Table,2,FALSE),"") | G5: Pay App #3 - Structural steel erection, Level 1-2. | H5: 62300 | I5: 3115 | J5: =IFERROR(H5,0) | K5: 2026-05-25 | M5: 0 | N5: =IFERROR(J5-IFERROR(M5,0),0) | O5: =IF(AND(L5<>"",IFERROR(M5,0)>=IFERROR(J5,0),IFERROR(J5,0)>0),"Paid",IF(K5="","",IF(TODAY()-K5<=0,"Current",IF(TODAY()-K5<=30,"1-30",IF(TODAY()-K5<=60,"31-60",IF(TODAY()-K5<=90,"61-90",IF(TODAY()-K5<=120,"91-120","120+"))))))) | P5: =IF(OR(K5="",IFERROR(N5,0)<=0),"",MAX(0,TODAY()-K5)) | Q5: Conditional | R5: Sent | S5: Pay app submitted. Conditional waiver issued; final on receipt.
A6: INV-1003 | B6: 2026-03-06 | C6: Pinnacle Dev Corp | D6: 23 | E6: 23 30 00 | F6: =IFERROR(VLOOKUP(D6,CSI_Table,2,FALSE),"") | G6: Pay App #1 - HVAC rough-in, Level 2 air distribution. | H6: 28750 | I6: 1437.5 | J6: =IFERROR(H6,0) | K6: 2026-04-05 | M6: 0 | N6: =IFERROR(J6-IFERROR(M6,0),0) | O6: =IF(AND(L6<>"",IFERROR(M6,0)>=IFERROR(J6,0),IFERROR(J6,0)>0),"Paid",IF(K6="","",IF(TODAY()-K6<=0,"Current",IF(TODAY()-K6<=30,"1-30",IF(TODAY()-K6<=60,"31-60",IF(TODAY()-K6<=90,"61-90",IF(TODAY()-K6<=120,"91-120","120+"))))))) | P6: =IF(OR(K6="",IFERROR(N6,0)<=0),"",MAX(0,TODAY()-K6)) | Q6: No | R6: Partially Paid | S6: Owner remitted $15k against this invoice; $13,750 outstanding. Follow-up email sent 2026-04-22.
A7: INV-1004 | B7: 2026-01-30 | C7: Heartland Builders | D7: 26 | E7: 26 50 00 | F7: =IFERROR(VLOOKUP(D7,CSI_Table,2,FALSE),"") | G7: Pay App #4 - Lighting fixtures & emergency egress install. | H7: 19400 | I7: 970 | J7: =IFERROR(H7,0) | K7: 2026-03-01 | M7: 0 | N7: =IFERROR(J7-IFERROR(M7,0),0) | O7: =IF(AND(L7<>"",IFERROR(M7,0)>=IFERROR(J7,0),IFERROR(J7,0)>0),"Paid",IF(K7="","",IF(TODAY()-K7<=0,"Current",IF(TODAY()-K7<=30,"1-30",IF(TODAY()-K7<=60,"31-60",IF(TODAY()-K7<=90,"61-90",IF(TODAY()-K7<=120,"91-120","120+"))))))) | P7: =IF(OR(K7="",IFERROR(N7,0)<=0),"",MAX(0,TODAY()-K7)) | Q7: No | R7: Disputed | S7: Owner disputes 6 fixture count. Demand letter draft prepared; escalate to attorney week of 5/19.
A8: INV-1005 | B8: 2025-12-11 | C8: Apex Industrial | D8: 07 | E8: 07 50 00 | F8: =IFERROR(VLOOKUP(D8,CSI_Table,2,FALSE),"") | G8: Pay App #2 - Membrane roofing, 32 sq install. | H8: 14200 | I8: 0 | J8: =IFERROR(H8,0) | K8: 2026-01-10 | M8: 0 | N8: =IFERROR(J8-IFERROR(M8,0),0) | O8: =IF(AND(L8<>"",IFERROR(M8,0)>=IFERROR(J8,0),IFERROR(J8,0)>0),"Paid",IF(K8="","",IF(TODAY()-K8<=0,"Current",IF(TODAY()-K8<=30,"1-30",IF(TODAY()-K8<=60,"31-60",IF(TODAY()-K8<=90,"61-90",IF(TODAY()-K8<=120,"91-120","120+"))))))) | P8: =IF(OR(K8="",IFERROR(N8,0)<=0),"",MAX(0,TODAY()-K8)) | Q8: No | R8: Disputed | S8: 120+ days. Notice of intent to lien filed 2026-04-15. Lien deadline tracking - confirm state statute window.
F9: =IFERROR(VLOOKUP(D9,CSI_Table,2,FALSE),"") | J9: =IFERROR(H9,0) | N9: =IFERROR(J9-IFERROR(M9,0),0) | O9: =IF(AND(L9<>"",IFERROR(M9,0)>=IFERROR(J9,0),IFERROR(J9,0)>0),"Paid",IF(K9="","",IF(TODAY()-K9<=0,"Current",IF(TODAY()-K9<=30,"1-30",IF(TODAY()-K9<=60,"31-60",IF(TODAY()-K9<=90,"61-90",IF(TODAY()-K9<=120,"91-120","120+"))))))) | P9: =IF(OR(K9="",IFERROR(N9,0)<=0),"",MAX(0,TODAY()-K9))
F10: =IFERROR(VLOOKUP(D10,CSI_Table,2,FALSE),"") | J10: =IFERROR(H10,0) | N10: =IFERROR(J10-IFERROR(M10,0),0) | O10: =IF(AND(L10<>"",IFERROR(M10,0)>=IFERROR(J10,0),IFERROR(J10,0)>0),"Paid",IF(K10="","",IF(TODAY()-K10<=0,"Current",IF(TODAY()-K10<=30,"1-30",IF(TODAY()-K10<=60,"31-60",IF(TODAY()-K10<=90,"61-90",IF(TODAY()-K10<=120,"91-120","120+"))))))) | P10: =IF(OR(K10="",IFERROR(N10,0)<=0),"",MAX(0,TODAY()-K10))
F11: =IFERROR(VLOOKUP(D11,CSI_Table,2,FALSE),"") | J11: =IFERROR(H11,0) | N11: =IFERROR(J11-IFERROR(M11,0),0) | O11: =IF(AND(L11<>"",IFERROR(M11,0)>=IFERROR(J11,0),IFERROR(J11,0)>0),"Paid",IF(K11="","",IF(TODAY()-K11<=0,"Current",IF(TODAY()-K11<=30,"1-30",IF(TODAY()-K11<=60,"31-60",IF(TODAY()-K11<=90,"61-90",IF(TODAY()-K11<=120,"91-120","120+"))))))) | P11: =IF(OR(K11="",IFERROR(N11,0)<=0),"",MAX(0,TODAY()-K11))
F12: =IFERROR(VLOOKUP(D12,CSI_Table,2,FALSE),"") | J12: =IFERROR(H12,0) | N12: =IFERROR(J12-IFERROR(M12,0),0) | O12: =IF(AND(L12<>"",IFERROR(M12,0)>=IFERROR(J12,0),IFERROR(J12,0)>0),"Paid",IF(K12="","",IF(TODAY()-K12<=0,"Current",IF(TODAY()-K12<=30,"1-30",IF(TODAY()-K12<=60,"31-60",IF(TODAY()-K12<=90,"61-90",IF(TODAY()-K12<=120,"91-120","120+"))))))) | P12: =IF(OR(K12="",IFERROR(N12,0)<=0),"",MAX(0,TODAY()-K12))
F13: =IFERROR(VLOOKUP(D13,CSI_Table,2,FALSE),"") | J13: =IFERROR(H13,0) | N13: =IFERROR(J13-IFERROR(M13,0),0) | O13: =IF(AND(L13<>"",IFERROR(M13,0)>=IFERROR(J13,0),IFERROR(J13,0)>0),"Paid",IF(K13="","",IF(TODAY()-K13<=0,"Current",IF(TODAY()-K13<=30,"1-30",IF(TODAY()-K13<=60,"31-60",IF(TODAY()-K13<=90,"61-90",IF(TODAY()-K13<=120,"91-120","120+"))))))) | P13: =IF(OR(K13="",IFERROR(N13,0)<=0),"",MAX(0,TODAY()-K13))
F14: =IFERROR(VLOOKUP(D14,CSI_Table,2,FALSE),"") | J14: =IFERROR(H14,0) | N14: =IFERROR(J14-IFERROR(M14,0),0) | O14: =IF(AND(L14<>"",IFERROR(M14,0)>=IFERROR(J14,0),IFERROR(J14,0)>0),"Paid",IF(K14="","",IF(TODAY()-K14<=0,"Current",IF(TODAY()-K14<=30,"1-30",IF(TODAY()-K14<=60,"31-60",IF(TODAY()-K14<=90,"61-90",IF(TODAY()-K14<=120,"91-120","120+"))))))) | P14: =IF(OR(K14="",IFERROR(N14,0)<=0),"",MAX(0,TODAY()-K14))
F15: =IFERROR(VLOOKUP(D15,CSI_Table,2,FALSE),"") | J15: =IFERROR(H15,0) | N15: =IFERROR(J15-IFERROR(M15,0),0) | O15: =IF(AND(L15<>"",IFERROR(M15,0)>=IFERROR(J15,0),IFERROR(J15,0)>0),"Paid",IF(K15="","",IF(TODAY()-K15<=0,"Current",IF(TODAY()-K15<=30,"1-30",IF(TODAY()-K15<=60,"31-60",IF(TODAY()-K15<=90,"61-90",IF(TODAY()-K15<=120,"91-120","120+"))))))) | P15: =IF(OR(K15="",IFERROR(N15,0)<=0),"",MAX(0,TODAY()-K15))
F16: =IFERROR(VLOOKUP(D16,CSI_Table,2,FALSE),"") | J16: =IFERROR(H16,0) | N16: =IFERROR(J16-IFERROR(M16,0),0) | O16: =IF(AND(L16<>"",IFERROR(M16,0)>=IFERROR(J16,0),IFERROR(J16,0)>0),"Paid",IF(K16="","",IF(TODAY()-K16<=0,"Current",IF(TODAY()-K16<=30,"1-30",IF(TODAY()-K16<=60,"31-60",IF(TODAY()-K16<=90,"61-90",IF(TODAY()-K16<=120,"91-120","120+"))))))) | P16: =IF(OR(K16="",IFERROR(N16,0)<=0),"",MAX(0,TODAY()-K16))
F17: =IFERROR(VLOOKUP(D17,CSI_Table,2,FALSE),"") | J17: =IFERROR(H17,0) | N17: =IFERROR(J17-IFERROR(M17,0),0) | O17: =IF(AND(L17<>"",IFERROR(M17,0)>=IFERROR(J17,0),IFERROR(J17,0)>0),"Paid",IF(K17="","",IF(TODAY()-K17<=0,"Current",IF(TODAY()-K17<=30,"1-30",IF(TODAY()-K17<=60,"31-60",IF(TODAY()-K17<=90,"61-90",IF(TODAY()-K17<=120,"91-120","120+"))))))) | P17: =IF(OR(K17="",IFERROR(N17,0)<=0),"",MAX(0,TODAY()-K17))
F18: =IFERROR(VLOOKUP(D18,CSI_Table,2,FALSE),"") | J18: =IFERROR(H18,0) | N18: =IFERROR(J18-IFERROR(M18,0),0) | O18: =IF(AND(L18<>"",IFERROR(M18,0)>=IFERROR(J18,0),IFERROR(J18,0)>0),"Paid",IF(K18="","",IF(TODAY()-K18<=0,"Current",IF(TODAY()-K18<=30,"1-30",IF(TODAY()-K18<=60,"31-60",IF(TODAY()-K18<=90,"61-90",IF(TODAY()-K18<=120,"91-120","120+"))))))) | P18: =IF(OR(K18="",IFERROR(N18,0)<=0),"",MAX(0,TODAY()-K18))
F19: =IFERROR(VLOOKUP(D19,CSI_Table,2,FALSE),"") | J19: =IFERROR(H19,0) | N19: =IFERROR(J19-IFERROR(M19,0),0) | O19: =IF(AND(L19<>"",IFERROR(M19,0)>=IFERROR(J19,0),IFERROR(J19,0)>0),"Paid",IF(K19="","",IF(TODAY()-K19<=0,"Current",IF(TODAY()-K19<=30,"1-30",IF(TODAY()-K19<=60,"31-60",IF(TODAY()-K19<=90,"61-90",IF(TODAY()-K19<=120,"91-120","120+"))))))) | P19: =IF(OR(K19="",IFERROR(N19,0)<=0),"",MAX(0,TODAY()-K19))
F20: =IFERROR(VLOOKUP(D20,CSI_Table,2,FALSE),"") | J20: =IFERROR(H20,0) | N20: =IFERROR(J20-IFERROR(M20,0),0) | O20: =IF(AND(L20<>"",IFERROR(M20,0)>=IFERROR(J20,0),IFERROR(J20,0)>0),"Paid",IF(K20="","",IF(TODAY()-K20<=0,"Current",IF(TODAY()-K20<=30,"1-30",IF(TODAY()-K20<=60,"31-60",IF(TODAY()-K20<=90,"61-90",IF(TODAY()-K20<=120,"91-120","120+"))))))) | P20: =IF(OR(K20="",IFERROR(N20,0)<=0),"",MAX(0,TODAY()-K20))
... F33: =IFERROR(VLOOKUP(D33,CSI_Table,2,FALSE),"") | J33: =IFERROR(H33,0) | N33: =IFERROR(J33-IFERROR(M33,0),0) | O33: =IF(AND(L33<>"",IFERROR(M33,0)>=IFERROR(J33,0),IFERROR(J33,0)>0),"Paid",IF(K33="","",IF(TODAY()-K33<=0,"Current",IF(TODAY()-K33<=30,"1-30",IF(TODAY()-K33<=60,"31-60",IF(TODAY()-K33<=90,"61-90",IF(TODAY()-K33<=120,"91-120","120+"))))))) | P33: =IF(OR(K33="",IFERROR(N33,0)<=0),"",MAX(0,TODAY()-K33))
G35: TOTALS | H35: =SUM(H4:H33) | I35: =SUM(I4:I33) | J35: =SUM(J4:J33) | M35: =SUM(M4:M33) | N35: =SUM(N4:N33)

Sheet Aging Summary
A1: AR Aging Summary (auto roll-up)
A2: Reads from Invoice Log via COUNTIF / SUMIFS - do not edit this tab directly. One row per aging bucket.
A3: Aging Bucket | B3: Count | C3: Total Outstanding | D3: % of Total
A4: Current | B4: =COUNTIF('Invoice Log'!$O$4:$O$33,A4) | C4: =SUMIFS('Invoice Log'!$N$4:$N$33,'Invoice Log'!$O$4:$O$33,A4) | D4: =IFERROR(C4/$C$10,0)
A5: 1-30 | B5: =COUNTIF('Invoice Log'!$O$4:$O$33,A5) | C5: =SUMIFS('Invoice Log'!$N$4:$N$33,'Invoice Log'!$O$4:$O$33,A5) | D5: =IFERROR(C5/$C$10,0)
A6: 31-60 | B6: =COUNTIF('Invoice Log'!$O$4:$O$33,A6) | C6: =SUMIFS('Invoice Log'!$N$4:$N$33,'Invoice Log'!$O$4:$O$33,A6) | D6: =IFERROR(C6/$C$10,0)
A7: 61-90 | B7: =COUNTIF('Invoice Log'!$O$4:$O$33,A7) | C7: =SUMIFS('Invoice Log'!$N$4:$N$33,'Invoice Log'!$O$4:$O$33,A7) | D7: =IFERROR(C7/$C$10,0)
A8: 91-120 | B8: =COUNTIF('Invoice Log'!$O$4:$O$33,A8) | C8: =SUMIFS('Invoice Log'!$N$4:$N$33,'Invoice Log'!$O$4:$O$33,A8) | D8: =IFERROR(C8/$C$10,0)
A9: 120+ | B9: =COUNTIF('Invoice Log'!$O$4:$O$33,A9) | C9: =SUMIFS('Invoice Log'!$N$4:$N$33,'Invoice Log'!$O$4:$O$33,A9) | D9: =IFERROR(C9/$C$10,0)
A10: TOTAL OUTSTANDING | B10: =SUM(B4:B9) | C10: =SUM(C4:C9) | D10: =1

Sheet Dashboard
A1: Accounts Receivable Dashboard
A2: Auto-calculated from Project Info and Invoice Log. Update those tabs - this one stays in sync.
A4: AR Headline
A5: Total Invoiced | D5: =SUM('Invoice Log'!$J$4:$J$33)
A6: Total Paid | D6: =SUM('Invoice Log'!$M$4:$M$33)
A7: Total Outstanding | D7: =SUM('Invoice Log'!$N$4:$N$33)
A8: Total Retainage Held | D8: =SUM('Invoice Log'!$I$4:$I$33)
A9: Days Sales Outstanding (DSO) | D9: =IFERROR(SUMPRODUCT('Invoice Log'!$N$4:$N$33,IFERROR('Invoice Log'!$P$4:$P$33+0,0))/SUM('Invoice Log'!$N$4:$N$33),0)
A12: Aging Breakdown
A13: Aging Bucket | B13: Count | C13: Outstanding
A14: Current | C14: =COUNTIF('Invoice Log'!$O$4:$O$33,"Current") | D14: =SUMIFS('Invoice Log'!$N$4:$N$33,'Invoice Log'!$O$4:$O$33,"Current") | E14: =IFERROR(SUMIFS('Invoice Log'!$N$4:$N$33,'Invoice Log'!$O$4:$O$33,"Current")/SUM('Invoice Log'!$N$4:$N$33),0)
A15: 1-30 | C15: =COUNTIF('Invoice Log'!$O$4:$O$33,"1-30") | D15: =SUMIFS('Invoice Log'!$N$4:$N$33,'Invoice Log'!$O$4:$O$33,"1-30") | E15: =IFERROR(SUMIFS('Invoice Log'!$N$4:$N$33,'Invoice Log'!$O$4:$O$33,"1-30")/SUM('Invoice Log'!$N$4:$N$33),0)
A16: 31-60 | C16: =COUNTIF('Invoice Log'!$O$4:$O$33,"31-60") | D16: =SUMIFS('Invoice Log'!$N$4:$N$33,'Invoice Log'!$O$4:$O$33,"31-60") | E16: =IFERROR(SUMIFS('Invoice Log'!$N$4:$N$33,'Invoice Log'!$O$4:$O$33,"31-60")/SUM('Invoice Log'!$N$4:$N$33),0)
A17: 61-90 | C17: =COUNTIF('Invoice Log'!$O$4:$O$33,"61-90") | D17: =SUMIFS('Invoice Log'!$N$4:$N$33,'Invoice Log'!$O$4:$O$33,"61-90") | E17: =IFERROR(SUMIFS('Invoice Log'!$N$4:$N$33,'Invoice Log'!$O$4:$O$33,"61-90")/SUM('Invoice Log'!$N$4:$N$33),0)
A18: 91-120 | C18: =COUNTIF('Invoice Log'!$O$4:$O$33,"91-120") | D18: =SUMIFS('Invoice Log'!$N$4:$N$33,'Invoice Log'!$O$4:$O$33,"91-120") | E18: =IFERROR(SUMIFS('Invoice Log'!$N$4:$N$33,'Invoice Log'!$O$4:$O$33,"91-120")/SUM('Invoice Log'!$N$4:$N$33),0)
A19: 120+ | C19: =COUNTIF('Invoice Log'!$O$4:$O$33,"120+") | D19: =SUMIFS('Invoice Log'!$N$4:$N$33,'Invoice Log'!$O$4:$O$33,"120+") | E19: =IFERROR(SUMIFS('Invoice Log'!$N$4:$N$33,'Invoice Log'!$O$4:$O$33,"120+")/SUM('Invoice Log'!$N$4:$N$33),0)
A20: TOTAL OUTSTANDING | C20: =COUNTIF('Invoice Log'!$O$4:$O$33,"Current")+COUNTIF('Invoice Log'!$O$4:$O$33,"1-30")+COUNTIF('Invoice Log'!$O$4:$O$33,"31-60")+COUNTIF('Invoice Log'!$O$4:$O$33,"61-90")+COUNTIF('Invoice Log'!$O$4:$O$33,"91-120")+COUNTIF('Invoice Log'!$O$4:$O$33,"120+") | D20: =SUM('Invoice Log'!$N$4:$N$33) | E20: =1
A22: Count by Status
A23: Status | B23: Count | C23: Amount Outstanding
A24: Sent | C24: =COUNTIF('Invoice Log'!$R$4:$R$33,"Sent") | D24: =SUMIFS('Invoice Log'!$N$4:$N$33,'Invoice Log'!$R$4:$R$33,"Sent") | E24: =IFERROR(SUMIFS('Invoice Log'!$N$4:$N$33,'Invoice Log'!$R$4:$R$33,"Sent")/SUM('Invoice Log'!$N$4:$N$33),0)
A25: Partially Paid | C25: =COUNTIF('Invoice Log'!$R$4:$R$33,"Partially Paid") | D25: =SUMIFS('Invoice Log'!$N$4:$N$33,'Invoice Log'!$R$4:$R$33,"Partially Paid") | E25: =IFERROR(SUMIFS('Invoice Log'!$N$4:$N$33,'Invoice Log'!$R$4:$R$33,"Partially Paid")/SUM('Invoice Log'!$N$4:$N$33),0)
A26: Paid | C26: =COUNTIF('Invoice Log'!$R$4:$R$33,"Paid") | D26: =SUMIFS('Invoice Log'!$N$4:$N$33,'Invoice Log'!$R$4:$R$33,"Paid") | E26: =IFERROR(SUMIFS('Invoice Log'!$N$4:$N$33,'Invoice Log'!$R$4:$R$33,"Paid")/SUM('Invoice Log'!$N$4:$N$33),0)
A27: Disputed | C27: =COUNTIF('Invoice Log'!$R$4:$R$33,"Disputed") | D27: =SUMIFS('Invoice Log'!$N$4:$N$33,'Invoice Log'!$R$4:$R$33,"Disputed") | E27: =IFERROR(SUMIFS('Invoice Log'!$N$4:$N$33,'Invoice Log'!$R$4:$R$33,"Disputed")/SUM('Invoice Log'!$N$4:$N$33),0)
A28: Written Off | C28: =COUNTIF('Invoice Log'!$R$4:$R$33,"Written Off") | D28: =SUMIFS('Invoice Log'!$N$4:$N$33,'Invoice Log'!$R$4:$R$33,"Written Off") | E28: =IFERROR(SUMIFS('Invoice Log'!$N$4:$N$33,'Invoice Log'!$R$4:$R$33,"Written Off")/SUM('Invoice Log'!$N$4:$N$33),0)
A29: ALL INVOICES (any status) | C29: =COUNTA('Invoice Log'!$A$4:$A$33) | D29: =SUM('Invoice Log'!$N$4:$N$33) | E29: =1

Sheet CSI Reference
A1: CSI MasterFormat Division Reference
A2: Pulled from the same canonical list as ContrPro Job Costing. Do not edit.
A3: CSI Division | B3: Division Name
A4: 01 | B4: General Requirements
A5: 02 | B5: Existing Conditions
A6: 03 | B6: Concrete
A7: 04 | B7: Masonry
A8: 05 | B8: Metals
A9: 06 | B9: Wood, Plastics, and Composites
A10: 07 | B10: Thermal and Moisture Protection
A11: 08 | B11: Openings
A12: 09 | B12: Finishes
A13: 10 | B13: Specialties
A14: 11 | B14: Equipment
... A38: 49 | B38: Reserved
