Workbook

Sheet Instructions
B2: ContrPro - Job Costing Spreadsheet
B3: CSI MasterFormat-coded job cost tracker for general contractors and trade subs.
B5: How to use this workbook
B6: This workbook tracks budget vs. actual cost on a single construction job, organized by CSI MasterFormat division and section. Five tabs work together: Job Info captures the contract, Cost Tracking is where line-item costs go, Division Summary rolls them up, and Dashboard shows the bottom line.
B7: Open the tabs at the bottom of the window in this order: Job Info first, then Cost Tracking, then check Division Summary and Dashboard.
B9: 1. Job Info
B10: Fill in Job Name, Job Number, Client, Contract Amount, Start Date, Target Completion, Project Manager, and Estimator on row 4 (the first blank row).
B11: Status is a dropdown: Not Started, In Progress, Substantial Completion, Final, On Hold.
B12: Contract Amount on the FIRST job row (row 4) is the value the Dashboard reads for profit projections. If you track multiple jobs, build a separate file per job.
B14: 2. Cost Tracking
B15: Each row is one scope item, coded by CSI Division (2-digit) and CSI Code (6-digit, e.g. 05 12 00).
B16: Pre-populated rows cover the divisions most jobs touch. Add more at the bottom in the empty rows.
... B52: ContrPro - built for builders. Questions: support@contrpro.com

Sheet Job Info
A1: Job Information
A3: Job Name | B3: Job Number | C3: Client Name | D3: Contract Amount | E3: Start Date | F3: Target Completion | G3: Actual Completion | H3: Status | I3: Project Manager | J3: Estimator | K3: Notes
A4: EXAMPLE - Riverside Office Bldg | B4: 2026-014 | C4: Riverside Holdings LLC | D4: 1850000 | E4: 2026-03-01 | F4: 2026-11-30 | H4: In Progress | I4: Sample PM | J4: Sample Estimator | K4: Example row - replace with your job.

Sheet Cost Tracking
A1: Cost Tracking (CSI MasterFormat)
A3: CSI Division | B3: CSI Code | C3: Division Name | D3: Description / Scope Item | E3: Trade | F3: Budget | G3: Committed | H3: Actual to Date | I3: Variance | J3: % Complete | K3: Earned Value | L3: Schedule of Values Item | M3: Notes
A4: 01 | B4: 01 10 00 | C4: General Requirements | D4: Summary | E4: General | I4: =IFERROR(F4-H4,0) | K4: =IFERROR(F4*J4,0)
A5: 01 | B5: 01 50 00 | C5: General Requirements | D5: Temporary Facilities and Controls | E5: General | I5: =IFERROR(F5-H5,0) | K5: =IFERROR(F5*J5,0)
A6: 01 | B6: 01 70 00 | C6: General Requirements | D6: Execution and Closeout Requirements | E6: General | I6: =IFERROR(F6-H6,0) | K6: =IFERROR(F6*J6,0)
A7: 02 | B7: 02 30 00 | C7: Existing Conditions | D7: Assessment | E7: General | I7: =IFERROR(F7-H7,0) | K7: =IFERROR(F7*J7,0)
A8: 02 | B8: 02 41 00 | C8: Existing Conditions | D8: Demolition | E8: General | I8: =IFERROR(F8-H8,0) | K8: =IFERROR(F8*J8,0)
A9: 03 | B9: 03 30 00 | C9: Concrete | D9: Cast-in-Place Concrete | E9: Structural Steel | I9: =IFERROR(F9-H9,0) | K9: =IFERROR(F9*J9,0)
A10: 03 | B10: 03 40 00 | C10: Concrete | D10: Precast Concrete | E10: Structural Steel | I10: =IFERROR(F10-H10,0) | K10: =IFERROR(F10*J10,0)
A11: 04 | B11: 04 20 00 | C11: Masonry | D11: Unit Masonry | E11: General | I11: =IFERROR(F11-H11,0) | K11: =IFERROR(F11*J11,0)
A12: 05 | B12: 05 12 00 | C12: Metals | D12: Structural Steel Framing | E12: Structural Steel | I12: =IFERROR(F12-H12,0) | K12: =IFERROR(F12*J12,0)
A13: 05 | B13: 05 31 00 | C13: Metals | D13: Steel Decking | E13: Structural Steel | I13: =IFERROR(F13-H13,0) | K13: =IFERROR(F13*J13,0)
A14: 05 | B14: 05 50 00 | C14: Metals | D14: Metal Fabrications | E14: Structural Steel | I14: =IFERROR(F14-H14,0) | K14: =IFERROR(F14*J14,0)
A15: 06 | B15: 06 10 00 | C15: Wood, Plastics, and Composites | D15: Rough Carpentry | E15: General | I15: =IFERROR(F15-H15,0) | K15: =IFERROR(F15*J15,0)
... A40: 33 | B40: 33 10 00 | C40: Utilities | D40: Water Utilities | E40: General | I40: =IFERROR(F40-H40,0) | K40: =IFERROR(F40*J40,0)
I41: =IFERROR(F41-H41,0) | K41: =IFERROR(F41*J41,0)
I42: =IFERROR(F42-H42,0) | K42: =IFERROR(F42*J42,0)
I43: =IFERROR(F43-H43,0) | K43: =IFERROR(F43*J43,0)
I44: =IFERROR(F44-H44,0) | K44: =IFERROR(F44*J44,0)
I45: =IFERROR(F45-H45,0) | K45: =IFERROR(F45*J45,0)
I46: =IFERROR(F46-H46,0) | K46: =IFERROR(F46*J46,0)
I47: =IFERROR(F47-H47,0) | K47: =IFERROR(F47*J47,0)
I48: =IFERROR(F48-H48,0) | K48: =IFERROR(F48*J48,0)
I49: =IFERROR(F49-H49,0) | K49: =IFERROR(F49*J49,0)
I50: =IFERROR(F50-H50,0) | K50: =IFERROR(F50*J50,0)
E52: TOTALS | F52: =SUM(F4:F50) | G52: =SUM(G4:G50) | H52: =SUM(H4:H50) | I52: =SUM(I4:I50) | J52: =IFERROR(SUMPRODUCT(F4:F50,J4:J50)/SUM(F4:F50),0) | K52: =SUM(K4:K50)

Sheet Division Summary
A1: Division Summary (auto roll-up)
A2: Reads from Cost Tracking via SUMIF - do not edit this tab directly.
A3: CSI Division | B3: Division Name | C3: Total Budget | D3: Total Committed | E3: Total Actual | F3: Total Variance | G3: Weighted % Complete | H3: Total Earned Value
A4: 01 | B4: General Requirements | C4: =SUMIF('Cost Tracking'!$A$4:$A$50,A4,'Cost Tracking'!$F$4:$F$50) | D4: =SUMIF('Cost Tracking'!$A$4:$A$50,A4,'Cost Tracking'!$G$4:$G$50) | E4: =SUMIF('Cost Tracking'!$A$4:$A$50,A4,'Cost Tracking'!$H$4:$H$50) | F4: =SUMIF('Cost Tracking'!$A$4:$A$50,A4,'Cost Tracking'!$I$4:$I$50) | G4: =IFERROR(SUMPRODUCT(('Cost Tracking'!$A$4:$A$50=A4)*'Cost Tracking'!$F$4:$F$50*'Cost Tracking'!$J$4:$J$50)/SUMIF('Cost Tracking'!$A$4:$A$50,A4,'Cost Tracking'!$F$4:$F$50),0) | H4: =SUMIF('Cost Tracking'!$A$4:$A$50,A4,'Cost Tracking'!$K$4:$K$50)
A5: 02 | B5: Existing Conditions | C5: =SUMIF('Cost Tracking'!$A$4:$A$50,A5,'Cost Tracking'!$F$4:$F$50) | D5: =SUMIF('Cost Tracking'!$A$4:$A$50,A5,'Cost Tracking'!$G$4:$G$50) | E5: =SUMIF('Cost Tracking'!$A$4:$A$50,A5,'Cost Tracking'!$H$4:$H$50) | F5: =SUMIF('Cost Tracking'!$A$4:$A$50,A5,'Cost Tracking'!$I$4:$I$50) | G5: =IFERROR(SUMPRODUCT(('Cost Tracking'!$A$4:$A$50=A5)*'Cost Tracking'!$F$4:$F$50*'Cost Tracking'!$J$4:$J$50)/SUMIF('Cost Tracking'!$A$4:$A$50,A5,'Cost Tracking'!$F$4:$F$50),0) | H5: =SUMIF('Cost Tracking'!$A$4:$A$50,A5,'Cost Tracking'!$K$4:$K$50)
A6: 03 | B6: Concrete | C6: =SUMIF('Cost Tracking'!$A$4:$A$50,A6,'Cost Tracking'!$F$4:$F$50) | D6: =SUMIF('Cost Tracking'!$A$4:$A$50,A6,'Cost Tracking'!$G$4:$G$50) | E6: =SUMIF('Cost Tracking'!$A$4:$A$50,A6,'Cost Tracking'!$H$4:$H$50) | F6: =SUMIF('Cost Tracking'!$A$4:$A$50,A6,'Cost Tracking'!$I$4:$I$50) | G6: =IFERROR(SUMPRODUCT(('Cost Tracking'!$A$4:$A$50=A6)*'Cost Tracking'!$F$4:$F$50*'Cost Tracking'!$J$4:$J$50)/SUMIF('Cost Tracking'!$A$4:$A$50,A6,'Cost Tracking'!$F$4:$F$50),0) | H6: =SUMIF('Cost Tracking'!$A$4:$A$50,A6,'Cost Tracking'!$K$4:$K$50)
A7: 04 | B7: Masonry | C7: =SUMIF('Cost Tracking'!$A$4:$A$50,A7,'Cost Tracking'!$F$4:$F$50) | D7: =SUMIF('Cost Tracking'!$A$4:$A$50,A7,'Cost Tracking'!$G$4:$G$50) | E7: =SUMIF('Cost Tracking'!$A$4:$A$50,A7,'Cost Tracking'!$H$4:$H$50) | F7: =SUMIF('Cost Tracking'!$A$4:$A$50,A7,'Cost Tracking'!$I$4:$I$50) | G7: =IFERROR(SUMPRODUCT(('Cost Tracking'!$A$4:$A$50=A7)*'Cost Tracking'!$F$4:$F$50*'Cost Tracking'!$J$4:$J$50)/SUMIF('Cost Tracking'!$A$4:$A$50,A7,'Cost Tracking'!$F$4:$F$50),0) | H7: =SUMIF('Cost Tracking'!$A$4:$A$50,A7,'Cost Tracking'!$K$4:$K$50)
A8: 05 | B8: Metals | C8: =SUMIF('Cost Tracking'!$A$4:$A$50,A8,'Cost Tracking'!$F$4:$F$50) | D8: =SUMIF('Cost Tracking'!$A$4:$A$50,A8,'Cost Tracking'!$G$4:$G$50) | E8: =SUMIF('Cost Tracking'!$A$4:$A$50,A8,'Cost Tracking'!$H$4:$H$50) | F8: =SUMIF('Cost Tracking'!$A$4:$A$50,A8,'Cost Tracking'!$I$4:$I$50) | G8: =IFERROR(SUMPRODUCT(('Cost Tracking'!$A$4:$A$50=A8)*'Cost Tracking'!$F$4:$F$50*'Cost Tracking'!$J$4:$J$50)/SUMIF('Cost Tracking'!$A$4:$A$50,A8,'Cost Tracking'!$F$4:$F$50),0) | H8: =SUMIF('Cost Tracking'!$A$4:$A$50,A8,'Cost Tracking'!$K$4:$K$50)
A9: 06 | B9: Wood, Plastics, and Composites | C9: =SUMIF('Cost Tracking'!$A$4:$A$50,A9,'Cost Tracking'!$F$4:$F$50) | D9: =SUMIF('Cost Tracking'!$A$4:$A$50,A9,'Cost Tracking'!$G$4:$G$50) | E9: =SUMIF('Cost Tracking'!$A$4:$A$50,A9,'Cost Tracking'!$H$4:$H$50) | F9: =SUMIF('Cost Tracking'!$A$4:$A$50,A9,'Cost Tracking'!$I$4:$I$50) | G9: =IFERROR(SUMPRODUCT(('Cost Tracking'!$A$4:$A$50=A9)*'Cost Tracking'!$F$4:$F$50*'Cost Tracking'!$J$4:$J$50)/SUMIF('Cost Tracking'!$A$4:$A$50,A9,'Cost Tracking'!$F$4:$F$50),0) | H9: =SUMIF('Cost Tracking'!$A$4:$A$50,A9,'Cost Tracking'!$K$4:$K$50)
A10: 07 | B10: Thermal and Moisture Protection | C10: =SUMIF('Cost Tracking'!$A$4:$A$50,A10,'Cost Tracking'!$F$4:$F$50) | D10: =SUMIF('Cost Tracking'!$A$4:$A$50,A10,'Cost Tracking'!$G$4:$G$50) | E10: =SUMIF('Cost Tracking'!$A$4:$A$50,A10,'Cost Tracking'!$H$4:$H$50) | F10: =SUMIF('Cost Tracking'!$A$4:$A$50,A10,'Cost Tracking'!$I$4:$I$50) | G10: =IFERROR(SUMPRODUCT(('Cost Tracking'!$A$4:$A$50=A10)*'Cost Tracking'!$F$4:$F$50*'Cost Tracking'!$J$4:$J$50)/SUMIF('Cost Tracking'!$A$4:$A$50,A10,'Cost Tracking'!$F$4:$F$50),0) | H10: =SUMIF('Cost Tracking'!$A$4:$A$50,A10,'Cost Tracking'!$K$4:$K$50)
A11: 08 | B11: Openings | C11: =SUMIF('Cost Tracking'!$A$4:$A$50,A11,'Cost Tracking'!$F$4:$F$50) | D11: =SUMIF('Cost Tracking'!$A$4:$A$50,A11,'Cost Tracking'!$G$4:$G$50) | E11: =SUMIF('Cost Tracking'!$A$4:$A$50,A11,'Cost Tracking'!$H$4:$H$50) | F11: =SUMIF('Cost Tracking'!$A$4:$A$50,A11,'Cost Tracking'!$I$4:$I$50) | G11: =IFERROR(SUMPRODUCT(('Cost Tracking'!$A$4:$A$50=A11)*'Cost Tracking'!$F$4:$F$50*'Cost Tracking'!$J$4:$J$50)/SUMIF('Cost Tracking'!$A$4:$A$50,A11,'Cost Tracking'!$F$4:$F$50),0) | H11: =SUMIF('Cost Tracking'!$A$4:$A$50,A11,'Cost Tracking'!$K$4:$K$50)
A12: 09 | B12: Finishes | C12: =SUMIF('Cost Tracking'!$A$4:$A$50,A12,'Cost Tracking'!$F$4:$F$50) | D12: =SUMIF('Cost Tracking'!$A$4:$A$50,A12,'Cost Tracking'!$G$4:$G$50) | E12: =SUMIF('Cost Tracking'!$A$4:$A$50,A12,'Cost Tracking'!$H$4:$H$50) | F12: =SUMIF('Cost Tracking'!$A$4:$A$50,A12,'Cost Tracking'!$I$4:$I$50) | G12: =IFERROR(SUMPRODUCT(('Cost Tracking'!$A$4:$A$50=A12)*'Cost Tracking'!$F$4:$F$50*'Cost Tracking'!$J$4:$J$50)/SUMIF('Cost Tracking'!$A$4:$A$50,A12,'Cost Tracking'!$F$4:$F$50),0) | H12: =SUMIF('Cost Tracking'!$A$4:$A$50,A12,'Cost Tracking'!$K$4:$K$50)
A13: 10 | B13: Specialties | C13: =SUMIF('Cost Tracking'!$A$4:$A$50,A13,'Cost Tracking'!$F$4:$F$50) | D13: =SUMIF('Cost Tracking'!$A$4:$A$50,A13,'Cost Tracking'!$G$4:$G$50) | E13: =SUMIF('Cost Tracking'!$A$4:$A$50,A13,'Cost Tracking'!$H$4:$H$50) | F13: =SUMIF('Cost Tracking'!$A$4:$A$50,A13,'Cost Tracking'!$I$4:$I$50) | G13: =IFERROR(SUMPRODUCT(('Cost Tracking'!$A$4:$A$50=A13)*'Cost Tracking'!$F$4:$F$50*'Cost Tracking'!$J$4:$J$50)/SUMIF('Cost Tracking'!$A$4:$A$50,A13,'Cost Tracking'!$F$4:$F$50),0) | H13: =SUMIF('Cost Tracking'!$A$4:$A$50,A13,'Cost Tracking'!$K$4:$K$50)
A14: 21 | B14: Fire Suppression | C14: =SUMIF('Cost Tracking'!$A$4:$A$50,A14,'Cost Tracking'!$F$4:$F$50) | D14: =SUMIF('Cost Tracking'!$A$4:$A$50,A14,'Cost Tracking'!$G$4:$G$50) | E14: =SUMIF('Cost Tracking'!$A$4:$A$50,A14,'Cost Tracking'!$H$4:$H$50) | F14: =SUMIF('Cost Tracking'!$A$4:$A$50,A14,'Cost Tracking'!$I$4:$I$50) | G14: =IFERROR(SUMPRODUCT(('Cost Tracking'!$A$4:$A$50=A14)*'Cost Tracking'!$F$4:$F$50*'Cost Tracking'!$J$4:$J$50)/SUMIF('Cost Tracking'!$A$4:$A$50,A14,'Cost Tracking'!$F$4:$F$50),0) | H14: =SUMIF('Cost Tracking'!$A$4:$A$50,A14,'Cost Tracking'!$K$4:$K$50)
A15: 22 | B15: Plumbing | C15: =SUMIF('Cost Tracking'!$A$4:$A$50,A15,'Cost Tracking'!$F$4:$F$50) | D15: =SUMIF('Cost Tracking'!$A$4:$A$50,A15,'Cost Tracking'!$G$4:$G$50) | E15: =SUMIF('Cost Tracking'!$A$4:$A$50,A15,'Cost Tracking'!$H$4:$H$50) | F15: =SUMIF('Cost Tracking'!$A$4:$A$50,A15,'Cost Tracking'!$I$4:$I$50) | G15: =IFERROR(SUMPRODUCT(('Cost Tracking'!$A$4:$A$50=A15)*'Cost Tracking'!$F$4:$F$50*'Cost Tracking'!$J$4:$J$50)/SUMIF('Cost Tracking'!$A$4:$A$50,A15,'Cost Tracking'!$F$4:$F$50),0) | H15: =SUMIF('Cost Tracking'!$A$4:$A$50,A15,'Cost Tracking'!$K$4:$K$50)
... A20: 33 | B20: Utilities | C20: =SUMIF('Cost Tracking'!$A$4:$A$50,A20,'Cost Tracking'!$F$4:$F$50) | D20: =SUMIF('Cost Tracking'!$A$4:$A$50,A20,'Cost Tracking'!$G$4:$G$50) | E20: =SUMIF('Cost Tracking'!$A$4:$A$50,A20,'Cost Tracking'!$H$4:$H$50) | F20: =SUMIF('Cost Tracking'!$A$4:$A$50,A20,'Cost Tracking'!$I$4:$I$50) | G20: =IFERROR(SUMPRODUCT(('Cost Tracking'!$A$4:$A$50=A20)*'Cost Tracking'!$F$4:$F$50*'Cost Tracking'!$J$4:$J$50)/SUMIF('Cost Tracking'!$A$4:$A$50,A20,'Cost Tracking'!$F$4:$F$50),0) | H20: =SUMIF('Cost Tracking'!$A$4:$A$50,A20,'Cost Tracking'!$K$4:$K$50)
B22: TOTALS | C22: =SUM(C4:C20) | D22: =SUM(D4:D20) | E22: =SUM(E4:E20) | F22: =SUM(F4:F20) | G22: =IFERROR(SUMPRODUCT(C4:C20,G4:G20)/SUM(C4:C20),0) | H22: =SUM(H4:H20)

Sheet Dashboard
A1: Job Dashboard
A2: Auto-calculated from Job Info and Cost Tracking. Update those tabs - this one stays in sync.
A4: Job Summary
A5: Contract Amount | D5: ='Job Info'!D4
A6: Total Budget | D6: =SUM('Cost Tracking'!F4:F50)
A7: Total Committed | D7: =SUM('Cost Tracking'!G4:G50)
A8: Total Actual to Date | D8: =SUM('Cost Tracking'!H4:H50)
A9: Total Variance (Budget - Actual) | D9: =SUM('Cost Tracking'!F4:F50)-SUM('Cost Tracking'!H4:H50)
A10: Weighted % Complete | D10: =IFERROR(SUMPRODUCT('Cost Tracking'!F4:F50,'Cost Tracking'!J4:J50)/SUM('Cost Tracking'!F4:F50),0)
A11: Projected Cost at Completion | D11: =IFERROR(SUM('Cost Tracking'!H4:H50)/IFERROR(SUMPRODUCT('Cost Tracking'!F4:F50,'Cost Tracking'!J4:J50)/SUM('Cost Tracking'!F4:F50),0),SUM('Cost Tracking'!F4:F50))
A12: Projected Profit | D12: ='Job Info'!D4-IFERROR(SUM('Cost Tracking'!H4:H50)/IFERROR(SUMPRODUCT('Cost Tracking'!F4:F50,'Cost Tracking'!J4:J50)/SUM('Cost Tracking'!F4:F50),0),SUM('Cost Tracking'!F4:F50))
A13: Profit Margin % | D13: =IFERROR(('Job Info'!D4-IFERROR(SUM('Cost Tracking'!H4:H50)/IFERROR(SUMPRODUCT('Cost Tracking'!F4:F50,'Cost Tracking'!J4:J50)/SUM('Cost Tracking'!F4:F50),0),SUM('Cost Tracking'!F4:F50)))/'Job Info'!D4,0)
A16: Per-Division Breakdown
A17: Div | B17: Division Name | C17: Budget | D17: Actual | E17: Variance | F17: % Complete
A18: 01 | B18: General Requirements | C18: =SUMIF('Cost Tracking'!$A$4:$A$50,A18,'Cost Tracking'!$F$4:$F$50) | D18: =SUMIF('Cost Tracking'!$A$4:$A$50,A18,'Cost Tracking'!$H$4:$H$50) | E18: =SUMIF('Cost Tracking'!$A$4:$A$50,A18,'Cost Tracking'!$I$4:$I$50) | F18: =IFERROR(SUMPRODUCT(('Cost Tracking'!$A$4:$A$50=A18)*'Cost Tracking'!$F$4:$F$50*'Cost Tracking'!$J$4:$J$50)/SUMIF('Cost Tracking'!$A$4:$A$50,A18,'Cost Tracking'!$F$4:$F$50),0)
A19: 02 | B19: Existing Conditions | C19: =SUMIF('Cost Tracking'!$A$4:$A$50,A19,'Cost Tracking'!$F$4:$F$50) | D19: =SUMIF('Cost Tracking'!$A$4:$A$50,A19,'Cost Tracking'!$H$4:$H$50) | E19: =SUMIF('Cost Tracking'!$A$4:$A$50,A19,'Cost Tracking'!$I$4:$I$50) | F19: =IFERROR(SUMPRODUCT(('Cost Tracking'!$A$4:$A$50=A19)*'Cost Tracking'!$F$4:$F$50*'Cost Tracking'!$J$4:$J$50)/SUMIF('Cost Tracking'!$A$4:$A$50,A19,'Cost Tracking'!$F$4:$F$50),0)
A20: 03 | B20: Concrete | C20: =SUMIF('Cost Tracking'!$A$4:$A$50,A20,'Cost Tracking'!$F$4:$F$50) | D20: =SUMIF('Cost Tracking'!$A$4:$A$50,A20,'Cost Tracking'!$H$4:$H$50) | E20: =SUMIF('Cost Tracking'!$A$4:$A$50,A20,'Cost Tracking'!$I$4:$I$50) | F20: =IFERROR(SUMPRODUCT(('Cost Tracking'!$A$4:$A$50=A20)*'Cost Tracking'!$F$4:$F$50*'Cost Tracking'!$J$4:$J$50)/SUMIF('Cost Tracking'!$A$4:$A$50,A20,'Cost Tracking'!$F$4:$F$50),0)
A21: 04 | B21: Masonry | C21: =SUMIF('Cost Tracking'!$A$4:$A$50,A21,'Cost Tracking'!$F$4:$F$50) | D21: =SUMIF('Cost Tracking'!$A$4:$A$50,A21,'Cost Tracking'!$H$4:$H$50) | E21: =SUMIF('Cost Tracking'!$A$4:$A$50,A21,'Cost Tracking'!$I$4:$I$50) | F21: =IFERROR(SUMPRODUCT(('Cost Tracking'!$A$4:$A$50=A21)*'Cost Tracking'!$F$4:$F$50*'Cost Tracking'!$J$4:$J$50)/SUMIF('Cost Tracking'!$A$4:$A$50,A21,'Cost Tracking'!$F$4:$F$50),0)
A22: 05 | B22: Metals | C22: =SUMIF('Cost Tracking'!$A$4:$A$50,A22,'Cost Tracking'!$F$4:$F$50) | D22: =SUMIF('Cost Tracking'!$A$4:$A$50,A22,'Cost Tracking'!$H$4:$H$50) | E22: =SUMIF('Cost Tracking'!$A$4:$A$50,A22,'Cost Tracking'!$I$4:$I$50) | F22: =IFERROR(SUMPRODUCT(('Cost Tracking'!$A$4:$A$50=A22)*'Cost Tracking'!$F$4:$F$50*'Cost Tracking'!$J$4:$J$50)/SUMIF('Cost Tracking'!$A$4:$A$50,A22,'Cost Tracking'!$F$4:$F$50),0)
A23: 06 | B23: Wood, Plastics, and Composites | C23: =SUMIF('Cost Tracking'!$A$4:$A$50,A23,'Cost Tracking'!$F$4:$F$50) | D23: =SUMIF('Cost Tracking'!$A$4:$A$50,A23,'Cost Tracking'!$H$4:$H$50) | E23: =SUMIF('Cost Tracking'!$A$4:$A$50,A23,'Cost Tracking'!$I$4:$I$50) | F23: =IFERROR(SUMPRODUCT(('Cost Tracking'!$A$4:$A$50=A23)*'Cost Tracking'!$F$4:$F$50*'Cost Tracking'!$J$4:$J$50)/SUMIF('Cost Tracking'!$A$4:$A$50,A23,'Cost Tracking'!$F$4:$F$50),0)
A24: 07 | B24: Thermal and Moisture Protection | C24: =SUMIF('Cost Tracking'!$A$4:$A$50,A24,'Cost Tracking'!$F$4:$F$50) | D24: =SUMIF('Cost Tracking'!$A$4:$A$50,A24,'Cost Tracking'!$H$4:$H$50) | E24: =SUMIF('Cost Tracking'!$A$4:$A$50,A24,'Cost Tracking'!$I$4:$I$50) | F24: =IFERROR(SUMPRODUCT(('Cost Tracking'!$A$4:$A$50=A24)*'Cost Tracking'!$F$4:$F$50*'Cost Tracking'!$J$4:$J$50)/SUMIF('Cost Tracking'!$A$4:$A$50,A24,'Cost Tracking'!$F$4:$F$50),0)
A25: 08 | B25: Openings | C25: =SUMIF('Cost Tracking'!$A$4:$A$50,A25,'Cost Tracking'!$F$4:$F$50) | D25: =SUMIF('Cost Tracking'!$A$4:$A$50,A25,'Cost Tracking'!$H$4:$H$50) | E25: =SUMIF('Cost Tracking'!$A$4:$A$50,A25,'Cost Tracking'!$I$4:$I$50) | F25: =IFERROR(SUMPRODUCT(('Cost Tracking'!$A$4:$A$50=A25)*'Cost Tracking'!$F$4:$F$50*'Cost Tracking'!$J$4:$J$50)/SUMIF('Cost Tracking'!$A$4:$A$50,A25,'Cost Tracking'!$F$4:$F$50),0)
A26: 09 | B26: Finishes | C26: =SUMIF('Cost Tracking'!$A$4:$A$50,A26,'Cost Tracking'!$F$4:$F$50) | D26: =SUMIF('Cost Tracking'!$A$4:$A$50,A26,'Cost Tracking'!$H$4:$H$50) | E26: =SUMIF('Cost Tracking'!$A$4:$A$50,A26,'Cost Tracking'!$I$4:$I$50) | F26: =IFERROR(SUMPRODUCT(('Cost Tracking'!$A$4:$A$50=A26)*'Cost Tracking'!$F$4:$F$50*'Cost Tracking'!$J$4:$J$50)/SUMIF('Cost Tracking'!$A$4:$A$50,A26,'Cost Tracking'!$F$4:$F$50),0)
A27: 10 | B27: Specialties | C27: =SUMIF('Cost Tracking'!$A$4:$A$50,A27,'Cost Tracking'!$F$4:$F$50) | D27: =SUMIF('Cost Tracking'!$A$4:$A$50,A27,'Cost Tracking'!$H$4:$H$50) | E27: =SUMIF('Cost Tracking'!$A$4:$A$50,A27,'Cost Tracking'!$I$4:$I$50) | F27: =IFERROR(SUMPRODUCT(('Cost Tracking'!$A$4:$A$50=A27)*'Cost Tracking'!$F$4:$F$50*'Cost Tracking'!$J$4:$J$50)/SUMIF('Cost Tracking'!$A$4:$A$50,A27,'Cost Tracking'!$F$4:$F$50),0)
A28: 21 | B28: Fire Suppression | C28: =SUMIF('Cost Tracking'!$A$4:$A$50,A28,'Cost Tracking'!$F$4:$F$50) | D28: =SUMIF('Cost Tracking'!$A$4:$A$50,A28,'Cost Tracking'!$H$4:$H$50) | E28: =SUMIF('Cost Tracking'!$A$4:$A$50,A28,'Cost Tracking'!$I$4:$I$50) | F28: =IFERROR(SUMPRODUCT(('Cost Tracking'!$A$4:$A$50=A28)*'Cost Tracking'!$F$4:$F$50*'Cost Tracking'!$J$4:$J$50)/SUMIF('Cost Tracking'!$A$4:$A$50,A28,'Cost Tracking'!$F$4:$F$50),0)
A29: 22 | B29: Plumbing | C29: =SUMIF('Cost Tracking'!$A$4:$A$50,A29,'Cost Tracking'!$F$4:$F$50) | D29: =SUMIF('Cost Tracking'!$A$4:$A$50,A29,'Cost Tracking'!$H$4:$H$50) | E29: =SUMIF('Cost Tracking'!$A$4:$A$50,A29,'Cost Tracking'!$I$4:$I$50) | F29: =IFERROR(SUMPRODUCT(('Cost Tracking'!$A$4:$A$50=A29)*'Cost Tracking'!$F$4:$F$50*'Cost Tracking'!$J$4:$J$50)/SUMIF('Cost Tracking'!$A$4:$A$50,A29,'Cost Tracking'!$F$4:$F$50),0)
... A34: 33 | B34: Utilities | C34: =SUMIF('Cost Tracking'!$A$4:$A$50,A34,'Cost Tracking'!$F$4:$F$50) | D34: =SUMIF('Cost Tracking'!$A$4:$A$50,A34,'Cost Tracking'!$H$4:$H$50) | E34: =SUMIF('Cost Tracking'!$A$4:$A$50,A34,'Cost Tracking'!$I$4:$I$50) | F34: =IFERROR(SUMPRODUCT(('Cost Tracking'!$A$4:$A$50=A34)*'Cost Tracking'!$F$4:$F$50*'Cost Tracking'!$J$4:$J$50)/SUMIF('Cost Tracking'!$A$4:$A$50,A34,'Cost Tracking'!$F$4:$F$50),0)
